Workbook
Name _lst_r_地方财政预算表2015年全省汇总_10_科目编码名称: [1]_ESList!$A$1:$A$27
Name 专项收入年初预算数: #REF!
Name 专项收入全年预计数: #REF!
Name 专项收入年初预算数: #REF!
Name 专项收入全年预计数: #REF!
Name 专项收入年初预算数: #REF!
Name 专项收入全年预计数: #REF!
Name 专项收入年初预算数: #REF!
Name 专项收入全年预计数: #REF!
Name 专项收入年初预算数: #REF!
Name 专项收入全年预计数: #REF!
Name 专项收入年初预算数: #REF!
Name 专项收入全年预计数: #REF!
Name 专项收入年初预算数: #REF!
Name 专项收入全年预计数: #REF!
Name 专项收入年初预算数: #REF!
Name 专项收入全年预计数: #REF!
Name 专项收入年初预算数: #REF!
Name 专项收入全年预计数: #REF!
Name 专项收入年初预算数: #REF!
Name 专项收入全年预计数: #REF!
Name 专项收入年初预算数: #REF!
Name 专项收入全年预计数: #REF!
Name 专项收入年初预算数: #REF!
Name 专项收入全年预计数: #REF!
Name 专项收入年初预算数: #REF!
Name 专项收入全年预计数: #REF!
Name 专项收入年初预算数: #REF!
Name 专项收入全年预计数: #REF!
Name _lst_r_地方财政预算表2015年全省汇总_10_科目编码名称: [3]_ESList!$A$1:$A$27
Name 专项收入年初预算数: #REF!
Name 专项收入全年预计数: #REF!
Name _lst_r_地方财政预算表2015年全省汇总_10_科目编码名称: [3]_ESList!$A$1:$A$27
Name 专项收入年初预算数: #REF!
Name 专项收入全年预计数: #REF!
Name _lst_r_地方财政预算表2015年全省汇总_10_科目编码名称: [3]_ESList!$A$1:$A$27
Name 专项收入年初预算数: #REF!
Name 专项收入全年预计数: #REF!
Name _lst_r_地方财政预算表2015年全省汇总_10_科目编码名称: [4]_ESList!$A$1:$A$27
Name 专项收入年初预算数: #REF!
Name 专项收入全年预计数: #REF!
Name _lst_r_地方财政预算表2015年全省汇总_10_科目编码名称: [3]_ESList!$A$1:$A$27
Name 专项收入年初预算数: #REF!
Name 专项收入全年预计数: #REF!
Name _lst_r_地方财政预算表2015年全省汇总_10_科目编码名称: [3]_ESList!$A$1:$A$27
Name 专项收入年初预算数: #REF!
Name 专项收入全年预计数: #REF!
Name 专项收入年初预算数: #REF!
Name 专项收入全年预计数: #REF!
Name 专项收入年初预算数: #REF!
Name 专项收入全年预计数: #REF!
Name 专项收入年初预算数: #REF!
Name 专项收入全年预计数: #REF!
Name 专项收入年初预算数: #REF!
Name 专项收入全年预计数: #REF!
Name 专项收入年初预算数: #REF!
Name 专项收入全年预计数: #REF!
Name 专项收入年初预算数: #REF!
Name 专项收入全年预计数: #REF!
Name 专项收入年初预算数: #REF!

Sheet 封面
C1: 会议资料 妥善保存
B3: 丽 江 市
B4: =YEAR(B7)-1&"年地方财政预算执行情况和"&YEAR(B7)&"年地方财政预算（草案）" -> 2025年地方财政预算执行情况和2026年地方财政预算（草案） | E4: 3
E5: 8
B6: 丽江市财政局编制 | E6: 10
B7: 46037 | E7: 22
E8: 23
E9: 24
E10: 25
E11: 26
E12: 28
E13: 29
E14: 30
E15: 31
E16: 32
E17: 33
E18: 34
E19: 35
... E50: 94

Sheet 目录
A1: 目 录 | B1: 非打印区域（过程）
A3: =B3&"、"&C3&REPT(".",75-LENB(B3&"、"&C3&E3))&E3 -> 表一、2025年丽江市一般公共预算收支情况表..................................1 | B3: 表一 | C3: 2025年丽江市一般公共预算收支情况表 | D3: =LEN(C3) -> 19 | E3: 1
A4: =B4&"、"&C4&REPT(".",75-LENB(B4&"、"&C4&E4))&E4 -> 表二、2025年丽江市一般公共预算支出执行情况表..............................3 | B4: 表二 | C4: 2025年丽江市一般公共预算支出执行情况表 | D4: =LEN(C4) -> 21 | E4: 3
A5: =B5&"、"&C5&REPT(".",75-LENB(B5&"、"&C5&E5))&E5 -> 表三、2025年市本级一般公共预算收支情况表..................................8 | B5: 表三 | C5: 2025年市本级一般公共预算收支情况表 | D5: =LEN(C5) -> 19 | E5: 8
A6: =B6&"、"&C6&REPT(".",75-LENB(B6&"、"&C6&E6))&E6 -> 表四、2025年市本级一般公共预算支出执行情况表.............................10 | B6: 表四 | C6: 2025年市本级一般公共预算支出执行情况表 | D6: =LEN(C6) -> 21 | E6: 10
A7: =B7&"、"&C7&REPT(".",75-LENB(B7&"、"&C7&E7))&E7 -> 表五、2025年市本级预备费安排情况表.......................................22 | B7: 表五 | C7: 2025年市本级预备费安排情况表 | D7: =LEN(C7) -> 16 | E7: 22
A8: =B8&"、"&C8&REPT(".",75-LENB(B8&"、"&C8&E8))&E8 -> 表六、2025年丽江市政府性基金预算收入执行情况表...........................23 | B8: 表六 | C8: 2025年丽江市政府性基金预算收入执行情况表 | D8: =LEN(C8) -> 22 | E8: 23
A9: =B9&"、"&C9&REPT(".",75-LENB(B9&"、"&C9&E9))&E9 -> 表七、2025年丽江市政府性基金预算支出执行情况表...........................24 | B9: 表七 | C9: 2025年丽江市政府性基金预算支出执行情况表 | D9: =LEN(C9) -> 22 | E9: 24
A10: =B10&"、"&C10&REPT(".",75-LENB(B10&"、"&C10&E10))&E10 -> 表八、2025年市本级政府性基金预算收入执行情况表...........................25 | B10: 表八 | C10: 2025年市本级政府性基金预算收入执行情况表 | D10: =LEN(C10) -> 22 | E10: 25
A11: =B11&"、"&C11&REPT(".",75-LENB(B11&"、"&C11&E11))&E11 -> 表九、2025年市本级政府性基金预算支出执行情况表...........................26 | B11: 表九 | C11: 2025年市本级政府性基金预算支出执行情况表 | D11: =LEN(C11) -> 22 | E11: 26
A12: =B12&"、"&C12&REPT(".",75-LENB(B12&"、"&C12&E12))&E12 -> 表十、2025年丽江市国有资本经营预算收入执行情况表.........................28 | B12: 表十 | C12: 2025年丽江市国有资本经营预算收入执行情况表 | D12: =LEN(C12) -> 23 | E12: 28
A13: =B13&"、"&C13&REPT(".",75-LENB(B13&"、"&C13&E13))&E13 -> 表十一、2025年丽江市国有资本经营预算支出执行情况表.......................29 | B13: 表十一 | C13: 2025年丽江市国有资本经营预算支出执行情况表 | D13: =LEN(C13) -> 23 | E13: 29
A14: =B14&"、"&C14&REPT(".",75-LENB(B14&"、"&C14&E14))&E14 -> 表十二、2025年市本级国有资本经营预算收入执行情况表.......................30 | B14: 表十二 | C14: 2025年市本级国有资本经营预算收入执行情况表 | D14: =LEN(C14) -> 23 | E14: 30
... A20: =B20&"、"&C20&REPT(".",75-LENB(B20&"、"&C20&E20))&E20 -> 表十八、2025年市本级社会保险基金预算支出执行情况表.......................36 | B20: 表十八 | C20: 2025年市本级社会保险基金预算支出执行情况表 | D20: =LEN(C20) -> 23 | E20: 36
A21: =B21&" "&C21&REPT(".",75-LENB(B21&"、"&C21&E21))&E21 -> 表十九 2025年市本级社会保险基金预算结余执行情况表.......................37 | B21: 表十九 | C21: 2025年市本级社会保险基金预算结余执行情况表 | D21: =LEN(C21) -> 23 | E21: 37
A22: =B22&"、"&C22&REPT(".",75-LENB(B22&"、"&C22&E22))&E22 -> 表二十、2026年丽江市一般公共预算收支情况表...............................38 | B22: 表二十 | C22: 2026年丽江市一般公共预算收支情况表 | D22: =LEN(C22) -> 19 | E22: 38
A23: =B23&"、"&C23&REPT(".",75-LENB(B23&"、"&C23&E23))&E23 -> 表二十一、2026年丽江市一般公共预算支出情况表.............................40 | B23: 表二十一 | C23: 2026年丽江市一般公共预算支出情况表 | D23: =LEN(C23) -> 19 | E23: 40
A24: =B24&"、"&C24&REPT(".",75-LENB(B24&"、"&C24&E24))&E24 -> 表二十二、2026年市本级一般公共预算收支情况表.............................45 | B24: 表二十二 | C24: 2026年市本级一般公共预算收支情况表 | D24: =LEN(C24) -> 19 | E24: 45
A25: =B25&"、"&C25&REPT(".",75-LENB(B25&"、"&C25&E25))&E25 -> 表二十三、2026年市本级一般公共预算支出情况表.............................47 | B25: 表二十三 | C25: 2026年市本级一般公共预算支出情况表 | D25: =LEN(C25) -> 19 | E25: 47
A26: =B26&"、"&C26&REPT(".",75-LENB(B26&"、"&C26&E26))&E26 -> 表二十四、2026年丽江市市本级一般公共预算支出表(市对下转移支付项目).......61 | B26: 表二十四 | C26: 2026年丽江市市本级一般公共预算支出表(市对下转移支付项目) | D26: =LEN(C26) -> 31 | E26: 61
A27: =B27&"、"&C27&REPT(".",75-LENB(B27&"、"&C27&E27))&E27 -> 表二十五、2026年丽江市分地区税收返还和转移支付预算表.....................64 | B27: 表二十五 | C27: 2026年丽江市分地区税收返还和转移支付预算表 | D27: =LEN(C27) -> 23 | E27: 64
A28: =B28&"、"&C28&REPT(".",75-LENB(B28&"、"&C28&E28))&E28 -> 表二十六、2026年丽江市市本级一般公共预算政府预算经济分类表(基本支出).....65 | B28: 表二十六 | C28: 2026年丽江市市本级一般公共预算政府预算经济分类表(基本支出) | D28: =LEN(C28) -> 32 | E28: 65
A29: =B29&"、"&C29&REPT(".",75-LENB(B29&"、"&C29&E29))&E29 -> 表二十七、2026年丽江市市本级一般公共预算重点项目情况表...................66 | B29: 表二十七 | C29: 2026年丽江市市本级一般公共预算重点项目情况表 | D29: =LEN(C29) -> 24 | E29: 66
A30: =B30&"、"&C30&REPT(".",75-LENB(B30&"、"&C30&E30))&E30 -> 表二十八、2026年丽江市政府性基金预算收入情况表...........................67 | B30: 表二十八 | C30: 2026年丽江市政府性基金预算收入情况表 | D30: =LEN(C30) -> 20 | E30: 67
A31: =B31&"、"&C31&REPT(".",75-LENB(B31&"、"&C31&E31))&E31 -> 表二十九、2026年丽江市政府性基金预算支出情况表...........................68 | B31: 表二十九 | C31: 2026年丽江市政府性基金预算支出情况表 | D31: =LEN(C31) -> 20 | E31: 68
A32: =B32&"、"&C32&REPT(".",75-LENB(B32&"、"&C32&E32))&E32 -> 表三十、2026年市本级政府性基金预算收入情况表.............................69 | B32: 表三十 | C32: 2026年市本级政府性基金预算收入情况表 | D32: =LEN(C32) -> 20 | E32: 69
A33: =B33&"、"&C33&REPT(".",75-LENB(B33&"、"&C33&E33))&E33 -> 表三十一、2026年市本级政府性基金预算支出情况表...........................70 | B33: 表三十一 | C33: 2026年市本级政府性基金预算支出情况表 | D33: =LEN(C33) -> 20 | E33: 70
... A50: =B50&"、"&C50&REPT(".",75-LENB(B50&"、"&C50&E50))&E50 -> 表四十八、丽江市2025年地方政府债务限额分地区情况表.......................94 | B50: 表四十八 | C50: 丽江市2025年地方政府债务限额分地区情况表 | D50: =LEN(C50) -> 22 | E50: 94

Sheet 01-1 
B1: 2025年丽江市一般公共预算收支情况表
B2: 表一 | H2: 单位：万元
A3: 科目编码 | B3: 项目 | C3: 2024年决算数 | D3: 2025年 | G3: 比较
D4: 预算数 | E4: 3 | F4: 执行数 | G4: 比2024年决算数增长% | H4: 完成2025年预算数的% | I4: 打印
A5: 101 | B5: 一、税收收入 | C5: =SUM(C6:C20) -> 250422 | D5: =SUM(D6:D20) -> 292946 | E5: 8 | F5: =SUM(F6:F20) -> 288755 | G5: =IFERROR((F5-C5)/C5,"") -> 0.15307361 | H5: =IFERROR(F5/D5,"") -> 0.98569361 | I5: =IF(LEN(A5)=3,"是",IF(B5<>"",IF(SUM(C5:F5)<>0,"是","否"),"是")) -> 是
A6: 10101 | B6: 增值税 | C6: 114306 | D6: 126500 | E6: 10 | F6: 118670 | G6: =IFERROR((F6-C6)/C6,"") -> 0.038178223 | H6: =IFERROR(F6/D6,"") -> 0.93810277 | I6: =IF(LEN(A6)=3,"是",IF(B6<>"",IF(SUM(C6:F6)<>0,"是","否"),"是")) -> 是
A7: 10104 | B7: 企业所得税 | C7: 12462 | D7: 11520 | E7: 22 | F7: 11823 | G7: =IFERROR((F7-C7)/C7,"") -> -0.051275879 | H7: =IFERROR(F7/D7,"") -> 1.0263021 | I7: =IF(LEN(A7)=3,"是",IF(B7<>"",IF(SUM(C7:F7)<>0,"是","否"),"是")) -> 是
A8: 10106 | B8: 个人所得税 | C8: 4161 | D8: 3840 | E8: 23 | F8: 4342 | G8: =IFERROR((F8-C8)/C8,"") -> 0.043499159 | H8: =IFERROR(F8/D8,"") -> 1.1307292 | I8: =IF(LEN(A8)=3,"是",IF(B8<>"",IF(SUM(C8:F8)<>0,"是","否"),"是")) -> 是
A9: 10107 | B9: 资源税 | C9: 2752 | D9: 33246 | E9: 24 | F9: 28214 | G9: =IFERROR((F9-C9)/C9,"") -> 9.2521802 | H9: =IFERROR(F9/D9,"") -> 0.84864345 | I9: =IF(LEN(A9)=3,"是",IF(B9<>"",IF(SUM(C9:F9)<>0,"是","否"),"是")) -> 是
A10: 10109 | B10: 城市维护建设税 | C10: 14498 | D10: 15000 | E10: 25 | F10: 14184 | G10: =IFERROR((F10-C10)/C10,"") -> -0.02165816 | H10: =IFERROR(F10/D10,"") -> 0.9456 | I10: =IF(LEN(A10)=3,"是",IF(B10<>"",IF(SUM(C10:F10)<>0,"是","否"),"是")) -> 是
A11: 10110 | B11: 房产税 | C11: 14253 | D11: 14500 | E11: 26 | F11: 13926 | G11: =IFERROR((F11-C11)/C11,"") -> -0.022942538 | H11: =IFERROR(F11/D11,"") -> 0.96041379 | I11: =IF(LEN(A11)=3,"是",IF(B11<>"",IF(SUM(C11:F11)<>0,"是","否"),"是")) -> 是
A12: 10111 | B12: 印花税 | C12: 2994 | D12: 3200 | E12: 28 | F12: 2757 | G12: =IFERROR((F12-C12)/C12,"") -> -0.079158317 | H12: =IFERROR(F12/D12,"") -> 0.8615625 | I12: =IF(LEN(A12)=3,"是",IF(B12<>"",IF(SUM(C12:F12)<>0,"是","否"),"是")) -> 是
A13: 10112 | B13: 城镇土地使用税 | C13: 9799 | D13: 9800 | E13: 29 | F13: 10454 | G13: =IFERROR((F13-C13)/C13,"") -> 0.066843555 | H13: =IFERROR(F13/D13,"") -> 1.0667347 | I13: =IF(LEN(A13)=3,"是",IF(B13<>"",IF(SUM(C13:F13)<>0,"是","否"),"是")) -> 是
A14: 10113 | B14: 土地增值税 | C14: 13119 | D14: 13000 | E14: 30 | F14: 10748 | G14: =IFERROR((F14-C14)/C14,"") -> -0.18073024 | H14: =IFERROR(F14/D14,"") -> 0.82676923 | I14: =IF(LEN(A14)=3,"是",IF(B14<>"",IF(SUM(C14:F14)<>0,"是","否"),"是")) -> 是
A15: 10114 | B15: 车船税 | C15: 8014 | D15: 8000 | E15: 31 | F15: 8371 | G15: =IFERROR((F15-C15)/C15,"") -> 0.044547043 | H15: =IFERROR(F15/D15,"") -> 1.046375 | I15: =IF(LEN(A15)=3,"是",IF(B15<>"",IF(SUM(C15:F15)<>0,"是","否"),"是")) -> 是
A16: 10118 | B16: 耕地占用税 | C16: 14219 | D16: 14000 | E16: 32 | F16: 21925 | G16: =IFERROR((F16-C16)/C16,"") -> 0.54195091 | H16: =IFERROR(F16/D16,"") -> 1.5660714 | I16: =IF(LEN(A16)=3,"是",IF(B16<>"",IF(SUM(C16:F16)<>0,"是","否"),"是")) -> 是
A17: 10119 | B17: 契税 | C17: 17992 | D17: 18340 | E17: 33 | F17: 21104 | G17: =IFERROR((F17-C17)/C17,"") -> 0.17296576 | H17: =IFERROR(F17/D17,"") -> 1.1507088 | I17: =IF(LEN(A17)=3,"是",IF(B17<>"",IF(SUM(C17:F17)<>0,"是","否"),"是")) -> 是
... A19: 10121 | B19: 环境保护税 | C19: 1084 | D19: 1000 | E19: 35 | F19: 1259 | G19: =IFERROR((F19-C19)/C19,"") -> 0.16143911 | H19: =IFERROR(F19/D19,"") -> 1.259 | I19: =IF(LEN(A19)=3,"是",IF(B19<>"",IF(SUM(C19:F19)<>0,"是","否"),"是")) -> 是
A20: 10199 | B20: 其他税收收入 | C20: 40 | E20: 36 | F20: 169 | G20: =IFERROR((F20-C20)/C20,"") -> 3.225 | H20: =IFERROR(F20/D20,"") | I20: =IF(LEN(A20)=3,"是",IF(B20<>"",IF(SUM(C20:F20)<>0,"是","否"),"是")) -> 是
A21: 103 | B21: 二、非税收入 | C21: =SUM(C22:C29) -> 316281 | D21: =SUM(D22:D29) -> 302091 | E21: 37 | F21: =SUM(F22:F29) -> 279000 | G21: =IFERROR((F21-C21)/C21,"") -> -0.11787303 | H21: =IFERROR(F21/D21,"") -> 0.92356277 | I21: =IF(LEN(A21)=3,"是",IF(B21<>"",IF(SUM(C21:F21)<>0,"是","否"),"是")) -> 是
A22: 10302 | B22: 专项收入 | C22: 17795 | D22: 25653 | E22: 38 | F22: 14801 | G22: =IFERROR((F22-C22)/C22,"") -> -0.16824951 | H22: =IFERROR(F22/D22,"") -> 0.57696956 | I22: =IF(LEN(A22)=3,"是",IF(B22<>"",IF(SUM(C22:F22)<>0,"是","否"),"是")) -> 是
A23: 10304 | B23: 行政事业性收费收入 | C23: 46437 | D23: 43265 | E23: 40 | F23: 41771 | G23: =IFERROR((F23-C23)/C23,"") -> -0.10048022 | H23: =IFERROR(F23/D23,"") -> 0.96546862 | I23: =IF(LEN(A23)=3,"是",IF(B23<>"",IF(SUM(C23:F23)<>0,"是","否"),"是")) -> 是
A24: 10305 | B24: 罚没收入 | C24: 29964 | D24: 26859 | E24: 45 | F24: 19234 | G24: =IFERROR((F24-C24)/C24,"") -> -0.35809638 | H24: =IFERROR(F24/D24,"") -> 0.71611006 | I24: =IF(LEN(A24)=3,"是",IF(B24<>"",IF(SUM(C24:F24)<>0,"是","否"),"是")) -> 是
A25: 10306 | B25: 国有资本经营收入 | C25: 0 | E25: 47 | G25: =IFERROR((F25-C25)/C25,"") | H25: =IFERROR(F25/D25,"") | I25: =IF(LEN(A25)=3,"是",IF(B25<>"",IF(SUM(C25:F25)<>0,"是","否"),"是")) -> 是
A26: 10307 | B26: 国有资源（资产）有偿使用收入 | C26: 214227 | D26: 198693 | E26: 61 | F26: 194578 | G26: =IFERROR((F26-C26)/C26,"") -> -0.091720465 | H26: =IFERROR(F26/D26,"") -> 0.97928966 | I26: =IF(LEN(A26)=3,"是",IF(B26<>"",IF(SUM(C26:F26)<>0,"是","否"),"是")) -> 是
A27: 10308 | B27: 捐赠收入 | C27: 0 | E27: 64 | F27: 6 | G27: =IFERROR((F27-C27)/C27,"") | H27: =IFERROR(F27/D27,"") | I27: =IF(LEN(A27)=3,"是",IF(B27<>"",IF(SUM(C27:F27)<>0,"是","否"),"是")) -> 是
A28: 10309 | B28: 政府住房基金收入 | C28: 7847 | D28: 7621 | E28: 65 | F28: 8601 | G28: =IFERROR((F28-C28)/C28,"") -> 0.096087677 | H28: =IFERROR(F28/D28,"") -> 1.128592 | I28: =IF(LEN(A28)=3,"是",IF(B28<>"",IF(SUM(C28:F28)<>0,"是","否"),"是")) -> 是
A29: 10399 | B29: 其他收入 | C29: 11 | E29: 66 | F29: 9 | G29: =IFERROR((F29-C29)/C29,"") -> -0.18181818 | H29: =IFERROR(F29/D29,"") | I29: =IF(LEN(A29)=3,"是",IF(B29<>"",IF(SUM(C29:F29)<>0,"是","否"),"是")) -> 是
E30: 67 | G30: =IFERROR((F30-C30)/C30,"") | H30: =IFERROR(F30/D30,"") | I30: =IF(LEN(A30)=3,"是",IF(B30<>"",IF(SUM(C30:F30)<>0,"是","否"),"是")) -> 是
B31: 全市一般公共预算收入 | C31: =SUM(C21,C5) -> 566703 | D31: =SUM(D21,D5) -> 595037 | E31: 68 | F31: =SUM(F21,F5) -> 567755 | G31: =IFERROR((F31-C31)/C31,"") -> 0.0018563516 | H31: =IFERROR(F31/D31,"") -> 0.95415075 | I31: =IF(LEN(A31)=3,"是",IF(B31<>"",IF(SUM(C31:F31)<>0,"是","否"),"是")) -> 是
A32: 105 | B32: 地方政府一般债务收入 | C32: 180780 | D32: 192645 | E32: 69 | F32: 237945 | G32: =IFERROR((F32-C32)/C32,"") -> 0.31621308 | H32: =IFERROR(F32/D32,"") -> 1.2351476 | I32: =IF(LEN(A32)=3,"是",IF(B32<>"",IF(SUM(C32:F32)<>0,"是","否"),"是")) -> 是
A33: 110 | B33: 转移性收入 | C33: =SUM(C34:C40) -> 1326634 | D33: =SUM(D34:D40) -> 1316167 | E33: 70 | F33: =SUM(F34:F40) -> 1275374 | G33: =IFERROR((F33-C33)/C33,"") -> -0.038639142 | H33: =IFERROR(F33/D33,"") -> 0.96900621 | I33: =IF(LEN(A33)=3,"是",IF(B33<>"",IF(SUM(C33:F33)<>0,"是","否"),"是")) -> 是
A34: 11001 | B34: 返还性收入 | C34: 41410 | D34: 40300 | E34: 72 | F34: 44029 | G34: =IFERROR((F34-C34)/C34,"") -> 0.063245593 | H34: =IFERROR(F34/D34,"") -> 1.092531 | I34: =IF(LEN(A34)=3,"是",IF(B34<>"",IF(SUM(C34:F34)<>0,"是","否"),"是")) -> 是
B35: 一般性转移支付收入 | C35: 917106 | D35: 912417 | E35: 73 | F35: 997380 | G35: =IFERROR((F35-C35)/C35,"") -> 0.087529686 | H35: =IFERROR(F35/D35,"") -> 1.0931186 | I35: =IF(LEN(A35)=3,"是",IF(B35<>"",IF(SUM(C35:F35)<>0,"是","否"),"是")) -> 是
B36: 专项转移支付收入 | C36: 264430 | D36: 264427 | E36: 74 | F36: 144850 | G36: =IFERROR((F36-C36)/C36,"") -> -0.45221798 | H36: =IFERROR(F36/D36,"") -> 0.54778824 | I36: =IF(LEN(A36)=3,"是",IF(B36<>"",IF(SUM(C36:F36)<>0,"是","否"),"是")) -> 是
A37: 11008 | B37: 上年结余收入 | C37: 49215 | D37: 48090 | E37: 75 | F37: 48541 | G37: =IFERROR((F37-C37)/C37,"") -> -0.013695012 | H37: =IFERROR(F37/D37,"") -> 1.0093782 | I37: =IF(LEN(A37)=3,"是",IF(B37<>"",IF(SUM(C37:F37)<>0,"是","否"),"是")) -> 是
A38: 11009 | B38: 调入资金 | C38: 51974 | D38: 50933 | E38: 76 | F38: 34108 | G38: =IFERROR((F38-C38)/C38,"") -> -0.3437488 | H38: =IFERROR(F38/D38,"") -> 0.66966407 | I38: =IF(LEN(A38)=3,"是",IF(B38<>"",IF(SUM(C38:F38)<>0,"是","否"),"是")) -> 是
A39: 11015 | B39: 动用预算稳定调节基金 | C39: 2499 | E39: 77 | F39: 6330 | G39: =IFERROR((F39-C39)/C39,"") -> 1.5330132 | H39: =IFERROR(F39/D39,"") | I39: =IF(LEN(A39)=3,"是",IF(B39<>"",IF(SUM(C39:F39)<>0,"是","否"),"是")) -> 是
A40: 11021 | B40: 区域间转移性收入 | E40: 78 | F40: 136 | G40: =IFERROR((F40-C40)/C40,"") | H40: =IFERROR(F40/D40,"") | I40: =IF(LEN(A40)=3,"是",IF(B40<>"",IF(SUM(C40:F40)<>0,"是","否"),"是")) -> 是
B41: 各项收入合计 | C41: =SUM(C31:C32,C33) -> 2074117 | D41: =SUM(D31:D32,D33) -> 2103849 | E41: 79 | F41: =SUM(F31:F32,F33) -> 2081074 | G41: =IFERROR((F41-C41)/C41,"") -> 0.0033541984 | H41: =IFERROR(F41/D41,"") -> 0.9891746 | I41: =IF(LEN(A41)=3,"是",IF(B41<>"",IF(SUM(C41:F41)<>0,"是","否"),"是")) -> 是
E42: 80
E43: 81
E44: 82
E45: 83
E46: 84
E47: 86
E48: 89
E49: 92
E50: 94

Sheet 01-2
B1: 2025年丽江市一般公共预算收支情况表
B2: 表一 | H2: 单位：万元
A3: 科目编码 | B3: 项目 | C3: 2024年决算数 | D3: 2025年 | G3: 比较
D4: 预算数 | E4: 3 | F4: 执行数 | G4: 比2024年决算数增长% | H4: 完成2025年预算数的% | I4: 打印
A5: 201 | B5: 一、一般公共服务支出 | C5: 132245 | D5: 138494 | E5: 8 | F5: ='02'!E5 -> 149662 | G5: =IFERROR((F5-C5)/C5,"") -> 0.13170252 | H5: =IFERROR(F5/D5,"") -> 1.0806389 | I5: =IF(LEN(A5)=3,"是",IF(B5<>"",IF(SUM(C5:F5)<>0,"是","否"),"是")) -> 是
A6: 202 | B6: 二、外交支出 | C6: 0 | E6: 10 | F6: ='02'!E253 -> 0 | G6: =IFERROR((F6-C6)/C6,"") | H6: =IFERROR(F6/D6,"") | I6: =IF(LEN(A6)=3,"是",IF(B6<>"",IF(SUM(C6:F6)<>0,"是","否"),"是")) -> 是
A7: 203 | B7: 三、国防支出 | C7: 2090 | D7: 2103 | E7: 22 | F7: ='02'!E293 -> 2580 | G7: =IFERROR((F7-C7)/C7,"") -> 0.23444976 | H7: =IFERROR(F7/D7,"") -> 1.2268188 | I7: =IF(LEN(A7)=3,"是",IF(B7<>"",IF(SUM(C7:F7)<>0,"是","否"),"是")) -> 是
A8: 204 | B8: 四、公共安全支出 | C8: 71463 | D8: 72985 | E8: 23 | F8: ='02'!E312 -> 75378 | G8: =IFERROR((F8-C8)/C8,"") -> 0.054783594 | H8: =IFERROR(F8/D8,"") -> 1.0327876 | I8: =IF(LEN(A8)=3,"是",IF(B8<>"",IF(SUM(C8:F8)<>0,"是","否"),"是")) -> 是
A9: 205 | B9: 五、教育支出 | C9: 255457 | D9: 270715 | E9: 24 | F9: ='02'!E402 -> 272444 | G9: =IFERROR((F9-C9)/C9,"") -> 0.066496514 | H9: =IFERROR(F9/D9,"") -> 1.0063868 | I9: =IF(LEN(A9)=3,"是",IF(B9<>"",IF(SUM(C9:F9)<>0,"是","否"),"是")) -> 是
A10: 206 | B10: 六、科学技术支出 | C10: 4318 | D10: 4613 | E10: 25 | F10: ='02'!E454 -> 6843 | G10: =IFERROR((F10-C10)/C10,"") -> 0.58476146 | H10: =IFERROR(F10/D10,"") -> 1.4834164 | I10: =IF(LEN(A10)=3,"是",IF(B10<>"",IF(SUM(C10:F10)<>0,"是","否"),"是")) -> 是
A11: 207 | B11: 七、文化旅游体育与传媒支出 | C11: 24616 | D11: 25013 | E11: 26 | F11: ='02'!E510 -> 22563 | G11: =IFERROR((F11-C11)/C11,"") -> -0.08340104 | H11: =IFERROR(F11/D11,"") -> 0.90205093 | I11: =IF(LEN(A11)=3,"是",IF(B11<>"",IF(SUM(C11:F11)<>0,"是","否"),"是")) -> 是
A12: 208 | B12: 八、社会保障和就业支出 | C12: 290336 | D12: 295265 | E12: 28 | F12: ='02'!E567 -> 292685 | G12: =IFERROR((F12-C12)/C12,"") -> 0.008090626 | H12: =IFERROR(F12/D12,"") -> 0.99126209 | I12: =IF(LEN(A12)=3,"是",IF(B12<>"",IF(SUM(C12:F12)<>0,"是","否"),"是")) -> 是
A13: 210 | B13: 九、卫生健康支出 | C13: 196852 | D13: 201368 | E13: 29 | F13: ='02'!E697 -> 214985 | G13: =IFERROR((F13-C13)/C13,"") -> 0.092114888 | H13: =IFERROR(F13/D13,"") -> 1.0676225 | I13: =IF(LEN(A13)=3,"是",IF(B13<>"",IF(SUM(C13:F13)<>0,"是","否"),"是")) -> 是
A14: 211 | B14: 十、节能环保支出 | C14: 90624 | D14: 93216 | E14: 30 | F14: ='02'!E782 -> 109450 | G14: =IFERROR((F14-C14)/C14,"") -> 0.20773746 | H14: =IFERROR(F14/D14,"") -> 1.1741547 | I14: =IF(LEN(A14)=3,"是",IF(B14<>"",IF(SUM(C14:F14)<>0,"是","否"),"是")) -> 是
A15: 212 | B15: 十一、城乡社区支出 | C15: 70334 | D15: 68458 | E15: 31 | F15: ='02'!E854 -> 73971 | G15: =IFERROR((F15-C15)/C15,"") -> 0.05171041 | H15: =IFERROR(F15/D15,"") -> 1.0805311 | I15: =IF(LEN(A15)=3,"是",IF(B15<>"",IF(SUM(C15:F15)<>0,"是","否"),"是")) -> 是
A16: 213 | B16: 十二、农林水支出 | C16: 377451 | D16: 359895 | E16: 32 | F16: ='02'!E877 -> 239253 | G16: =IFERROR((F16-C16)/C16,"") -> -0.36613494 | H16: =IFERROR(F16/D16,"") -> 0.66478556 | I16: =IF(LEN(A16)=3,"是",IF(B16<>"",IF(SUM(C16:F16)<>0,"是","否"),"是")) -> 是
A17: 214 | B17: 十三、交通运输支出 | C17: 51669 | D17: 52184 | E17: 33 | F17: ='02'!E984 -> 66230 | G17: =IFERROR((F17-C17)/C17,"") -> 0.28181308 | H17: =IFERROR(F17/D17,"") -> 1.269163 | I17: =IF(LEN(A17)=3,"是",IF(B17<>"",IF(SUM(C17:F17)<>0,"是","否"),"是")) -> 是
A18: 215 | B18: 十四、资源勘探工业信息等支出 | C18: 75263 | D18: 69853 | E18: 34 | F18: ='02'!E1036 -> 76311 | G18: =IFERROR((F18-C18)/C18,"") -> 0.013924505 | H18: =IFERROR(F18/D18,"") -> 1.0924513 | I18: =IF(LEN(A18)=3,"是",IF(B18<>"",IF(SUM(C18:F18)<>0,"是","否"),"是")) -> 是
A19: 216 | B19: 十五、商业服务业等支出 | C19: 1873 | D19: 1912 | E19: 35 | F19: ='02'!E1100 -> 2905 | G19: =IFERROR((F19-C19)/C19,"") -> 0.55098772 | H19: =IFERROR(F19/D19,"") -> 1.5193515 | I19: =IF(LEN(A19)=3,"是",IF(B19<>"",IF(SUM(C19:F19)<>0,"是","否"),"是")) -> 是
A20: 217 | B20: 十六、金融支出 | C20: 644 | D20: 625 | E20: 36 | F20: ='02'!E1120 -> 1711 | G20: =IFERROR((F20-C20)/C20,"") -> 1.6568323 | H20: =IFERROR(F20/D20,"") -> 2.7376 | I20: =IF(LEN(A20)=3,"是",IF(B20<>"",IF(SUM(C20:F20)<>0,"是","否"),"是")) -> 是
A21: 219 | B21: 十七、援助其他地区支出 | C21: 0 | E21: 37 | F21: ='02'!E1150 -> 0 | G21: =IFERROR((F21-C21)/C21,"") | H21: =IFERROR(F21/D21,"") | I21: =IF(LEN(A21)=3,"是",IF(B21<>"",IF(SUM(C21:F21)<>0,"是","否"),"是")) -> 是
A22: 220 | B22: 十八、自然资源海洋气象等支出 | C22: 19061 | D22: 19853 | E22: 38 | F22: ='02'!E1160 -> 21460 | G22: =IFERROR((F22-C22)/C22,"") -> 0.12585908 | H22: =IFERROR(F22/D22,"") -> 1.0809449 | I22: =IF(LEN(A22)=3,"是",IF(B22<>"",IF(SUM(C22:F22)<>0,"是","否"),"是")) -> 是
A23: 221 | B23: 十九、住房保障支出 | C23: 65723 | D23: 67253 | E23: 40 | F23: ='02'!E1205 -> 61136 | G23: =IFERROR((F23-C23)/C23,"") -> -0.069792919 | H23: =IFERROR(F23/D23,"") -> 0.90904495 | I23: =IF(LEN(A23)=3,"是",IF(B23<>"",IF(SUM(C23:F23)<>0,"是","否"),"是")) -> 是
A24: 222 | B24: 二十、粮油物资储备支出 | C24: 2311 | D24: 2295 | E24: 45 | F24: ='02'!E1227 -> 2085 | G24: =IFERROR((F24-C24)/C24,"") -> -0.097793163 | H24: =IFERROR(F24/D24,"") -> 0.90849673 | I24: =IF(LEN(A24)=3,"是",IF(B24<>"",IF(SUM(C24:F24)<>0,"是","否"),"是")) -> 是
A25: 224 | B25: 二十一、灾害防治及应急管理支出 | C25: 27427 | D25: 26693 | E25: 47 | F25: ='02'!E1272 -> 21135 | G25: =IFERROR((F25-C25)/C25,"") -> -0.22940898 | H25: =IFERROR(F25/D25,"") -> 0.79178062 | I25: =IF(LEN(A25)=3,"是",IF(B25<>"",IF(SUM(C25:F25)<>0,"是","否"),"是")) -> 是
A26: 227 | B26: 二十二、预备费 | C26: 0 | D26: 18500 | E26: 61 | F26: ='02'!E1322 -> 0 | G26: =IFERROR((F26-C26)/C26,"") | H26: =IFERROR(F26/D26,"") -> 0 | I26: =IF(LEN(A26)=3,"是",IF(B26<>"",IF(SUM(C26:F26)<>0,"是","否"),"是")) -> 是
A27: 232 | B27: 二十三、债务付息支出 | C27: 48249 | D27: 45794 | E27: 64 | F27: ='02'!E1323 -> 46367 | G27: =IFERROR((F27-C27)/C27,"") -> -0.03900599 | H27: =IFERROR(F27/D27,"") -> 1.0125126 | I27: =IF(LEN(A27)=3,"是",IF(B27<>"",IF(SUM(C27:F27)<>0,"是","否"),"是")) -> 是
A28: 233 | B28: 二十四、债务发行费用支出 | C28: 187 | D28: 140 | E28: 65 | F28: ='02'!E1329 -> 238 | G28: =IFERROR((F28-C28)/C28,"") -> 0.27272727 | H28: =IFERROR(F28/D28,"") -> 1.7 | I28: =IF(LEN(A28)=3,"是",IF(B28<>"",IF(SUM(C28:F28)<>0,"是","否"),"是")) -> 是
A29: 229 | B29: 二十五、其他支出 | C29: 1883 | E29: 66 | F29: ='02'!E1331 -> 3839 | G29: =IFERROR((F29-C29)/C29,"") -> 1.0387679 | H29: =IFERROR(F29/D29,"") | I29: =IF(LEN(A29)=3,"是",IF(B29<>"",IF(SUM(C29:F29)<>0,"是","否"),"是")) -> 是
E30: 67 | G30: =IFERROR((F30-C30)/C30,"") | H30: =IFERROR(F30/D30,"") | I30: =IF(LEN(A30)=3,"是",IF(B30<>"",IF(SUM(C30:F30)<>0,"是","否"),"是")) -> 是
B31: 全市一般公共预算支出 | C31: =SUM(C5:C29) -> 1810076 | D31: =SUM(D5:D29) -> 1837227 | E31: 68 | F31: =SUM(F5:F29) -> 1763231 | G31: =IFERROR((F31-C31)/C31,"") -> -0.025880129 | H31: =IFERROR(F31/D31,"") -> 0.95972408 | I31: =IF(LEN(A31)=3,"是",IF(B31<>"",IF(SUM(C31:F31)<>0,"是","否"),"是")) -> 是
A32: 230 | B32: 转移性支出 | C32: =SUM(C33:C36) -> 40294 | D32: =SUM(D33:D36) -> 33869 | E32: 69 | F32: =SUM(F33:F36) -> 37977 | G32: =IFERROR((F32-C32)/C32,"") -> -0.057502358 | H32: =IFERROR(F32/D32,"") -> 1.1212909 | I32: =IF(LEN(A32)=3,"是",IF(B32<>"",IF(SUM(C32:F32)<>0,"是","否"),"是")) -> 是
A33: 23006 | B33: 上解支出 | C33: 33648 | D33: 33869 | E33: 70 | F33: 35218 | G33: =IFERROR((F33-C33)/C33,"") -> 0.046659534 | H33: =IFERROR(F33/D33,"") -> 1.0398299 | I33: =IF(LEN(A33)=3,"是",IF(B33<>"",IF(SUM(C33:F33)<>0,"是","否"),"是")) -> 是
A34: 23008 | B34: 调出资金 | C34: 3948 | E34: 72 | G34: =IFERROR((F34-C34)/C34,"") -> -1 | H34: =IFERROR(F34/D34,"") | I34: =IF(LEN(A34)=3,"是",IF(B34<>"",IF(SUM(C34:F34)<>0,"是","否"),"是")) -> 是
A35: 23015 | B35: 安排预算稳定调节基金 | C35: 2698 | E35: 73 | F35: 2759 | G35: =IFERROR((F35-C35)/C35,"") -> 0.02260934 | H35: =IFERROR(F35/D35,"") | I35: =IF(LEN(A35)=3,"是",IF(B35<>"",IF(SUM(C35:F35)<>0,"是","否"),"是")) -> 是
A36: 23016 | B36: 补充预算周转金 | C36: 0 | E36: 74 | G36: =IFERROR((F36-C36)/C36,"") | H36: =IFERROR(F36/D36,"") | I36: =IF(LEN(A36)=3,"是",IF(B36<>"",IF(SUM(C36:F36)<>0,"是","否"),"是")) -> 是
A37: 231 | B37: 地方政府一般债务还本支出 | C37: 175206 | D37: 214260 | E37: 75 | F37: 234021 | G37: =IFERROR((F37-C37)/C37,"") -> 0.33569056 | H37: =IFERROR(F37/D37,"") -> 1.0922291 | I37: =IF(LEN(A37)=3,"是",IF(B37<>"",IF(SUM(C37:F37)<>0,"是","否"),"是")) -> 是
A38: 23021 | B38: 区域间转移性支出 | E38: 76 | F38: 38 | G38: =IFERROR((F38-C38)/C38,"") | H38: =IFERROR(F38/D38,"") | I38: =IF(LEN(A38)=3,"是",IF(B38<>"",IF(SUM(C38:F38)<>0,"是","否"),"是")) -> 是
A39: 23009 | B39: 年终结转 | C39: 48541 | D39: 18493 | E39: 77 | F39: 45807 | G39: =IFERROR((F39-C39)/C39,"") -> -0.05632352 | H39: =IFERROR(F39/D39,"") -> 2.4769913 | I39: =IF(LEN(A39)=3,"是",IF(B39<>"",IF(SUM(C39:F39)<>0,"是","否"),"是")) -> 是
B40: 各项支出合计 | C40: =SUM(C31:C32,C37:C39) -> 2074117 | D40: =SUM(D31:D32,D37:D39) -> 2103849 | E40: 78 | F40: =SUM(F31:F32,F37:F39) -> 2081074 | G40: =IFERROR((F40-C40)/C40,"") -> 0.0033541984 | H40: =IFERROR(F40/D40,"") -> 0.9891746 | I40: =IF(LEN(A40)=3,"是",IF(B40<>"",IF(SUM(C40:F40)<>0,"是","否"),"是")) -> 是
E41: 79
E42: 80
E43: 81
E44: 82
E45: 83
E46: 84
E47: 86
E48: 89
E49: 92
E50: 94

Sheet 02
B1: 2025年丽江市一般公共预算支出执行情况表
B2: 表二 | G2: 单位：万元
B3: 项目 | C3: 2024年决算数 | D3: 2025年 | F3: 比较
A4: 科目编码 | D4: 预算数 | E4: 执行数 | F4: 比2024年决算数增长% | G4: 完成2025年预算数的% | H4: 打印 | I4: 类-款-项
A5: 201 | B5: 一、一般公共服务支出 | C5: =C6+C18+C27+C37+C48+C59+C70+C78+C87+C100+C109+C120+C132+C139+C147+C153+C160+C167+C174+C181+C188+C196+C202+C208+C215+C230+C237+C250 -> 132245 | D5: =D6+D18+D27+D37+D48+D59+D70+D78+D87+D100+D109+D120+D132+D139+D147+D153+D160+D167+D174+D181+D188+D196+D202+D208+D215+D230+D237+D250 -> 138494 | E5: =E6+E18+E27+E37+E48+E59+E70+E78+E87+E100+E109+E120+E132+E139+E147+E153+E160+E167+E174+E181+E188+E196+E202+E208+E215+E230+E237+E250 -> 149662 | F5: =IFERROR((E5-C5)/C5,"") -> 0.13170252 | G5: =IFERROR(E5/D5,"") -> 1.0806389 | H5: =IF(LEN(A5)=3,"是",IF(B5<>"",IF(SUM(C5:E5)<>0,"是","否"),"是")) -> 是 | I5: =IF(LEN(A5)=3,"类",IF(LEN(A5)=5,"款","项")) -> 类
A6: 20101 | B6: 人大事务 | C6: =SUM(C7:C17) -> 3063 | D6: =SUM(D7:D17) -> 3107 | E6: =SUM(E7:E17) -> 5903 | F6: =IFERROR((E6-C6)/C6,"") -> 0.92719556 | G6: =IFERROR(E6/D6,"") -> 1.8999034 | H6: =IF(LEN(A6)=3,"是",IF(B6<>"",IF(SUM(C6:E6)<>0,"是","否"),"是")) -> 是 | I6: =IF(LEN(A6)=3,"类",IF(LEN(A6)=5,"款","项")) -> 款
A7: 2010101 | B7: 行政运行 | C7: ='[2]2'!E7 -> 2225 | D7: 2256 | E7: 4990 | F7: =IFERROR((E7-C7)/C7,"") -> 1.2426966 | G7: =IFERROR(E7/D7,"") -> 2.2118794 | H7: =IF(LEN(A7)=3,"是",IF(B7<>"",IF(SUM(C7:E7)<>0,"是","否"),"是")) -> 是 | I7: =IF(LEN(A7)=3,"类",IF(LEN(A7)=5,"款","项")) -> 项
A8: 2010102 | B8: 一般行政管理事务 | C8: ='[2]2'!E8 -> 173 | D8: 182 | E8: 175 | F8: =IFERROR((E8-C8)/C8,"") -> 0.011560694 | G8: =IFERROR(E8/D8,"") -> 0.96153846 | H8: =IF(LEN(A8)=3,"是",IF(B8<>"",IF(SUM(C8:E8)<>0,"是","否"),"是")) -> 是 | I8: =IF(LEN(A8)=3,"类",IF(LEN(A8)=5,"款","项")) -> 项
A9: 2010103 | B9: 机关服务 | C9: ='[2]2'!E9 -> 57 | D9: 60 | E9: 54 | F9: =IFERROR((E9-C9)/C9,"") -> -0.052631579 | G9: =IFERROR(E9/D9,"") -> 0.9 | H9: =IF(LEN(A9)=3,"是",IF(B9<>"",IF(SUM(C9:E9)<>0,"是","否"),"是")) -> 是 | I9: =IF(LEN(A9)=3,"类",IF(LEN(A9)=5,"款","项")) -> 项
A10: 2010104 | B10: 人大会议 | C10: ='[2]2'!E10 -> 280 | D10: 285 | E10: 312 | F10: =IFERROR((E10-C10)/C10,"") -> 0.11428571 | G10: =IFERROR(E10/D10,"") -> 1.0947368 | H10: =IF(LEN(A10)=3,"是",IF(B10<>"",IF(SUM(C10:E10)<>0,"是","否"),"是")) -> 是 | I10: =IF(LEN(A10)=3,"类",IF(LEN(A10)=5,"款","项")) -> 项
A11: 2010105 | B11: 人大立法 | C11: ='[2]2'!E11 -> 1 | D11: 1 | E11: 4 | F11: =IFERROR((E11-C11)/C11,"") -> 3 | G11: =IFERROR(E11/D11,"") -> 4 | H11: =IF(LEN(A11)=3,"是",IF(B11<>"",IF(SUM(C11:E11)<>0,"是","否"),"是")) -> 是 | I11: =IF(LEN(A11)=3,"类",IF(LEN(A11)=5,"款","项")) -> 项
A12: 2010106 | B12: 人大监督 | C12: ='[2]2'!E12 -> 16 | D12: 17 | E12: 20 | F12: =IFERROR((E12-C12)/C12,"") -> 0.25 | G12: =IFERROR(E12/D12,"") -> 1.1764706 | H12: =IF(LEN(A12)=3,"是",IF(B12<>"",IF(SUM(C12:E12)<>0,"是","否"),"是")) -> 是 | I12: =IF(LEN(A12)=3,"类",IF(LEN(A12)=5,"款","项")) -> 项
A13: 2010107 | B13: 人大代表履职能力提升 | C13: ='[2]2'!E13 -> 112 | D13: 115 | E13: 94 | F13: =IFERROR((E13-C13)/C13,"") -> -0.16071429 | G13: =IFERROR(E13/D13,"") -> 0.8173913 | H13: =IF(LEN(A13)=3,"是",IF(B13<>"",IF(SUM(C13:E13)<>0,"是","否"),"是")) -> 是 | I13: =IF(LEN(A13)=3,"类",IF(LEN(A13)=5,"款","项")) -> 项
A14: 2010108 | B14: 代表工作 | C14: ='[2]2'!E14 -> 52 | D14: 55 | E14: 84 | F14: =IFERROR((E14-C14)/C14,"") -> 0.61538462 | G14: =IFERROR(E14/D14,"") -> 1.5272727 | H14: =IF(LEN(A14)=3,"是",IF(B14<>"",IF(SUM(C14:E14)<>0,"是","否"),"是")) -> 是 | I14: =IF(LEN(A14)=3,"类",IF(LEN(A14)=5,"款","项")) -> 项
A15: 2010109 | B15: 人大信访工作 | C15: ='[2]2'!E15 -> 0 | E15: 0 | F15: =IFERROR((E15-C15)/C15,"") | G15: =IFERROR(E15/D15,"") | H15: =IF(LEN(A15)=3,"是",IF(B15<>"",IF(SUM(C15:E15)<>0,"是","否"),"是")) -> 否 | I15: =IF(LEN(A15)=3,"类",IF(LEN(A15)=5,"款","项")) -> 项
A16: 2010150 | B16: 事业运行 | C16: ='[2]2'!E16 -> 34 | D16: 35 | E16: 0 | F16: =IFERROR((E16-C16)/C16,"") -> -1 | G16: =IFERROR(E16/D16,"") -> 0 | H16: =IF(LEN(A16)=3,"是",IF(B16<>"",IF(SUM(C16:E16)<>0,"是","否"),"是")) -> 是 | I16: =IF(LEN(A16)=3,"类",IF(LEN(A16)=5,"款","项")) -> 项
A17: 2010199 | B17: 其他人大事务支出 | C17: ='[2]2'!E17 -> 113 | D17: 101 | E17: 170 | F17: =IFERROR((E17-C17)/C17,"") -> 0.50442478 | G17: =IFERROR(E17/D17,"") -> 1.6831683 | H17: =IF(LEN(A17)=3,"是",IF(B17<>"",IF(SUM(C17:E17)<>0,"是","否"),"是")) -> 是 | I17: =IF(LEN(A17)=3,"类",IF(LEN(A17)=5,"款","项")) -> 项
A18: 20102 | B18: 政协事务 | C18: =SUM(C19:C26) -> 4957 | D18: =SUM(D19:D26) -> 4983 | E18: =SUM(E19:E26) -> 5289 | F18: =IFERROR((E18-C18)/C18,"") -> 0.066975994 | G18: =IFERROR(E18/D18,"") -> 1.0614088 | H18: =IF(LEN(A18)=3,"是",IF(B18<>"",IF(SUM(C18:E18)<>0,"是","否"),"是")) -> 是 | I18: =IF(LEN(A18)=3,"类",IF(LEN(A18)=5,"款","项")) -> 款
A19: 2010201 | B19: 行政运行 | C19: ='[2]2'!E19 -> 4464 | D19: 4485 | E19: 4791 | F19: =IFERROR((E19-C19)/C19,"") -> 0.073252688 | G19: =IFERROR(E19/D19,"") -> 1.0682274 | H19: =IF(LEN(A19)=3,"是",IF(B19<>"",IF(SUM(C19:E19)<>0,"是","否"),"是")) -> 是 | I19: =IF(LEN(A19)=3,"类",IF(LEN(A19)=5,"款","项")) -> 项
A20: 2010202 | B20: 一般行政管理事务 | C20: ='[2]2'!E20 -> 159 | D20: 162 | E20: 110 | F20: =IFERROR((E20-C20)/C20,"") -> -0.3081761 | G20: =IFERROR(E20/D20,"") -> 0.67901235 | H20: =IF(LEN(A20)=3,"是",IF(B20<>"",IF(SUM(C20:E20)<>0,"是","否"),"是")) -> 是 | I20: =IF(LEN(A20)=3,"类",IF(LEN(A20)=5,"款","项")) -> 项
A21: 2010203 | B21: 机关服务 | C21: ='[2]2'!E21 -> 0 | E21: 0 | F21: =IFERROR((E21-C21)/C21,"") | G21: =IFERROR(E21/D21,"") | H21: =IF(LEN(A21)=3,"是",IF(B21<>"",IF(SUM(C21:E21)<>0,"是","否"),"是")) -> 否 | I21: =IF(LEN(A21)=3,"类",IF(LEN(A21)=5,"款","项")) -> 项
A22: 2010204 | B22: 政协会议 | C22: ='[2]2'!E22 -> 172 | D22: 179 | E22: 137 | F22: =IFERROR((E22-C22)/C22,"") -> -0.20348837 | G22: =IFERROR(E22/D22,"") -> 0.76536313 | H22: =IF(LEN(A22)=3,"是",IF(B22<>"",IF(SUM(C22:E22)<>0,"是","否"),"是")) -> 是 | I22: =IF(LEN(A22)=3,"类",IF(LEN(A22)=5,"款","项")) -> 项
A23: 2010205 | B23: 委员视察 | C23: ='[2]2'!E23 -> 23 | D23: 25 | E23: 12 | F23: =IFERROR((E23-C23)/C23,"") -> -0.47826087 | G23: =IFERROR(E23/D23,"") -> 0.48 | H23: =IF(LEN(A23)=3,"是",IF(B23<>"",IF(SUM(C23:E23)<>0,"是","否"),"是")) -> 是 | I23: =IF(LEN(A23)=3,"类",IF(LEN(A23)=5,"款","项")) -> 项
A24: 2010206 | B24: 参政议政 | C24: ='[2]2'!E24 -> 19 | D24: 21 | E24: 14 | F24: =IFERROR((E24-C24)/C24,"") -> -0.26315789 | G24: =IFERROR(E24/D24,"") -> 0.66666667 | H24: =IF(LEN(A24)=3,"是",IF(B24<>"",IF(SUM(C24:E24)<>0,"是","否"),"是")) -> 是 | I24: =IF(LEN(A24)=3,"类",IF(LEN(A24)=5,"款","项")) -> 项
A25: 2010250 | B25: 事业运行 | C25: ='[2]2'!E25 -> 0 | E25: 0 | F25: =IFERROR((E25-C25)/C25,"") | G25: =IFERROR(E25/D25,"") | H25: =IF(LEN(A25)=3,"是",IF(B25<>"",IF(SUM(C25:E25)<>0,"是","否"),"是")) -> 否 | I25: =IF(LEN(A25)=3,"类",IF(LEN(A25)=5,"款","项")) -> 项
A26: 2010299 | B26: 其他政协事务支出 | C26: ='[2]2'!E26 -> 120 | D26: 111 | E26: 225 | F26: =IFERROR((E26-C26)/C26,"") -> 0.875 | G26: =IFERROR(E26/D26,"") -> 2.027027 | H26: =IF(LEN(A26)=3,"是",IF(B26<>"",IF(SUM(C26:E26)<>0,"是","否"),"是")) -> 是 | I26: =IF(LEN(A26)=3,"类",IF(LEN(A26)=5,"款","项")) -> 项
A27: 20103 | B27: 政府办公厅(室)及相关机构事务 | C27: =SUM(C28:C36) -> 47212 | D27: =SUM(D28:D36) -> 46455 | E27: =SUM(E28:E36) -> 53527 | F27: =IFERROR((E27-C27)/C27,"") -> 0.13375837 | G27: =IFERROR(E27/D27,"") -> 1.1522333 | H27: =IF(LEN(A27)=3,"是",IF(B27<>"",IF(SUM(C27:E27)<>0,"是","否"),"是")) -> 是 | I27: =IF(LEN(A27)=3,"类",IF(LEN(A27)=5,"款","项")) -> 款
A28: 2010301 | B28: 行政运行 | C28: ='[2]2'!E28 -> 30603 | D28: 30859 | E28: 32143 | F28: =IFERROR((E28-C28)/C28,"") -> 0.050321864 | G28: =IFERROR(E28/D28,"") -> 1.0416086 | H28: =IF(LEN(A28)=3,"是",IF(B28<>"",IF(SUM(C28:E28)<>0,"是","否"),"是")) -> 是 | I28: =IF(LEN(A28)=3,"类",IF(LEN(A28)=5,"款","项")) -> 项
A29: 2010302 | B29: 一般行政管理事务 | C29: ='[2]2'!E29 -> 1499 | D29: 1523 | E29: 1854 | F29: =IFERROR((E29-C29)/C29,"") -> 0.23682455 | G29: =IFERROR(E29/D29,"") -> 1.2173342 | H29: =IF(LEN(A29)=3,"是",IF(B29<>"",IF(SUM(C29:E29)<>0,"是","否"),"是")) -> 是 | I29: =IF(LEN(A29)=3,"类",IF(LEN(A29)=5,"款","项")) -> 项
A30: 2010303 | B30: 机关服务 | C30: ='[2]2'!E30 -> 825 | D30: 832 | E30: 730 | F30: =IFERROR((E30-C30)/C30,"") -> -0.11515152 | G30: =IFERROR(E30/D30,"") -> 0.87740385 | H30: =IF(LEN(A30)=3,"是",IF(B30<>"",IF(SUM(C30:E30)<>0,"是","否"),"是")) -> 是 | I30: =IF(LEN(A30)=3,"类",IF(LEN(A30)=5,"款","项")) -> 项
A31: 2010304 | B31: 专项服务 | C31: ='[2]2'!E31 -> 2 | D31: 0 | E31: 2 | F31: =IFERROR((E31-C31)/C31,"") -> 0 | G31: =IFERROR(E31/D31,"") | H31: =IF(LEN(A31)=3,"是",IF(B31<>"",IF(SUM(C31:E31)<>0,"是","否"),"是")) -> 是 | I31: =IF(LEN(A31)=3,"类",IF(LEN(A31)=5,"款","项")) -> 项
A32: 2010305 | B32: 专项业务及机关事务管理 | C32: ='[2]2'!E32 -> 18 | D32: 19 | E32: 9 | F32: =IFERROR((E32-C32)/C32,"") -> -0.5 | G32: =IFERROR(E32/D32,"") -> 0.47368421 | H32: =IF(LEN(A32)=3,"是",IF(B32<>"",IF(SUM(C32:E32)<>0,"是","否"),"是")) -> 是 | I32: =IF(LEN(A32)=3,"类",IF(LEN(A32)=5,"款","项")) -> 项
A33: 2010306 | B33: 政务公开审批 | C33: ='[2]2'!E33 -> 0 | E33: 0 | F33: =IFERROR((E33-C33)/C33,"") | G33: =IFERROR(E33/D33,"") | H33: =IF(LEN(A33)=3,"是",IF(B33<>"",IF(SUM(C33:E33)<>0,"是","否"),"是")) -> 否 | I33: =IF(LEN(A33)=3,"类",IF(LEN(A33)=5,"款","项")) -> 项
A34: 2010309 | B34: 参事事务 | C34: ='[2]2'!E34 -> 15 | D34: 16 | E34: 9 | F34: =IFERROR((E34-C34)/C34,"") -> -0.4 | G34: =IFERROR(E34/D34,"") -> 0.5625 | H34: =IF(LEN(A34)=3,"是",IF(B34<>"",IF(SUM(C34:E34)<>0,"是","否"),"是")) -> 是 | I34: =IF(LEN(A34)=3,"类",IF(LEN(A34)=5,"款","项")) -> 项
A35: 2010350 | B35: 事业运行 | C35: ='[2]2'!E35 -> 8879 | D35: 8921 | E35: 17719 | F35: =IFERROR((E35-C35)/C35,"") -> 0.99560761 | G35: =IFERROR(E35/D35,"") -> 1.9862123 | H35: =IF(LEN(A35)=3,"是",IF(B35<>"",IF(SUM(C35:E35)<>0,"是","否"),"是")) -> 是 | I35: =IF(LEN(A35)=3,"类",IF(LEN(A35)=5,"款","项")) -> 项
A36: 2010399 | B36: 其他政府办公厅（室）及相关机构事务支出 | C36: ='[2]2'!E36 -> 5371 | D36: 4285 | E36: 1061 | F36: =IFERROR((E36-C36)/C36,"") -> -0.80245764 | G36: =IFERROR(E36/D36,"") -> 0.24760793 | H36: =IF(LEN(A36)=3,"是",IF(B36<>"",IF(SUM(C36:E36)<>0,"是","否"),"是")) -> 是 | I36: =IF(LEN(A36)=3,"类",IF(LEN(A36)=5,"款","项")) -> 项
A37: 20104 | B37: 发展与改革事务 | C37: =SUM(C38:C47) -> 5400 | D37: =SUM(D38:D47) -> 5395 | E37: =SUM(E38:E47) -> 7745 | F37: =IFERROR((E37-C37)/C37,"") -> 0.43425926 | G37: =IFERROR(E37/D37,"") -> 1.4355885 | H37: =IF(LEN(A37)=3,"是",IF(B37<>"",IF(SUM(C37:E37)<>0,"是","否"),"是")) -> 是 | I37: =IF(LEN(A37)=3,"类",IF(LEN(A37)=5,"款","项")) -> 款
A38: 2010401 | B38: 行政运行 | C38: ='[2]2'!E38 -> 3174 | D38: 3195 | E38: 3194 | F38: =IFERROR((E38-C38)/C38,"") -> 0.0063011972 | G38: =IFERROR(E38/D38,"") -> 0.99968701 | H38: =IF(LEN(A38)=3,"是",IF(B38<>"",IF(SUM(C38:E38)<>0,"是","否"),"是")) -> 是 | I38: =IF(LEN(A38)=3,"类",IF(LEN(A38)=5,"款","项")) -> 项
A39: 2010402 | B39: 一般行政管理事务 | C39: ='[2]2'!E39 -> 4 | D39: 5 | E39: 117 | F39: =IFERROR((E39-C39)/C39,"") -> 28.25 | G39: =IFERROR(E39/D39,"") -> 23.4 | H39: =IF(LEN(A39)=3,"是",IF(B39<>"",IF(SUM(C39:E39)<>0,"是","否"),"是")) -> 是 | I39: =IF(LEN(A39)=3,"类",IF(LEN(A39)=5,"款","项")) -> 项
A40: 2010403 | B40: 机关服务 | C40: ='[2]2'!E40 -> 0 | E40: 0 | F40: =IFERROR((E40-C40)/C40,"") | G40: =IFERROR(E40/D40,"") | H40: =IF(LEN(A40)=3,"是",IF(B40<>"",IF(SUM(C40:E40)<>0,"是","否"),"是")) -> 否 | I40: =IF(LEN(A40)=3,"类",IF(LEN(A40)=5,"款","项")) -> 项
A41: 2010404 | B41: 战略规划与实施 | C41: ='[2]2'!E41 -> 225 | D41: 227 | E41: 634 | F41: =IFERROR((E41-C41)/C41,"") -> 1.8177778 | G41: =IFERROR(E41/D41,"") -> 2.7929515 | H41: =IF(LEN(A41)=3,"是",IF(B41<>"",IF(SUM(C41:E41)<>0,"是","否"),"是")) -> 是 | I41: =IF(LEN(A41)=3,"类",IF(LEN(A41)=5,"款","项")) -> 项
A42: 2010405 | B42: 日常经济运行调节 | C42: ='[2]2'!E42 -> 0 | E42: 0 | F42: =IFERROR((E42-C42)/C42,"") | G42: =IFERROR(E42/D42,"") | H42: =IF(LEN(A42)=3,"是",IF(B42<>"",IF(SUM(C42:E42)<>0,"是","否"),"是")) -> 否 | I42: =IF(LEN(A42)=3,"类",IF(LEN(A42)=5,"款","项")) -> 项
A43: 2010406 | B43: 社会事业发展规划 | C43: ='[2]2'!E43 -> 678 | D43: 685 | E43: 218 | F43: =IFERROR((E43-C43)/C43,"") -> -0.67846608 | G43: =IFERROR(E43/D43,"") -> 0.31824818 | H43: =IF(LEN(A43)=3,"是",IF(B43<>"",IF(SUM(C43:E43)<>0,"是","否"),"是")) -> 是 | I43: =IF(LEN(A43)=3,"类",IF(LEN(A43)=5,"款","项")) -> 项
A44: 2010407 | B44: 经济体制改革研究 | C44: ='[2]2'!E44 -> 0 | E44: 0 | F44: =IFERROR((E44-C44)/C44,"") | G44: =IFERROR(E44/D44,"") | H44: =IF(LEN(A44)=3,"是",IF(B44<>"",IF(SUM(C44:E44)<>0,"是","否"),"是")) -> 否 | I44: =IF(LEN(A44)=3,"类",IF(LEN(A44)=5,"款","项")) -> 项
A45: 2010408 | B45: 物价管理 | C45: ='[2]2'!E45 -> 8 | D45: 5 | E45: 7 | F45: =IFERROR((E45-C45)/C45,"") -> -0.125 | G45: =IFERROR(E45/D45,"") -> 1.4 | H45: =IF(LEN(A45)=3,"是",IF(B45<>"",IF(SUM(C45:E45)<>0,"是","否"),"是")) -> 是 | I45: =IF(LEN(A45)=3,"类",IF(LEN(A45)=5,"款","项")) -> 项
A46: 2010450 | B46: 事业运行 | C46: ='[2]2'!E46 -> 714 | D46: 716 | E46: 937 | F46: =IFERROR((E46-C46)/C46,"") -> 0.31232493 | G46: =IFERROR(E46/D46,"") -> 1.3086592 | H46: =IF(LEN(A46)=3,"是",IF(B46<>"",IF(SUM(C46:E46)<>0,"是","否"),"是")) -> 是 | I46: =IF(LEN(A46)=3,"类",IF(LEN(A46)=5,"款","项")) -> 项
A47: 2010499 | B47: 其他发展与改革事务支出 | C47: ='[2]2'!E47 -> 597 | D47: 562 | E47: 2638 | F47: =IFERROR((E47-C47)/C47,"") -> 3.4187605 | G47: =IFERROR(E47/D47,"") -> 4.6939502 | H47: =IF(LEN(A47)=3,"是",IF(B47<>"",IF(SUM(C47:E47)<>0,"是","否"),"是")) -> 是 | I47: =IF(LEN(A47)=3,"类",IF(LEN(A47)=5,"款","项")) -> 项
A48: 20105 | B48: 统计信息事务 | C48: =SUM(C49:C58) -> 2668 | D48: =SUM(D49:D58) -> 2672 | E48: =SUM(E49:E58) -> 2427 | F48: =IFERROR((E48-C48)/C48,"") -> -0.090329835 | G48: =IFERROR(E48/D48,"") -> 0.90830838 | H48: =IF(LEN(A48)=3,"是",IF(B48<>"",IF(SUM(C48:E48)<>0,"是","否"),"是")) -> 是 | I48: =IF(LEN(A48)=3,"类",IF(LEN(A48)=5,"款","项")) -> 款
A49: 2010501 | B49: 行政运行 | C49: ='[2]2'!E49 -> 1096 | D49: 1105 | E49: 1144 | F49: =IFERROR((E49-C49)/C49,"") -> 0.04379562 | G49: =IFERROR(E49/D49,"") -> 1.0352941 | H49: =IF(LEN(A49)=3,"是",IF(B49<>"",IF(SUM(C49:E49)<>0,"是","否"),"是")) -> 是 | I49: =IF(LEN(A49)=3,"类",IF(LEN(A49)=5,"款","项")) -> 项
A50: 2010502 | B50: 一般行政管理事务 | C50: ='[2]2'!E50 -> 16 | D50: 18 | E50: 40 | F50: =IFERROR((E50-C50)/C50,"") -> 1.5 | G50: =IFERROR(E50/D50,"") -> 2.2222222 | H50: =IF(LEN(A50)=3,"是",IF(B50<>"",IF(SUM(C50:E50)<>0,"是","否"),"是")) -> 是 | I50: =IF(LEN(A50)=3,"类",IF(LEN(A50)=5,"款","项")) -> 项
A51: 2010503 | B51: 机关服务 | C51: ='[2]2'!E51 -> 0 | E51: 0 | F51: =IFERROR((E51-C51)/C51,"") | G51: =IFERROR(E51/D51,"") | H51: =IF(LEN(A51)=3,"是",IF(B51<>"",IF(SUM(C51:E51)<>0,"是","否"),"是")) -> 否 | I51: =IF(LEN(A51)=3,"类",IF(LEN(A51)=5,"款","项")) -> 项
A52: 2010504 | B52: 信息事务 | C52: ='[2]2'!E52 -> 0 | E52: 0 | F52: =IFERROR((E52-C52)/C52,"") | G52: =IFERROR(E52/D52,"") | H52: =IF(LEN(A52)=3,"是",IF(B52<>"",IF(SUM(C52:E52)<>0,"是","否"),"是")) -> 否 | I52: =IF(LEN(A52)=3,"类",IF(LEN(A52)=5,"款","项")) -> 项
A53: 2010505 | B53: 专项统计业务 | C53: ='[2]2'!E53 -> 280 | D53: 275 | E53: 198 | F53: =IFERROR((E53-C53)/C53,"") -> -0.29285714 | G53: =IFERROR(E53/D53,"") -> 0.72 | H53: =IF(LEN(A53)=3,"是",IF(B53<>"",IF(SUM(C53:E53)<>0,"是","否"),"是")) -> 是 | I53: =IF(LEN(A53)=3,"类",IF(LEN(A53)=5,"款","项")) -> 项
A54: 2010506 | B54: 统计管理 | C54: ='[2]2'!E54 -> 8 | D54: 9 | E54: 11 | F54: =IFERROR((E54-C54)/C54,"") -> 0.375 | G54: =IFERROR(E54/D54,"") -> 1.2222222 | H54: =IF(LEN(A54)=3,"是",IF(B54<>"",IF(SUM(C54:E54)<>0,"是","否"),"是")) -> 是 | I54: =IF(LEN(A54)=3,"类",IF(LEN(A54)=5,"款","项")) -> 项
A55: 2010507 | B55: 专项普查活动 | C55: ='[2]2'!E55 -> 390 | D55: 402 | E55: 164 | F55: =IFERROR((E55-C55)/C55,"") -> -0.57948718 | G55: =IFERROR(E55/D55,"") -> 0.4079602 | H55: =IF(LEN(A55)=3,"是",IF(B55<>"",IF(SUM(C55:E55)<>0,"是","否"),"是")) -> 是 | I55: =IF(LEN(A55)=3,"类",IF(LEN(A55)=5,"款","项")) -> 项
A56: 2010508 | B56: 统计抽样调查 | C56: ='[2]2'!E56 -> 235 | D56: 221 | E56: 86 | F56: =IFERROR((E56-C56)/C56,"") -> -0.63404255 | G56: =IFERROR(E56/D56,"") -> 0.38914027 | H56: =IF(LEN(A56)=3,"是",IF(B56<>"",IF(SUM(C56:E56)<>0,"是","否"),"是")) -> 是 | I56: =IF(LEN(A56)=3,"类",IF(LEN(A56)=5,"款","项")) -> 项
A57: 2010550 | B57: 事业运行 | C57: ='[2]2'!E57 -> 618 | D57: 621 | E57: 784 | F57: =IFERROR((E57-C57)/C57,"") -> 0.26860841 | G57: =IFERROR(E57/D57,"") -> 1.2624799 | H57: =IF(LEN(A57)=3,"是",IF(B57<>"",IF(SUM(C57:E57)<>0,"是","否"),"是")) -> 是 | I57: =IF(LEN(A57)=3,"类",IF(LEN(A57)=5,"款","项")) -> 项
A58: 2010599 | B58: 其他统计信息事务支出 | C58: ='[2]2'!E58 -> 25 | D58: 21 | E58: 0 | F58: =IFERROR((E58-C58)/C58,"") -> -1 | G58: =IFERROR(E58/D58,"") -> 0 | H58: =IF(LEN(A58)=3,"是",IF(B58<>"",IF(SUM(C58:E58)<>0,"是","否"),"是")) -> 是 | I58: =IF(LEN(A58)=3,"类",IF(LEN(A58)=5,"款","项")) -> 项
A59: 20106 | B59: 财政事务 | C59: =SUM(C60:C69) -> 8284 | D59: =SUM(D60:D69) -> 8303 | E59: =SUM(E60:E69) -> 8353 | F59: =IFERROR((E59-C59)/C59,"") -> 0.0083293095 | G59: =IFERROR(E59/D59,"") -> 1.0060219 | H59: =IF(LEN(A59)=3,"是",IF(B59<>"",IF(SUM(C59:E59)<>0,"是","否"),"是")) -> 是 | I59: =IF(LEN(A59)=3,"类",IF(LEN(A59)=5,"款","项")) -> 款
A60: 2010601 | B60: 行政运行 | C60: ='[2]2'!E60 -> 4914 | D60: 4921 | E60: 4703 | F60: =IFERROR((E60-C60)/C60,"") -> -0.042938543 | G60: =IFERROR(E60/D60,"") -> 0.95570006 | H60: =IF(LEN(A60)=3,"是",IF(B60<>"",IF(SUM(C60:E60)<>0,"是","否"),"是")) -> 是 | I60: =IF(LEN(A60)=3,"类",IF(LEN(A60)=5,"款","项")) -> 项
A61: 2010602 | B61: 一般行政管理事务 | C61: ='[2]2'!E61 -> 299 | D61: 303 | E61: 53 | F61: =IFERROR((E61-C61)/C61,"") -> -0.82274247 | G61: =IFERROR(E61/D61,"") -> 0.17491749 | H61: =IF(LEN(A61)=3,"是",IF(B61<>"",IF(SUM(C61:E61)<>0,"是","否"),"是")) -> 是 | I61: =IF(LEN(A61)=3,"类",IF(LEN(A61)=5,"款","项")) -> 项
A62: 2010603 | B62: 机关服务 | C62: ='[2]2'!E62 -> 0 | E62: 0 | F62: =IFERROR((E62-C62)/C62,"") | G62: =IFERROR(E62/D62,"") | H62: =IF(LEN(A62)=3,"是",IF(B62<>"",IF(SUM(C62:E62)<>0,"是","否"),"是")) -> 否 | I62: =IF(LEN(A62)=3,"类",IF(LEN(A62)=5,"款","项")) -> 项
A63: 2010604 | B63: 预算改革业务 | C63: ='[2]2'!E63 -> 70 | D63: 75 | E63: 79 | F63: =IFERROR((E63-C63)/C63,"") -> 0.12857143 | G63: =IFERROR(E63/D63,"") -> 1.0533333 | H63: =IF(LEN(A63)=3,"是",IF(B63<>"",IF(SUM(C63:E63)<>0,"是","否"),"是")) -> 是 | I63: =IF(LEN(A63)=3,"类",IF(LEN(A63)=5,"款","项")) -> 项
A64: 2010605 | B64: 财政国库业务 | C64: ='[2]2'!E64 -> 32 | D64: 34 | E64: 4 | F64: =IFERROR((E64-C64)/C64,"") -> -0.875 | G64: =IFERROR(E64/D64,"") -> 0.11764706 | H64: =IF(LEN(A64)=3,"是",IF(B64<>"",IF(SUM(C64:E64)<>0,"是","否"),"是")) -> 是 | I64: =IF(LEN(A64)=3,"类",IF(LEN(A64)=5,"款","项")) -> 项
A65: 2010606 | B65: 财政监察 | C65: ='[2]2'!E65 -> 0 | E65: 0 | F65: =IFERROR((E65-C65)/C65,"") | G65: =IFERROR(E65/D65,"") | H65: =IF(LEN(A65)=3,"是",IF(B65<>"",IF(SUM(C65:E65)<>0,"是","否"),"是")) -> 否 | I65: =IF(LEN(A65)=3,"类",IF(LEN(A65)=5,"款","项")) -> 项
A66: 2010607 | B66: 信息化建设 | C66: ='[2]2'!E66 -> 186 | D66: 189 | E66: 428 | F66: =IFERROR((E66-C66)/C66,"") -> 1.3010753 | G66: =IFERROR(E66/D66,"") -> 2.2645503 | H66: =IF(LEN(A66)=3,"是",IF(B66<>"",IF(SUM(C66:E66)<>0,"是","否"),"是")) -> 是 | I66: =IF(LEN(A66)=3,"类",IF(LEN(A66)=5,"款","项")) -> 项
A67: 2010608 | B67: 财政委托业务支出 | C67: ='[2]2'!E67 -> 486 | D67: 489 | E67: 285 | F67: =IFERROR((E67-C67)/C67,"") -> -0.41358025 | G67: =IFERROR(E67/D67,"") -> 0.58282209 | H67: =IF(LEN(A67)=3,"是",IF(B67<>"",IF(SUM(C67:E67)<>0,"是","否"),"是")) -> 是 | I67: =IF(LEN(A67)=3,"类",IF(LEN(A67)=5,"款","项")) -> 项
A68: 2010650 | B68: 事业运行 | C68: ='[2]2'!E68 -> 1717 | D68: 1721 | E68: 1433 | F68: =IFERROR((E68-C68)/C68,"") -> -0.16540478 | G68: =IFERROR(E68/D68,"") -> 0.83265543 | H68: =IF(LEN(A68)=3,"是",IF(B68<>"",IF(SUM(C68:E68)<>0,"是","否"),"是")) -> 是 | I68: =IF(LEN(A68)=3,"类",IF(LEN(A68)=5,"款","项")) -> 项
A69: 2010699 | B69: 其他财政事务支出 | C69: ='[2]2'!E69 -> 580 | D69: 571 | E69: 1368 | F69: =IFERROR((E69-C69)/C69,"") -> 1.3586207 | G69: =IFERROR(E69/D69,"") -> 2.3957968 | H69: =IF(LEN(A69)=3,"是",IF(B69<>"",IF(SUM(C69:E69)<>0,"是","否"),"是")) -> 是 | I69: =IF(LEN(A69)=3,"类",IF(LEN(A69)=5,"款","项")) -> 项
A70: 20107 | B70: 税收事务 | C70: =SUM(C71:C77) -> 827 | D70: =SUM(D71:D77) -> 822 | E70: =SUM(E71:E77) -> 765 | F70: =IFERROR((E70-C70)/C70,"") -> -0.07496977 | G70: =IFERROR(E70/D70,"") -> 0.93065693 | H70: =IF(LEN(A70)=3,"是",IF(B70<>"",IF(SUM(C70:E70)<>0,"是","否"),"是")) -> 是 | I70: =IF(LEN(A70)=3,"类",IF(LEN(A70)=5,"款","项")) -> 款
A71: 2010701 | B71: 行政运行 | C71: ='[2]2'!E71 -> 478 | D71: 481 | E71: 395 | F71: =IFERROR((E71-C71)/C71,"") -> -0.17364017 | G71: =IFERROR(E71/D71,"") -> 0.82120582 | H71: =IF(LEN(A71)=3,"是",IF(B71<>"",IF(SUM(C71:E71)<>0,"是","否"),"是")) -> 是 | I71: =IF(LEN(A71)=3,"类",IF(LEN(A71)=5,"款","项")) -> 项
A72: 2010702 | B72: 一般行政管理事务 | C72: ='[2]2'!E72 -> 114 | D72: 116 | E72: 106 | F72: =IFERROR((E72-C72)/C72,"") -> -0.070175439 | G72: =IFERROR(E72/D72,"") -> 0.9137931 | H72: =IF(LEN(A72)=3,"是",IF(B72<>"",IF(SUM(C72:E72)<>0,"是","否"),"是")) -> 是 | I72: =IF(LEN(A72)=3,"类",IF(LEN(A72)=5,"款","项")) -> 项
A73: 2010703 | B73: 机关服务 | C73: ='[2]2'!E73 -> 0 | E73: 0 | F73: =IFERROR((E73-C73)/C73,"") | G73: =IFERROR(E73/D73,"") | H73: =IF(LEN(A73)=3,"是",IF(B73<>"",IF(SUM(C73:E73)<>0,"是","否"),"是")) -> 否 | I73: =IF(LEN(A73)=3,"类",IF(LEN(A73)=5,"款","项")) -> 项
A74: 2010709 | B74: 信息化建设 | C74: ='[2]2'!E74 -> 0 | E74: 0 | F74: =IFERROR((E74-C74)/C74,"") | G74: =IFERROR(E74/D74,"") | H74: =IF(LEN(A74)=3,"是",IF(B74<>"",IF(SUM(C74:E74)<>0,"是","否"),"是")) -> 否 | I74: =IF(LEN(A74)=3,"类",IF(LEN(A74)=5,"款","项")) -> 项
A75: 2010710 | B75: 税收业务 | C75: ='[2]2'!E75 -> 50 | D75: 50 | E75: 6 | F75: =IFERROR((E75-C75)/C75,"") -> -0.88 | G75: =IFERROR(E75/D75,"") -> 0.12 | H75: =IF(LEN(A75)=3,"是",IF(B75<>"",IF(SUM(C75:E75)<>0,"是","否"),"是")) -> 是 | I75: =IF(LEN(A75)=3,"类",IF(LEN(A75)=5,"款","项")) -> 项
A76: 2010750 | B76: 事业运行 | C76: ='[2]2'!E76 -> 0 | E76: 0 | F76: =IFERROR((E76-C76)/C76,"") | G76: =IFERROR(E76/D76,"") | H76: =IF(LEN(A76)=3,"是",IF(B76<>"",IF(SUM(C76:E76)<>0,"是","否"),"是")) -> 否 | I76: =IF(LEN(A76)=3,"类",IF(LEN(A76)=5,"款","项")) -> 项
A77: 2010799 | B77: 其他税收事务支出 | C77: ='[2]2'!E77 -> 185 | D77: 175 | E77: 258 | F77: =IFERROR((E77-C77)/C77,"") -> 0.39459459 | G77: =IFERROR(E77/D77,"") -> 1.4742857 | H77: =IF(LEN(A77)=3,"是",IF(B77<>"",IF(SUM(C77:E77)<>0,"是","否"),"是")) -> 是 | I77: =IF(LEN(A77)=3,"类",IF(LEN(A77)=5,"款","项")) -> 项
A78: 20108 | B78: 审计事务 | C78: =SUM(C79:C86) -> 694 | D78: =SUM(D79:D86) -> 696 | E78: =SUM(E79:E86) -> 382 | F78: =IFERROR((E78-C78)/C78,"") -> -0.44956772 | G78: =IFERROR(E78/D78,"") -> 0.54885057 | H78: =IF(LEN(A78)=3,"是",IF(B78<>"",IF(SUM(C78:E78)<>0,"是","否"),"是")) -> 是 | I78: =IF(LEN(A78)=3,"类",IF(LEN(A78)=5,"款","项")) -> 款
A79: 2010801 | B79: 行政运行 | C79: ='[2]2'!E79 -> 1 | D79: 1 | E79: 0 | F79: =IFERROR((E79-C79)/C79,"") -> -1 | G79: =IFERROR(E79/D79,"") -> 0 | H79: =IF(LEN(A79)=3,"是",IF(B79<>"",IF(SUM(C79:E79)<>0,"是","否"),"是")) -> 是 | I79: =IF(LEN(A79)=3,"类",IF(LEN(A79)=5,"款","项")) -> 项
A80: 2010802 | B80: 一般行政管理事务 | C80: ='[2]2'!E80 -> 0 | E80: 0 | F80: =IFERROR((E80-C80)/C80,"") | G80: =IFERROR(E80/D80,"") | H80: =IF(LEN(A80)=3,"是",IF(B80<>"",IF(SUM(C80:E80)<>0,"是","否"),"是")) -> 否 | I80: =IF(LEN(A80)=3,"类",IF(LEN(A80)=5,"款","项")) -> 项
A81: 2010803 | B81: 机关服务 | C81: ='[2]2'!E81 -> 0 | E81: 0 | F81: =IFERROR((E81-C81)/C81,"") | G81: =IFERROR(E81/D81,"") | H81: =IF(LEN(A81)=3,"是",IF(B81<>"",IF(SUM(C81:E81)<>0,"是","否"),"是")) -> 否 | I81: =IF(LEN(A81)=3,"类",IF(LEN(A81)=5,"款","项")) -> 项
A82: 2010804 | B82: 审计业务 | C82: ='[2]2'!E82 -> 670 | D82: 672 | E82: 366 | F82: =IFERROR((E82-C82)/C82,"") -> -0.45373134 | G82: =IFERROR(E82/D82,"") -> 0.54464286 | H82: =IF(LEN(A82)=3,"是",IF(B82<>"",IF(SUM(C82:E82)<>0,"是","否"),"是")) -> 是 | I82: =IF(LEN(A82)=3,"类",IF(LEN(A82)=5,"款","项")) -> 项
A83: 2010805 | B83: 审计管理 | C83: ='[2]2'!E83 -> 0 | E83: 0 | F83: =IFERROR((E83-C83)/C83,"") | G83: =IFERROR(E83/D83,"") | H83: =IF(LEN(A83)=3,"是",IF(B83<>"",IF(SUM(C83:E83)<>0,"是","否"),"是")) -> 否 | I83: =IF(LEN(A83)=3,"类",IF(LEN(A83)=5,"款","项")) -> 项
A84: 2010806 | B84: 信息化建设 | C84: ='[2]2'!E84 -> 0 | E84: 0 | F84: =IFERROR((E84-C84)/C84,"") | G84: =IFERROR(E84/D84,"") | H84: =IF(LEN(A84)=3,"是",IF(B84<>"",IF(SUM(C84:E84)<>0,"是","否"),"是")) -> 否 | I84: =IF(LEN(A84)=3,"类",IF(LEN(A84)=5,"款","项")) -> 项
A85: 2010850 | B85: 事业运行 | C85: ='[2]2'!E85 -> 23 | D85: 23 | E85: 16 | F85: =IFERROR((E85-C85)/C85,"") -> -0.30434783 | G85: =IFERROR(E85/D85,"") -> 0.69565217 | H85: =IF(LEN(A85)=3,"是",IF(B85<>"",IF(SUM(C85:E85)<>0,"是","否"),"是")) -> 是 | I85: =IF(LEN(A85)=3,"类",IF(LEN(A85)=5,"款","项")) -> 项
A86: 2010899 | B86: 其他审计事务支出 | C86: ='[2]2'!E86 -> 0 | E86: 0 | F86: =IFERROR((E86-C86)/C86,"") | G86: =IFERROR(E86/D86,"") | H86: =IF(LEN(A86)=3,"是",IF(B86<>"",IF(SUM(C86:E86)<>0,"是","否"),"是")) -> 否 | I86: =IF(LEN(A86)=3,"类",IF(LEN(A86)=5,"款","项")) -> 项
A87: 20109 | B87: 海关事务 | C87: =SUM(C88:C99) -> 98 | D87: =SUM(D88:D99) -> 95 | E87: =SUM(E88:E99) -> 97 | F87: =IFERROR((E87-C87)/C87,"") -> -0.010204082 | G87: =IFERROR(E87/D87,"") -> 1.0210526 | H87: =IF(LEN(A87)=3,"是",IF(B87<>"",IF(SUM(C87:E87)<>0,"是","否"),"是")) -> 是 | I87: =IF(LEN(A87)=3,"类",IF(LEN(A87)=5,"款","项")) -> 款
A88: 2010901 | B88: 行政运行 | C88: ='[2]2'!E88 -> 0 | E88: 2 | F88: =IFERROR((E88-C88)/C88,"") | G88: =IFERROR(E88/D88,"") | H88: =IF(LEN(A88)=3,"是",IF(B88<>"",IF(SUM(C88:E88)<>0,"是","否"),"是")) -> 是 | I88: =IF(LEN(A88)=3,"类",IF(LEN(A88)=5,"款","项")) -> 项
A89: 2010902 | B89: 一般行政管理事务 | C89: ='[2]2'!E89 -> 98 | D89: 95 | E89: 95 | F89: =IFERROR((E89-C89)/C89,"") -> -0.030612245 | G89: =IFERROR(E89/D89,"") -> 1 | H89: =IF(LEN(A89)=3,"是",IF(B89<>"",IF(SUM(C89:E89)<>0,"是","否"),"是")) -> 是 | I89: =IF(LEN(A89)=3,"类",IF(LEN(A89)=5,"款","项")) -> 项
A90: 2010903 | B90: 机关服务 | C90: ='[2]2'!E90 -> 0 | E90: 0 | F90: =IFERROR((E90-C90)/C90,"") | G90: =IFERROR(E90/D90,"") | H90: =IF(LEN(A90)=3,"是",IF(B90<>"",IF(SUM(C90:E90)<>0,"是","否"),"是")) -> 否 | I90: =IF(LEN(A90)=3,"类",IF(LEN(A90)=5,"款","项")) -> 项
A91: 2010905 | B91: 缉私办案 | C91: ='[2]2'!E91 -> 0 | E91: 0 | F91: =IFERROR((E91-C91)/C91,"") | G91: =IFERROR(E91/D91,"") | H91: =IF(LEN(A91)=3,"是",IF(B91<>"",IF(SUM(C91:E91)<>0,"是","否"),"是")) -> 否 | I91: =IF(LEN(A91)=3,"类",IF(LEN(A91)=5,"款","项")) -> 项
A92: 2010907 | B92: 口岸管理 | C92: ='[2]2'!E92 -> 0 | E92: 0 | F92: =IFERROR((E92-C92)/C92,"") | G92: =IFERROR(E92/D92,"") | H92: =IF(LEN(A92)=3,"是",IF(B92<>"",IF(SUM(C92:E92)<>0,"是","否"),"是")) -> 否 | I92: =IF(LEN(A92)=3,"类",IF(LEN(A92)=5,"款","项")) -> 项
A93: 2010908 | B93: 信息化建设 | C93: ='[2]2'!E93 -> 0 | E93: 0 | F93: =IFERROR((E93-C93)/C93,"") | G93: =IFERROR(E93/D93,"") | H93: =IF(LEN(A93)=3,"是",IF(B93<>"",IF(SUM(C93:E93)<>0,"是","否"),"是")) -> 否 | I93: =IF(LEN(A93)=3,"类",IF(LEN(A93)=5,"款","项")) -> 项
A94: 2010909 | B94: 海关关务 | C94: ='[2]2'!E94 -> 0 | E94: 0 | F94: =IFERROR((E94-C94)/C94,"") | G94: =IFERROR(E94/D94,"") | H94: =IF(LEN(A94)=3,"是",IF(B94<>"",IF(SUM(C94:E94)<>0,"是","否"),"是")) -> 否 | I94: =IF(LEN(A94)=3,"类",IF(LEN(A94)=5,"款","项")) -> 项
A95: 2010910 | B95: 关税征管 | C95: ='[2]2'!E95 -> 0 | E95: 0 | F95: =IFERROR((E95-C95)/C95,"") | G95: =IFERROR(E95/D95,"") | H95: =IF(LEN(A95)=3,"是",IF(B95<>"",IF(SUM(C95:E95)<>0,"是","否"),"是")) -> 否 | I95: =IF(LEN(A95)=3,"类",IF(LEN(A95)=5,"款","项")) -> 项
A96: 2010911 | B96: 海关监管 | C96: ='[2]2'!E96 -> 0 | E96: 0 | F96: =IFERROR((E96-C96)/C96,"") | G96: =IFERROR(E96/D96,"") | H96: =IF(LEN(A96)=3,"是",IF(B96<>"",IF(SUM(C96:E96)<>0,"是","否"),"是")) -> 否 | I96: =IF(LEN(A96)=3,"类",IF(LEN(A96)=5,"款","项")) -> 项
A97: 2010912 | B97: 检验检疫 | C97: ='[2]2'!E97 -> 0 | E97: 0 | F97: =IFERROR((E97-C97)/C97,"") | G97: =IFERROR(E97/D97,"") | H97: =IF(LEN(A97)=3,"是",IF(B97<>"",IF(SUM(C97:E97)<>0,"是","否"),"是")) -> 否 | I97: =IF(LEN(A97)=3,"类",IF(LEN(A97)=5,"款","项")) -> 项
A98: 2010950 | B98: 事业运行 | C98: ='[2]2'!E98 -> 0 | E98: 0 | F98: =IFERROR((E98-C98)/C98,"") | G98: =IFERROR(E98/D98,"") | H98: =IF(LEN(A98)=3,"是",IF(B98<>"",IF(SUM(C98:E98)<>0,"是","否"),"是")) -> 否 | I98: =IF(LEN(A98)=3,"类",IF(LEN(A98)=5,"款","项")) -> 项
A99: 2010999 | B99: 其他海关事务支出 | C99: ='[2]2'!E99 -> 0 | E99: 0 | F99: =IFERROR((E99-C99)/C99,"") | G99: =IFERROR(E99/D99,"") | H99: =IF(LEN(A99)=3,"是",IF(B99<>"",IF(SUM(C99:E99)<>0,"是","否"),"是")) -> 否 | I99: =IF(LEN(A99)=3,"类",IF(LEN(A99)=5,"款","项")) -> 项
A100: 20111 | B100: 纪检监察事务 | C100: =SUM(C101:C108) -> 15231 | D100: =SUM(D101:D108) -> 15160 | E100: =SUM(E101:E108) -> 13479 | F100: =IFERROR((E100-C100)/C100,"") -> -0.11502856 | G100: =IFERROR(E100/D100,"") -> 0.88911609 | H100: =IF(LEN(A100)=3,"是",IF(B100<>"",IF(SUM(C100:E100)<>0,"是","否"),"是")) -> 是 | I100: =IF(LEN(A100)=3,"类",IF(LEN(A100)=5,"款","项")) -> 款
...

Sheet 03-1
B1: 2025年市本级一般公共预算收支情况表
B2: 表三 | H2: 单位：万元
A3: 科目编码 | B3: 项目 | C3: 2024年决算数 | D3: 2025年 | G3: 比较
D4: 预算数 | E4: 调整预算数 | F4: 执行数 | G4: 比2024年决算数增长% | H4: 完成2025年预算数的% | I4: 打印
A5: 101 | B5: 一、税收收入 | C5: =SUM(C6:C20) -> 77130 | D5: =SUM(D6:D20) -> 89559 | E5: =SUM(E6:E20) -> 89559 | F5: =SUM(F6:F20) -> 85531 | G5: =IFERROR((F5-C5)/C5,"") -> 0.10892001 | H5: =IFERROR(F5/D5,"") -> 0.95502406 | I5: =IF(LEN(A5)=3,"是",IF(B5<>"",IF(SUM(C5:F5)<>0,"是","否"),"是")) -> 是
A6: 10101 | B6: 增值税 | C6: 56284 | D6: 58634 | E6: 58634 | F6: 55637 | G6: =IFERROR((F6-C6)/C6,"") -> -0.011495274 | H6: =IFERROR(F6/D6,"") -> 0.94888631 | I6: =IF(LEN(A6)=3,"是",IF(B6<>"",IF(SUM(C6:F6)<>0,"是","否"),"是")) -> 是
A7: 10104 | B7: 企业所得税 | C7: 8678 | D7: 9614 | E7: 9614 | F7: 6961 | G7: =IFERROR((F7-C7)/C7,"") -> -0.19785665 | H7: =IFERROR(F7/D7,"") -> 0.72404826 | I7: =IF(LEN(A7)=3,"是",IF(B7<>"",IF(SUM(C7:F7)<>0,"是","否"),"是")) -> 是
A8: 10106 | B8: 个人所得税 | C8: 1317 | D8: 1447 | E8: 1447 | F8: 1378 | G8: =IFERROR((F8-C8)/C8,"") -> 0.046317388 | H8: =IFERROR(F8/D8,"") -> 0.95231513 | I8: =IF(LEN(A8)=3,"是",IF(B8<>"",IF(SUM(C8:F8)<>0,"是","否"),"是")) -> 是
A9: 10107 | B9: 资源税 | C9: 0 | D9: 8572 | E9: 8572 | F9: 7217 | G9: =IFERROR((F9-C9)/C9,"") | H9: =IFERROR(F9/D9,"") -> 0.8419272 | I9: =IF(LEN(A9)=3,"是",IF(B9<>"",IF(SUM(C9:F9)<>0,"是","否"),"是")) -> 是
A10: 10109 | B10: 城市维护建设税 | C10: 3520 | D10: 3839 | E10: 3839 | F10: 3203 | G10: =IFERROR((F10-C10)/C10,"") -> -0.090056818 | H10: =IFERROR(F10/D10,"") -> 0.83433186 | I10: =IF(LEN(A10)=3,"是",IF(B10<>"",IF(SUM(C10:F10)<>0,"是","否"),"是")) -> 是
A11: 10110 | B11: 房产税 | C11: 53 | D11: 53 | E11: 53 | F11: 53 | G11: =IFERROR((F11-C11)/C11,"") -> 0 | H11: =IFERROR(F11/D11,"") -> 1 | I11: =IF(LEN(A11)=3,"是",IF(B11<>"",IF(SUM(C11:F11)<>0,"是","否"),"是")) -> 是
A12: 10111 | B12: 印花税 | C12: 67 | D12: 90 | E12: 90 | F12: 53 | G12: =IFERROR((F12-C12)/C12,"") -> -0.20895522 | H12: =IFERROR(F12/D12,"") -> 0.58888889 | I12: =IF(LEN(A12)=3,"是",IF(B12<>"",IF(SUM(C12:F12)<>0,"是","否"),"是")) -> 是
A13: 10112 | B13: 城镇土地使用税 | C13: 16 | D13: 20 | E13: 20 | F13: 16 | G13: =IFERROR((F13-C13)/C13,"") -> 0 | H13: =IFERROR(F13/D13,"") -> 0.8 | I13: =IF(LEN(A13)=3,"是",IF(B13<>"",IF(SUM(C13:F13)<>0,"是","否"),"是")) -> 是
A14: 10113 | B14: 土地增值税 | C14: 0 | E14: 0 | G14: =IFERROR((F14-C14)/C14,"") | H14: =IFERROR(F14/D14,"") | I14: =IF(LEN(A14)=3,"是",IF(B14<>"",IF(SUM(C14:F14)<>0,"是","否"),"是")) -> 否
A15: 10114 | B15: 车船税 | C15: 0 | E15: 0 | G15: =IFERROR((F15-C15)/C15,"") | H15: =IFERROR(F15/D15,"") | I15: =IF(LEN(A15)=3,"是",IF(B15<>"",IF(SUM(C15:F15)<>0,"是","否"),"是")) -> 否
A16: 10118 | B16: 耕地占用税 | C16: 7110 | D16: 7290 | E16: 7290 | F16: 10962 | G16: =IFERROR((F16-C16)/C16,"") -> 0.54177215 | H16: =IFERROR(F16/D16,"") -> 1.5037037 | I16: =IF(LEN(A16)=3,"是",IF(B16<>"",IF(SUM(C16:F16)<>0,"是","否"),"是")) -> 是
A17: 10119 | B17: 契税 | C17: 73 | E17: 0 | G17: =IFERROR((F17-C17)/C17,"") -> -1 | H17: =IFERROR(F17/D17,"") | I17: =IF(LEN(A17)=3,"是",IF(B17<>"",IF(SUM(C17:F17)<>0,"是","否"),"是")) -> 是
A18: 10120 | B18: 烟叶税 | C18: 0 | E18: 0 | G18: =IFERROR((F18-C18)/C18,"") | H18: =IFERROR(F18/D18,"") | I18: =IF(LEN(A18)=3,"是",IF(B18<>"",IF(SUM(C18:F18)<>0,"是","否"),"是")) -> 否
A19: 10121 | B19: 环境保护税 | C19: 0 | E19: 0 | G19: =IFERROR((F19-C19)/C19,"") | H19: =IFERROR(F19/D19,"") | I19: =IF(LEN(A19)=3,"是",IF(B19<>"",IF(SUM(C19:F19)<>0,"是","否"),"是")) -> 否
A20: 10199 | B20: 其他税收收入 | C20: 12 | E20: 0 | F20: 51 | G20: =IFERROR((F20-C20)/C20,"") -> 3.25 | H20: =IFERROR(F20/D20,"") | I20: =IF(LEN(A20)=3,"是",IF(B20<>"",IF(SUM(C20:F20)<>0,"是","否"),"是")) -> 是
A21: 103 | B21: 二、非税收入 | C21: =SUM(C22:C29) -> 193211 | D21: =SUM(D22:D29) -> 194299 | E21: =SUM(E22:E29) -> 194299 | F21: =SUM(F22:F29) -> 151528 | G21: =IFERROR((F21-C21)/C21,"") -> -0.21573823 | H21: =IFERROR(F21/D21,"") -> 0.7798702 | I21: =IF(LEN(A21)=3,"是",IF(B21<>"",IF(SUM(C21:F21)<>0,"是","否"),"是")) -> 是
A22: 10302 | B22: 专项收入 | C22: 5626 | D22: 5322 | E22: 5322 | F22: 4127 | G22: =IFERROR((F22-C22)/C22,"") -> -0.26644152 | H22: =IFERROR(F22/D22,"") -> 0.77546035 | I22: =IF(LEN(A22)=3,"是",IF(B22<>"",IF(SUM(C22:F22)<>0,"是","否"),"是")) -> 是
A23: 10304 | B23: 行政事业性收费收入 | C23: 30028 | D23: 42479 | E23: 42479 | F23: 15810 | G23: =IFERROR((F23-C23)/C23,"") -> -0.47349141 | H23: =IFERROR(F23/D23,"") -> 0.3721839 | I23: =IF(LEN(A23)=3,"是",IF(B23<>"",IF(SUM(C23:F23)<>0,"是","否"),"是")) -> 是
A24: 10305 | B24: 罚没收入 | C24: 10141 | D24: 7820 | E24: 7820 | F24: 6119 | G24: =IFERROR((F24-C24)/C24,"") -> -0.39660783 | H24: =IFERROR(F24/D24,"") -> 0.78248082 | I24: =IF(LEN(A24)=3,"是",IF(B24<>"",IF(SUM(C24:F24)<>0,"是","否"),"是")) -> 是
A25: 10306 | B25: 国有资本经营收入 | C25: 0 | G25: =IFERROR((F25-C25)/C25,"") | H25: =IFERROR(F25/D25,"") | I25: =IF(LEN(A25)=3,"是",IF(B25<>"",IF(SUM(C25:F25)<>0,"是","否"),"是")) -> 否
A26: 10307 | B26: 国有资源（资产）有偿使用收入 | C26: 140768 | D26: 131528 | E26: 131528 | F26: 117392 | G26: =IFERROR((F26-C26)/C26,"") -> -0.16606047 | H26: =IFERROR(F26/D26,"") -> 0.89252479 | I26: =IF(LEN(A26)=3,"是",IF(B26<>"",IF(SUM(C26:F26)<>0,"是","否"),"是")) -> 是
A27: 10308 | B27: 捐赠收入 | C27: 0 | G27: =IFERROR((F27-C27)/C27,"") | H27: =IFERROR(F27/D27,"") | I27: =IF(LEN(A27)=3,"是",IF(B27<>"",IF(SUM(C27:F27)<>0,"是","否"),"是")) -> 否
A28: 10309 | B28: 政府住房基金收入 | C28: 6648 | D28: 7150 | E28: 7150 | F28: 8071 | G28: =IFERROR((F28-C28)/C28,"") -> 0.21404934 | H28: =IFERROR(F28/D28,"") -> 1.1288112 | I28: =IF(LEN(A28)=3,"是",IF(B28<>"",IF(SUM(C28:F28)<>0,"是","否"),"是")) -> 是
A29: 10399 | B29: 其他收入 | C29: 0 | F29: 9 | G29: =IFERROR((F29-C29)/C29,"") | H29: =IFERROR(F29/D29,"") | I29: =IF(LEN(A29)=3,"是",IF(B29<>"",IF(SUM(C29:F29)<>0,"是","否"),"是")) -> 是
G30: =IFERROR((F30-C30)/C30,"") | H30: =IFERROR(F30/D30,"") | I30: =IF(LEN(A30)=3,"是",IF(B30<>"",IF(SUM(C30:F30)<>0,"是","否"),"是")) -> 是
B31: 市本级一般公共预算收入 | C31: =SUM(C5,C21) -> 270341 | D31: =SUM(D5,D21) -> 283858 | E31: =SUM(E5,E21) -> 283858 | F31: =SUM(F5,F21) -> 237059 | G31: =IFERROR((F31-C31)/C31,"") -> -0.12311118 | H31: =IFERROR(F31/D31,"") -> 0.83513235 | I31: =IF(LEN(A31)=3,"是",IF(B31<>"",IF(SUM(C31:F31)<>0,"是","否"),"是")) -> 是
A32: 105 | B32: 地方政府一般债务收入 | C32: 180780 | D32: 192645 | E32: 242842 | F32: 237945 | G32: =IFERROR((F32-C32)/C32,"") -> 0.31621308 | H32: =IFERROR(F32/D32,"") -> 1.2351476 | I32: =IF(LEN(A32)=3,"是",IF(B32<>"",IF(SUM(C32:F32)<>0,"是","否"),"是")) -> 是
A33: 110 | B33: 转移性收入 | C33: =SUM(C34:C41) -> 1287032 | D33: =SUM(D34:D41) -> 1311102 | E33: =SUM(E34:E41) -> 1291454 | F33: =SUM(F34:F41) -> 1247877 | G33: =IFERROR((F33-C33)/C33,"") -> -0.030422709 | H33: =IFERROR(F33/D33,"") -> 0.95177721 | I33: =IF(LEN(A33)=3,"是",IF(B33<>"",IF(SUM(C33:F33)<>0,"是","否"),"是")) -> 是
A34: 11001 | B34: 返还性收入 | C34: 41410 | D34: 40300 | E34: 40300 | F34: 44029 | G34: =IFERROR((F34-C34)/C34,"") -> 0.063245593 | H34: =IFERROR(F34/D34,"") -> 1.092531 | I34: =IF(LEN(A34)=3,"是",IF(B34<>"",IF(SUM(C34:F34)<>0,"是","否"),"是")) -> 是
B35: 一般性转移支付收入 | C35: 917106 | D35: 912417 | E35: 912417 | F35: 997380 | G35: =IFERROR((F35-C35)/C35,"") -> 0.087529686 | H35: =IFERROR(F35/D35,"") -> 1.0931186 | I35: =IF(LEN(A35)=3,"是",IF(B35<>"",IF(SUM(C35:F35)<>0,"是","否"),"是")) -> 是
B36: 专项转移支付收入 | C36: 264430 | D36: 264427 | E36: 264427 | F36: 144850 | G36: =IFERROR((F36-C36)/C36,"") -> -0.45221798 | H36: =IFERROR(F36/D36,"") -> 0.54778824 | I36: =IF(LEN(A36)=3,"是",IF(B36<>"",IF(SUM(C36:F36)<>0,"是","否"),"是")) -> 是
A37: 11006 | B37: 上解收入 | C37: 33536 | D37: 34056 | E37: 34056 | F37: 34316 | G37: =IFERROR((F37-C37)/C37,"") -> 0.023258588 | H37: =IFERROR(F37/D37,"") -> 1.0076345 | I37: =IF(LEN(A37)=3,"是",IF(B37<>"",IF(SUM(C37:F37)<>0,"是","否"),"是")) -> 是
A38: 11008 | B38: 上年结余收入 | C38: 13535 | D38: 14902 | E38: 14902 | F38: 15483 | G38: =IFERROR((F38-C38)/C38,"") -> 0.14392316 | H38: =IFERROR(F38/D38,"") -> 1.0389881 | I38: =IF(LEN(A38)=3,"是",IF(B38<>"",IF(SUM(C38:F38)<>0,"是","否"),"是")) -> 是
A39: 11009 | B39: 调入资金 | C39: 17015 | D39: 45000 | E39: 25352 | F39: 11819 | G39: =IFERROR((F39-C39)/C39,"") -> -0.30537761 | H39: =IFERROR(F39/D39,"") -> 0.26264444 | I39: =IF(LEN(A39)=3,"是",IF(B39<>"",IF(SUM(C39:F39)<>0,"是","否"),"是")) -> 是
A40: 11015 | B40: 动用预算稳定调节基金 | C40: 0 | G40: =IFERROR((F40-C40)/C40,"") | H40: =IFERROR(F40/D40,"") | I40: =IF(LEN(A40)=3,"是",IF(B40<>"",IF(SUM(C40:F40)<>0,"是","否"),"是")) -> 否
A41: 11021 | B41: 区域间转移性收入 | C41: 0 | G41: =IFERROR((F41-C41)/C41,"") | H41: =IFERROR(F41/D41,"") | I41: =IF(LEN(A41)=3,"是",IF(B41<>"",IF(SUM(C41:F41)<>0,"是","否"),"是")) -> 否
B42: 各项收入合计 | C42: =SUM(C31:C33) -> 1738153 | D42: =SUM(D31:D33) -> 1787605 | E42: =SUM(E31:E33) -> 1818154 | F42: =SUM(F31:F33) -> 1722881 | G42: =IFERROR((F42-C42)/C42,"") -> -0.0087863381 | H42: =IFERROR(F42/D42,"") -> 0.9637929 | I42: =IF(LEN(A42)=3,"是",IF(B42<>"",IF(SUM(C42:F42)<>0,"是","否"),"是")) -> 是

Sheet 03-2
B1: 2025年市本级一般公共预算收支情况表
B2: 表三 | H2: 单位：万元
A3: 科目编码 | B3: 项目 | C3: 2024年决算数 | D3: 2025年 | G3: 比较
D4: 预算数 | E4: 调整预算数 | F4: 执行数 | G4: 比2024年决算数增长% | H4: 完成2025年预算数的% | I4: 打印
A5: 201 | B5: 一、一般公共服务 | C5: 39616 | D5: 44036 | E5: 44036 | F5: ='04'!F5 -> 38632 | G5: =IFERROR((F5-C5)/C5,"") -> -0.024838449 | H5: =IFERROR(F5/D5,"") -> 0.87728222 | I5: =IF(LEN(A5)=3,"是",IF(B5<>"",IF(SUM(C5:F5)<>0,"是","否"),"是")) -> 是
A6: 202 | B6: 二、外交支出 | C6: 0 | E6: 0 | F6: ='04'!F253 -> 0 | G6: =IFERROR((F6-C6)/C6,"") | H6: =IFERROR(F6/D6,"") | I6: =IF(LEN(A6)=3,"是",IF(B6<>"",IF(SUM(C6:F6)<>0,"是","否"),"是")) -> 是
A7: 203 | B7: 三、国防支出 | C7: 770 | D7: 781 | E7: 781 | F7: ='04'!F293 -> 1279 | G7: =IFERROR((F7-C7)/C7,"") -> 0.66103896 | H7: =IFERROR(F7/D7,"") -> 1.637644 | I7: =IF(LEN(A7)=3,"是",IF(B7<>"",IF(SUM(C7:F7)<>0,"是","否"),"是")) -> 是
A8: 204 | B8: 四、公共安全支出 | C8: 18147 | D8: 18644 | E8: 18597 | F8: ='04'!F312 -> 22295 | G8: =IFERROR((F8-C8)/C8,"") -> 0.22857773 | H8: =IFERROR(F8/D8,"") -> 1.1958271 | I8: =IF(LEN(A8)=3,"是",IF(B8<>"",IF(SUM(C8:F8)<>0,"是","否"),"是")) -> 是
A9: 205 | B9: 五、教育支出 | C9: 27952 | D9: 29431 | E9: 30309 | F9: ='04'!F402 -> 38236 | G9: =IFERROR((F9-C9)/C9,"") -> 0.36791643 | H9: =IFERROR(F9/D9,"") -> 1.2991743 | I9: =IF(LEN(A9)=3,"是",IF(B9<>"",IF(SUM(C9:F9)<>0,"是","否"),"是")) -> 是
A10: 206 | B10: 六、科学技术支出 | C10: 2477 | D10: 2553 | E10: 2553 | F10: ='04'!F454 -> 3289 | G10: =IFERROR((F10-C10)/C10,"") -> 0.32781591 | H10: =IFERROR(F10/D10,"") -> 1.2882883 | I10: =IF(LEN(A10)=3,"是",IF(B10<>"",IF(SUM(C10:F10)<>0,"是","否"),"是")) -> 是
A11: 207 | B11: 七、文化旅游体育与传媒支出 | C11: 12275 | D11: 12540 | E11: 12638 | F11: ='04'!F510 -> 11167 | G11: =IFERROR((F11-C11)/C11,"") -> -0.090264766 | H11: =IFERROR(F11/D11,"") -> 0.89051037 | I11: =IF(LEN(A11)=3,"是",IF(B11<>"",IF(SUM(C11:F11)<>0,"是","否"),"是")) -> 是
A12: 208 | B12: 八、社会保障和就业支出 | C12: 59198 | D12: 61422 | E12: 61422 | F12: ='04'!F566 -> 66109 | G12: =IFERROR((F12-C12)/C12,"") -> 0.11674381 | H12: =IFERROR(F12/D12,"") -> 1.0763082 | I12: =IF(LEN(A12)=3,"是",IF(B12<>"",IF(SUM(C12:F12)<>0,"是","否"),"是")) -> 是
A13: 210 | B13: 九、卫生健康支出 | C13: 99631 | D13: 102400 | E13: 102400 | F13: ='04'!F695 -> 102305 | G13: =IFERROR((F13-C13)/C13,"") -> 0.026839036 | H13: =IFERROR(F13/D13,"") -> 0.99907227 | I13: =IF(LEN(A13)=3,"是",IF(B13<>"",IF(SUM(C13:F13)<>0,"是","否"),"是")) -> 是
A14: 211 | B14: 十、节能环保支出 | C14: 59344 | D14: 60711 | E14: 55026 | F14: ='04'!F778 -> 63120 | G14: =IFERROR((F14-C14)/C14,"") -> 0.063629011 | H14: =IFERROR(F14/D14,"") -> 1.0396798 | I14: =IF(LEN(A14)=3,"是",IF(B14<>"",IF(SUM(C14:F14)<>0,"是","否"),"是")) -> 是
A15: 212 | B15: 十一、城乡社区支出 | C15: 14200 | D15: 13722 | E15: 13121 | F15: ='04'!F850 -> 17917 | G15: =IFERROR((F15-C15)/C15,"") -> 0.26176056 | H15: =IFERROR(F15/D15,"") -> 1.3057135 | I15: =IF(LEN(A15)=3,"是",IF(B15<>"",IF(SUM(C15:F15)<>0,"是","否"),"是")) -> 是
A16: 213 | B16: 十二、农林水支出 | C16: 86730 | D16: 82615 | E16: 82358 | F16: ='04'!F873 -> 17832 | G16: =IFERROR((F16-C16)/C16,"") -> -0.7943964 | H16: =IFERROR(F16/D16,"") -> 0.21584458 | I16: =IF(LEN(A16)=3,"是",IF(B16<>"",IF(SUM(C16:F16)<>0,"是","否"),"是")) -> 是
A17: 214 | B17: 十三、交通运输支出 | C17: 21839 | D17: 22433 | E17: 17634 | F17: ='04'!F976 -> 28594 | G17: =IFERROR((F17-C17)/C17,"") -> 0.30930903 | H17: =IFERROR(F17/D17,"") -> 1.27464 | I17: =IF(LEN(A17)=3,"是",IF(B17<>"",IF(SUM(C17:F17)<>0,"是","否"),"是")) -> 是
A18: 215 | B18: 十四、资源勘探工业信息等支出 | C18: 73429 | D18: 68152 | E18: 79061 | F18: ='04'!F1028 -> 44782 | G18: =IFERROR((F18-C18)/C18,"") -> -0.39013196 | H18: =IFERROR(F18/D18,"") -> 0.65709003 | I18: =IF(LEN(A18)=3,"是",IF(B18<>"",IF(SUM(C18:F18)<>0,"是","否"),"是")) -> 是
A19: 216 | B19: 十五、商业服务业等支出 | C19: 283 | D19: 292 | E19: 292 | F19: ='04'!F1092 -> 1649 | G19: =IFERROR((F19-C19)/C19,"") -> 4.8268551 | H19: =IFERROR(F19/D19,"") -> 5.6472603 | I19: =IF(LEN(A19)=3,"是",IF(B19<>"",IF(SUM(C19:F19)<>0,"是","否"),"是")) -> 是
A20: 217 | B20: 十六、金融支出 | C20: 326 | D20: 321 | E20: 321 | F20: ='04'!F1112 -> 439 | G20: =IFERROR((F20-C20)/C20,"") -> 0.34662577 | H20: =IFERROR(F20/D20,"") -> 1.3676012 | I20: =IF(LEN(A20)=3,"是",IF(B20<>"",IF(SUM(C20:F20)<>0,"是","否"),"是")) -> 是
A21: 219 | B21: 十七、援助其他地区支出 | C21: 0 | E21: 0 | F21: ='04'!F1142 -> 0 | G21: =IFERROR((F21-C21)/C21,"") | H21: =IFERROR(F21/D21,"") | I21: =IF(LEN(A21)=3,"是",IF(B21<>"",IF(SUM(C21:F21)<>0,"是","否"),"是")) -> 是
A22: 220 | B22: 十八、自然资源海洋气象等支出 | C22: 3936 | D22: 4043 | E22: 4374 | F22: ='04'!F1152 -> 6051 | G22: =IFERROR((F22-C22)/C22,"") -> 0.53734756 | H22: =IFERROR(F22/D22,"") -> 1.4966609 | I22: =IF(LEN(A22)=3,"是",IF(B22<>"",IF(SUM(C22:F22)<>0,"是","否"),"是")) -> 是
A23: 221 | B23: 十九、住房保障支出 | C23: 10177 | D23: 10285 | E23: 10285 | F23: ='04'!F1197 -> 10227 | G23: =IFERROR((F23-C23)/C23,"") -> 0.0049130392 | H23: =IFERROR(F23/D23,"") -> 0.99436072 | I23: =IF(LEN(A23)=3,"是",IF(B23<>"",IF(SUM(C23:F23)<>0,"是","否"),"是")) -> 是
A24: 222 | B24: 二十、粮油物资储备支出 | C24: 1495 | D24: 1417 | E24: 1417 | F24: ='04'!F1216 -> 1326 | G24: =IFERROR((F24-C24)/C24,"") -> -0.11304348 | H24: =IFERROR(F24/D24,"") -> 0.93577982 | I24: =IF(LEN(A24)=3,"是",IF(B24<>"",IF(SUM(C24:F24)<>0,"是","否"),"是")) -> 是
A25: 224 | B25: 二十一、灾害防治及应急管理支出 | C25: 11818 | D25: 11410 | E25: 11935 | F25: ='04'!F1261 -> 4915 | G25: =IFERROR((F25-C25)/C25,"") -> -0.58410899 | H25: =IFERROR(F25/D25,"") -> 0.43076249 | I25: =IF(LEN(A25)=3,"是",IF(B25<>"",IF(SUM(C25:F25)<>0,"是","否"),"是")) -> 是
A26: 227 | B26: 二十二、预备费 | C26: 0 | D26: 5800 | E26: 5800 | F26: ='04'!F1311 -> 0 | G26: =IFERROR((F26-C26)/C26,"") | H26: =IFERROR(F26/D26,"") -> 0 | I26: =IF(LEN(A26)=3,"是",IF(B26<>"",IF(SUM(C26:F26)<>0,"是","否"),"是")) -> 是
A27: 232 | B27: 二十三、债务付息支出 | C27: 20273 | D27: 19358 | E27: 19358 | F27: ='04'!F1312 -> 19596 | G27: =IFERROR((F27-C27)/C27,"") -> -0.03339417 | H27: =IFERROR(F27/D27,"") -> 1.0122947 | I27: =IF(LEN(A27)=3,"是",IF(B27<>"",IF(SUM(C27:F27)<>0,"是","否"),"是")) -> 是
A28: 233 | B28: 二十四、债务发行费用支出 | C28: 90 | D28: 100 | E28: 100 | F28: ='04'!F1318 -> 138 | G28: =IFERROR((F28-C28)/C28,"") -> 0.53333333 | H28: =IFERROR(F28/D28,"") -> 1.38 | I28: =IF(LEN(A28)=3,"是",IF(B28<>"",IF(SUM(C28:F28)<>0,"是","否"),"是")) -> 是
A29: 229 | B29: 二十五、其他支出 | C29: 0 | E29: 0 | F29: ='04'!F1320 -> 12 | G29: =IFERROR((F29-C29)/C29,"") | H29: =IFERROR(F29/D29,"") | I29: =IF(LEN(A29)=3,"是",IF(B29<>"",IF(SUM(C29:F29)<>0,"是","否"),"是")) -> 是
G30: =IFERROR((F30-C30)/C30,"") | H30: =IFERROR(F30/D30,"") | I30: =IF(LEN(A30)=3,"是",IF(B30<>"",IF(SUM(C30:F30)<>0,"是","否"),"是")) -> 是
B31: 市本级一般公共预算支出 | C31: =SUM(C5:C29) -> 564006 | D31: =SUM(D5:D29) -> 572466 | E31: =SUM(E5:E29) -> 573818 | F31: =SUM(F5:F29) -> 499910 | G31: =IFERROR((F31-C31)/C31,"") -> -0.11364418 | H31: =IFERROR(F31/D31,"") -> 0.8732571 | I31: =IF(LEN(A31)=3,"是",IF(B31<>"",IF(SUM(C31:F31)<>0,"是","否"),"是")) -> 是
A32: 230 | B32: 转移性支出 | C32: =SUM(C33:C40) -> 1082458 | D32: =SUM(D33:D40) -> 1093289 | E32: =SUM(E33:E40) -> 1117486 | F32: =SUM(F33:F40) -> 1085140 | G32: =IFERROR((F32-C32)/C32,"") -> 0.0024776943 | H32: =IFERROR(F32/D32,"") -> 0.99254634 | I32: =IF(LEN(A32)=3,"是",IF(B32<>"",IF(SUM(C32:F32)<>0,"是","否"),"是")) -> 是
A33: 23001 | B33: 返还性支出 | C33: 23501 | D33: 23784 | E33: 23784 | F33: 25249 | G33: =IFERROR((F33-C33)/C33,"") -> 0.074379814 | H33: =IFERROR(F33/D33,"") -> 1.061596 | I33: =IF(LEN(A33)=3,"是",IF(B33<>"",IF(SUM(C33:F33)<>0,"是","否"),"是")) -> 是
B34: 一般性转移支付支出 | C34: 745563 | D34: 770227 | E34: 770227 | F34: 785932 | G34: =IFERROR((F34-C34)/C34,"") -> 0.054145659 | H34: =IFERROR(F34/D34,"") -> 1.0203901 | I34: =IF(LEN(A34)=3,"是",IF(B34<>"",IF(SUM(C34:F34)<>0,"是","否"),"是")) -> 是
B35: 专项转移支付支出 | C35: 184676 | D35: 182414 | E35: 182414 | F35: 136446 | G35: =IFERROR((F35-C35)/C35,"") -> -0.26116009 | H35: =IFERROR(F35/D35,"") -> 0.7480018 | I35: =IF(LEN(A35)=3,"是",IF(B35<>"",IF(SUM(C35:F35)<>0,"是","否"),"是")) -> 是
A36: 23006 | B36: 上解支出 | C36: 33648 | D36: 33869 | E36: 33869 | F36: 35218 | G36: =IFERROR((F36-C36)/C36,"") -> 0.046659534 | H36: =IFERROR(F36/D36,"") -> 1.0398299 | I36: =IF(LEN(A36)=3,"是",IF(B36<>"",IF(SUM(C36:F36)<>0,"是","否"),"是")) -> 是
A37: 23008 | B37: 调出资金 | C37: 0 | G37: =IFERROR((F37-C37)/C37,"") | H37: =IFERROR(F37/D37,"") | I37: =IF(LEN(A37)=3,"是",IF(B37<>"",IF(SUM(C37:F37)<>0,"是","否"),"是")) -> 否
A38: 2301101 | B38: 地方政府一般债务转贷支出 | C38: 95070 | D38: 82995 | E38: 107192 | F38: 102295 | G38: =IFERROR((F38-C38)/C38,"") -> 0.075996634 | H38: =IFERROR(F38/D38,"") -> 1.2325441 | I38: =IF(LEN(A38)=3,"是",IF(B38<>"",IF(SUM(C38:F38)<>0,"是","否"),"是")) -> 是
A39: 23015 | B39: 安排预算稳定调节基金 | C39: 0 | G39: =IFERROR((F39-C39)/C39,"") | H39: =IFERROR(F39/D39,"") | I39: =IF(LEN(A39)=3,"是",IF(B39<>"",IF(SUM(C39:F39)<>0,"是","否"),"是")) -> 否
A40: 23016 | B40: 补充预算周转金 | C40: 0 | G40: =IFERROR((F40-C40)/C40,"") | H40: =IFERROR(F40/D40,"") | I40: =IF(LEN(A40)=3,"是",IF(B40<>"",IF(SUM(C40:F40)<>0,"是","否"),"是")) -> 否
A41: 231 | B41: 地方政府一般债务还本支出 | C41: 76206 | D41: 121850 | E41: 126850 | F41: 126856 | G41: =IFERROR((F41-C41)/C41,"") -> 0.66464583 | H41: =IFERROR(F41/D41,"") -> 1.0410833 | I41: =IF(LEN(A41)=3,"是",IF(B41<>"",IF(SUM(C41:F41)<>0,"是","否"),"是")) -> 是
A42: 23021 | B42: 区域间转移性支出 | G42: =IFERROR((F42-C42)/C42,"") | H42: =IFERROR(F42/D42,"") | I42: =IF(LEN(A42)=3,"是",IF(B42<>"",IF(SUM(C42:F42)<>0,"是","否"),"是")) -> 否
A43: 23009 | B43: 年终结转 | C43: 15483 | F43: 10975 | G43: =IFERROR((F43-C43)/C43,"") -> -0.29115804 | H43: =IFERROR(F43/D43,"") | I43: =IF(LEN(A43)=3,"是",IF(B43<>"",IF(SUM(C43:F43)<>0,"是","否"),"是")) -> 是
B44: 各项支出合计 | C44: =SUM(C31:C32,C41:C43) -> 1738153 | D44: =SUM(D31:D32,D41:D43) -> 1787605 | E44: =SUM(E31:E32,E41:E43) -> 1818154 | F44: =SUM(F31:F32,F41:F43) -> 1722881 | G44: =IFERROR((F44-C44)/C44,"") -> -0.0087863381 | H44: =IFERROR(F44/D44,"") -> 0.9637929 | I44: =IF(LEN(A44)=3,"是",IF(B44<>"",IF(SUM(C44:F44)<>0,"是","否"),"是")) -> 是

Sheet 04
B1: 2025年市本级一般公共预算支出执行情况表
B2: 表四 | H2: 单位：万元
A3: 科目编码 | B3: 项目 | C3: 2024年决算数 | D3: 2025年 | G3: 比较
D4: 预算数 | E4: 调整预算数 | F4: 执行数 | G4: 比2024年决算数增长% | H4: 完成2025年预算数的% | I4: 打印 | J4: 类-款-项
A5: 201 | B5: 一、一般公共服务支出 | C5: 39616 | D5: =D6+D18+D27+D37+D48+D59+D70+D78+D87+D100+D109+D120+D132+D139+D147+D153+D160+D167+D174+D181+D188+D196+D202+D208+D215+D230+D237+D250 -> 44036 | E5: =E6+E18+E27+E37+E48+E59+E70+E78+E87+E100+E109+E120+E132+E139+E147+E153+E160+E167+E174+E181+E188+E196+E202+E208+E215+E230+E237+E250 -> 44036 | F5: =F6+F18+F27+F37+F48+F59+F70+F78+F87+F100+F109+F120+F132+F139+F147+F153+F160+F167+F174+F181+F188+F196+F202+F208+F215+F230+F237+F250 -> 38632 | G5: =IFERROR((F5-C5)/C5,"") -> -0.024838449 | H5: =IFERROR(F5/D5,"") -> 0.87728222 | I5: =IF(LEN(A5)=3,"是",IF(B5<>"",IF(SUM(C5:F5)<>0,"是","否"),"是")) -> 是 | J5: =IF(LEN(A5)=3,"类",IF(LEN(A5)=5,"款","项")) -> 类
A6: 20101 | B6: 人大事务 | C6: 1685 | D6: =SUM(D7:D17) -> 1847 | E6: =SUM(E7:E17) -> 1847 | F6: =SUM(F7:F17) -> 1558 | G6: =IFERROR((F6-C6)/C6,"") -> -0.07537092 | H6: =IFERROR(F6/D6,"") -> 0.84353005 | I6: =IF(LEN(A6)=3,"是",IF(B6<>"",IF(SUM(C6:F6)<>0,"是","否"),"是")) -> 是 | J6: =IF(LEN(A6)=3,"类",IF(LEN(A6)=5,"款","项")) -> 款
A7: 2010101 | B7: 行政运行 | C7: 1405 | D7: 1512 | E7: 1512 | F7: 1243 | G7: =IFERROR((F7-C7)/C7,"") -> -0.11530249 | H7: =IFERROR(F7/D7,"") -> 0.82208995 | I7: =IF(LEN(A7)=3,"是",IF(B7<>"",IF(SUM(C7:F7)<>0,"是","否"),"是")) -> 是 | J7: =IF(LEN(A7)=3,"类",IF(LEN(A7)=5,"款","项")) -> 项
A8: 2010102 | B8: 一般行政管理事务 | C8: 82 | D8: 86 | E8: 86 | F8: 42 | G8: =IFERROR((F8-C8)/C8,"") -> -0.48780488 | H8: =IFERROR(F8/D8,"") -> 0.48837209 | I8: =IF(LEN(A8)=3,"是",IF(B8<>"",IF(SUM(C8:F8)<>0,"是","否"),"是")) -> 是 | J8: =IF(LEN(A8)=3,"类",IF(LEN(A8)=5,"款","项")) -> 项
A9: 2010103 | B9: 机关服务 | C9: 57 | D9: 60 | E9: 60 | F9: 54 | G9: =IFERROR((F9-C9)/C9,"") -> -0.052631579 | H9: =IFERROR(F9/D9,"") -> 0.9 | I9: =IF(LEN(A9)=3,"是",IF(B9<>"",IF(SUM(C9:F9)<>0,"是","否"),"是")) -> 是 | J9: =IF(LEN(A9)=3,"类",IF(LEN(A9)=5,"款","项")) -> 项
A10: 2010104 | B10: 人大会议 | C10: 97 | D10: 120 | E10: 120 | F10: 99 | G10: =IFERROR((F10-C10)/C10,"") -> 0.020618557 | H10: =IFERROR(F10/D10,"") -> 0.825 | I10: =IF(LEN(A10)=3,"是",IF(B10<>"",IF(SUM(C10:F10)<>0,"是","否"),"是")) -> 是 | J10: =IF(LEN(A10)=3,"类",IF(LEN(A10)=5,"款","项")) -> 项
A11: 2010105 | B11: 人大立法 | C11: 0 | D11: 0 | E11: 0 | F11: 0 | G11: =IFERROR((F11-C11)/C11,"") | H11: =IFERROR(F11/D11,"") | I11: =IF(LEN(A11)=3,"是",IF(B11<>"",IF(SUM(C11:F11)<>0,"是","否"),"是")) -> 否 | J11: =IF(LEN(A11)=3,"类",IF(LEN(A11)=5,"款","项")) -> 项
A12: 2010106 | B12: 人大监督 | C12: 0 | D12: 0 | E12: 0 | F12: 0 | G12: =IFERROR((F12-C12)/C12,"") | H12: =IFERROR(F12/D12,"") | I12: =IF(LEN(A12)=3,"是",IF(B12<>"",IF(SUM(C12:F12)<>0,"是","否"),"是")) -> 否 | J12: =IF(LEN(A12)=3,"类",IF(LEN(A12)=5,"款","项")) -> 项
A13: 2010107 | B13: 人大代表履职能力提升 | C13: 9 | D13: 28 | E13: 28 | F13: 26 | G13: =IFERROR((F13-C13)/C13,"") -> 1.8888889 | H13: =IFERROR(F13/D13,"") -> 0.92857143 | I13: =IF(LEN(A13)=3,"是",IF(B13<>"",IF(SUM(C13:F13)<>0,"是","否"),"是")) -> 是 | J13: =IF(LEN(A13)=3,"类",IF(LEN(A13)=5,"款","项")) -> 项
A14: 2010108 | B14: 代表工作 | C14: 0 | D14: 0 | E14: 0 | F14: 9 | G14: =IFERROR((F14-C14)/C14,"") | H14: =IFERROR(F14/D14,"") | I14: =IF(LEN(A14)=3,"是",IF(B14<>"",IF(SUM(C14:F14)<>0,"是","否"),"是")) -> 是 | J14: =IF(LEN(A14)=3,"类",IF(LEN(A14)=5,"款","项")) -> 项
A15: 2010109 | B15: 人大信访工作 | C15: 0 | D15: 0 | E15: 0 | F15: 0 | G15: =IFERROR((F15-C15)/C15,"") | H15: =IFERROR(F15/D15,"") | I15: =IF(LEN(A15)=3,"是",IF(B15<>"",IF(SUM(C15:F15)<>0,"是","否"),"是")) -> 否 | J15: =IF(LEN(A15)=3,"类",IF(LEN(A15)=5,"款","项")) -> 项
A16: 2010150 | B16: 事业运行 | C16: 0 | D16: 0 | E16: 0 | F16: 0 | G16: =IFERROR((F16-C16)/C16,"") | H16: =IFERROR(F16/D16,"") | I16: =IF(LEN(A16)=3,"是",IF(B16<>"",IF(SUM(C16:F16)<>0,"是","否"),"是")) -> 否 | J16: =IF(LEN(A16)=3,"类",IF(LEN(A16)=5,"款","项")) -> 项
A17: 2010199 | B17: 其他人大事务支出 | C17: 35 | D17: 41 | E17: 41 | F17: 85 | G17: =IFERROR((F17-C17)/C17,"") -> 1.4285714 | H17: =IFERROR(F17/D17,"") -> 2.0731707 | I17: =IF(LEN(A17)=3,"是",IF(B17<>"",IF(SUM(C17:F17)<>0,"是","否"),"是")) -> 是 | J17: =IF(LEN(A17)=3,"类",IF(LEN(A17)=5,"款","项")) -> 项
A18: 20102 | B18: 政协事务 | C18: 1481 | D18: =SUM(D19:D26) -> 1598 | E18: =SUM(E19:E26) -> 1598 | F18: =SUM(F19:F26) -> 1613 | G18: =IFERROR((F18-C18)/C18,"") -> 0.089128967 | H18: =IFERROR(F18/D18,"") -> 1.0093867 | I18: =IF(LEN(A18)=3,"是",IF(B18<>"",IF(SUM(C18:F18)<>0,"是","否"),"是")) -> 是 | J18: =IF(LEN(A18)=3,"类",IF(LEN(A18)=5,"款","项")) -> 款
A19: 2010201 | B19: 行政运行 | C19: 1305 | D19: 1403 | E19: 1403 | F19: 1529 | G19: =IFERROR((F19-C19)/C19,"") -> 0.17164751 | H19: =IFERROR(F19/D19,"") -> 1.0898076 | I19: =IF(LEN(A19)=3,"是",IF(B19<>"",IF(SUM(C19:F19)<>0,"是","否"),"是")) -> 是 | J19: =IF(LEN(A19)=3,"类",IF(LEN(A19)=5,"款","项")) -> 项
A20: 2010202 | B20: 一般行政管理事务 | C20: 47 | D20: 51 | E20: 51 | F20: 21 | G20: =IFERROR((F20-C20)/C20,"") -> -0.55319149 | H20: =IFERROR(F20/D20,"") -> 0.41176471 | I20: =IF(LEN(A20)=3,"是",IF(B20<>"",IF(SUM(C20:F20)<>0,"是","否"),"是")) -> 是 | J20: =IF(LEN(A20)=3,"类",IF(LEN(A20)=5,"款","项")) -> 项
A21: 2010203 | B21: 机关服务 | C21: 0 | D21: 0 | E21: 0 | F21: 0 | G21: =IFERROR((F21-C21)/C21,"") | H21: =IFERROR(F21/D21,"") | I21: =IF(LEN(A21)=3,"是",IF(B21<>"",IF(SUM(C21:F21)<>0,"是","否"),"是")) -> 否 | J21: =IF(LEN(A21)=3,"类",IF(LEN(A21)=5,"款","项")) -> 项
A22: 2010204 | B22: 政协会议 | C22: 75 | D22: 81 | E22: 81 | F22: 0 | G22: =IFERROR((F22-C22)/C22,"") -> -1 | H22: =IFERROR(F22/D22,"") -> 0 | I22: =IF(LEN(A22)=3,"是",IF(B22<>"",IF(SUM(C22:F22)<>0,"是","否"),"是")) -> 是 | J22: =IF(LEN(A22)=3,"类",IF(LEN(A22)=5,"款","项")) -> 项
A23: 2010205 | B23: 委员视察 | C23: 0 | D23: 0 | E23: 0 | F23: 0 | G23: =IFERROR((F23-C23)/C23,"") | H23: =IFERROR(F23/D23,"") | I23: =IF(LEN(A23)=3,"是",IF(B23<>"",IF(SUM(C23:F23)<>0,"是","否"),"是")) -> 否 | J23: =IF(LEN(A23)=3,"类",IF(LEN(A23)=5,"款","项")) -> 项
A24: 2010206 | B24: 参政议政 | C24: 15 | D24: 18 | E24: 18 | F24: 11 | G24: =IFERROR((F24-C24)/C24,"") -> -0.26666667 | H24: =IFERROR(F24/D24,"") -> 0.61111111 | I24: =IF(LEN(A24)=3,"是",IF(B24<>"",IF(SUM(C24:F24)<>0,"是","否"),"是")) -> 是 | J24: =IF(LEN(A24)=3,"类",IF(LEN(A24)=5,"款","项")) -> 项
A25: 2010250 | B25: 事业运行 | C25: 0 | D25: 0 | E25: 0 | F25: 0 | G25: =IFERROR((F25-C25)/C25,"") | H25: =IFERROR(F25/D25,"") | I25: =IF(LEN(A25)=3,"是",IF(B25<>"",IF(SUM(C25:F25)<>0,"是","否"),"是")) -> 否 | J25: =IF(LEN(A25)=3,"类",IF(LEN(A25)=5,"款","项")) -> 项
A26: 2010299 | B26: 其他政协事务支出 | C26: 39 | D26: 45 | E26: 45 | F26: 52 | G26: =IFERROR((F26-C26)/C26,"") -> 0.33333333 | H26: =IFERROR(F26/D26,"") -> 1.1555556 | I26: =IF(LEN(A26)=3,"是",IF(B26<>"",IF(SUM(C26:F26)<>0,"是","否"),"是")) -> 是 | J26: =IF(LEN(A26)=3,"类",IF(LEN(A26)=5,"款","项")) -> 项
A27: 20103 | B27: 政府办公厅(室)及相关机构事务 | C27: 7638 | D27: =SUM(D28:D36) -> 8020 | E27: =SUM(E28:E36) -> 8020 | F27: =SUM(F28:F36) -> 7190 | G27: =IFERROR((F27-C27)/C27,"") -> -0.058654098 | H27: =IFERROR(F27/D27,"") -> 0.89650873 | I27: =IF(LEN(A27)=3,"是",IF(B27<>"",IF(SUM(C27:F27)<>0,"是","否"),"是")) -> 是 | J27: =IF(LEN(A27)=3,"类",IF(LEN(A27)=5,"款","项")) -> 款
A28: 2010301 | B28: 行政运行 | C28: 3457 | D28: 3568 | E28: 3568 | F28: 3412 | G28: =IFERROR((F28-C28)/C28,"") -> -0.013017067 | H28: =IFERROR(F28/D28,"") -> 0.95627803 | I28: =IF(LEN(A28)=3,"是",IF(B28<>"",IF(SUM(C28:F28)<>0,"是","否"),"是")) -> 是 | J28: =IF(LEN(A28)=3,"类",IF(LEN(A28)=5,"款","项")) -> 项
A29: 2010302 | B29: 一般行政管理事务 | C29: 381 | D29: 383 | E29: 383 | F29: 406 | G29: =IFERROR((F29-C29)/C29,"") -> 0.065616798 | H29: =IFERROR(F29/D29,"") -> 1.0600522 | I29: =IF(LEN(A29)=3,"是",IF(B29<>"",IF(SUM(C29:F29)<>0,"是","否"),"是")) -> 是 | J29: =IF(LEN(A29)=3,"类",IF(LEN(A29)=5,"款","项")) -> 项
A30: 2010303 | B30: 机关服务 | C30: 0 | D30: 0 | E30: 0 | F30: 0 | G30: =IFERROR((F30-C30)/C30,"") | H30: =IFERROR(F30/D30,"") | I30: =IF(LEN(A30)=3,"是",IF(B30<>"",IF(SUM(C30:F30)<>0,"是","否"),"是")) -> 否 | J30: =IF(LEN(A30)=3,"类",IF(LEN(A30)=5,"款","项")) -> 项
A31: 2010304 | B31: 专项服务 | C31: 0 | D31: 0 | E31: 0 | F31: 0 | G31: =IFERROR((F31-C31)/C31,"") | H31: =IFERROR(F31/D31,"") | I31: =IF(LEN(A31)=3,"是",IF(B31<>"",IF(SUM(C31:F31)<>0,"是","否"),"是")) -> 否 | J31: =IF(LEN(A31)=3,"类",IF(LEN(A31)=5,"款","项")) -> 项
A32: 2010305 | B32: 专项业务及机关事务管理 | C32: 0 | D32: 0 | E32: 0 | F32: 0 | G32: =IFERROR((F32-C32)/C32,"") | H32: =IFERROR(F32/D32,"") | I32: =IF(LEN(A32)=3,"是",IF(B32<>"",IF(SUM(C32:F32)<>0,"是","否"),"是")) -> 否 | J32: =IF(LEN(A32)=3,"类",IF(LEN(A32)=5,"款","项")) -> 项
A33: 2010306 | B33: 政务公开审批 | C33: 0 | D33: 0 | E33: 0 | F33: 0 | G33: =IFERROR((F33-C33)/C33,"") | H33: =IFERROR(F33/D33,"") | I33: =IF(LEN(A33)=3,"是",IF(B33<>"",IF(SUM(C33:F33)<>0,"是","否"),"是")) -> 否 | J33: =IF(LEN(A33)=3,"类",IF(LEN(A33)=5,"款","项")) -> 项
A34: 2010309 | B34: 参事事务 | C34: 15 | D34: 15 | E34: 15 | F34: 9 | G34: =IFERROR((F34-C34)/C34,"") -> -0.4 | H34: =IFERROR(F34/D34,"") -> 0.6 | I34: =IF(LEN(A34)=3,"是",IF(B34<>"",IF(SUM(C34:F34)<>0,"是","否"),"是")) -> 是 | J34: =IF(LEN(A34)=3,"类",IF(LEN(A34)=5,"款","项")) -> 项
A35: 2010350 | B35: 事业运行 | C35: 1515 | D35: 1842 | E35: 1842 | F35: 1632 | G35: =IFERROR((F35-C35)/C35,"") -> 0.077227723 | H35: =IFERROR(F35/D35,"") -> 0.88599349 | I35: =IF(LEN(A35)=3,"是",IF(B35<>"",IF(SUM(C35:F35)<>0,"是","否"),"是")) -> 是 | J35: =IF(LEN(A35)=3,"类",IF(LEN(A35)=5,"款","项")) -> 项
A36: 2010399 | B36: 其他政府办公厅（室）及相关机构事务支出 | C36: 2270 | D36: 2212 | E36: 2212 | F36: 1731 | G36: =IFERROR((F36-C36)/C36,"") -> -0.23744493 | H36: =IFERROR(F36/D36,"") -> 0.78254973 | I36: =IF(LEN(A36)=3,"是",IF(B36<>"",IF(SUM(C36:F36)<>0,"是","否"),"是")) -> 是 | J36: =IF(LEN(A36)=3,"类",IF(LEN(A36)=5,"款","项")) -> 项
A37: 20104 | B37: 发展与改革事务 | C37: 1660 | D37: =SUM(D38:D47) -> 1769 | E37: =SUM(E38:E47) -> 1769 | F37: =SUM(F38:F47) -> 2161 | G37: =IFERROR((F37-C37)/C37,"") -> 0.30180723 | H37: =IFERROR(F37/D37,"") -> 1.2215941 | I37: =IF(LEN(A37)=3,"是",IF(B37<>"",IF(SUM(C37:F37)<>0,"是","否"),"是")) -> 是 | J37: =IF(LEN(A37)=3,"类",IF(LEN(A37)=5,"款","项")) -> 款
A38: 2010401 | B38: 行政运行 | C38: 1148 | D38: 1243 | E38: 1243 | F38: 1092 | G38: =IFERROR((F38-C38)/C38,"") -> -0.048780488 | H38: =IFERROR(F38/D38,"") -> 0.87851971 | I38: =IF(LEN(A38)=3,"是",IF(B38<>"",IF(SUM(C38:F38)<>0,"是","否"),"是")) -> 是 | J38: =IF(LEN(A38)=3,"类",IF(LEN(A38)=5,"款","项")) -> 项
A39: 2010402 | B39: 一般行政管理事务 | C39: 0 | D39: 0 | E39: 0 | F39: 0 | G39: =IFERROR((F39-C39)/C39,"") | H39: =IFERROR(F39/D39,"") | I39: =IF(LEN(A39)=3,"是",IF(B39<>"",IF(SUM(C39:F39)<>0,"是","否"),"是")) -> 否 | J39: =IF(LEN(A39)=3,"类",IF(LEN(A39)=5,"款","项")) -> 项
A40: 2010403 | B40: 机关服务 | C40: 0 | D40: 0 | E40: 0 | F40: 0 | G40: =IFERROR((F40-C40)/C40,"") | H40: =IFERROR(F40/D40,"") | I40: =IF(LEN(A40)=3,"是",IF(B40<>"",IF(SUM(C40:F40)<>0,"是","否"),"是")) -> 否 | J40: =IF(LEN(A40)=3,"类",IF(LEN(A40)=5,"款","项")) -> 项
A41: 2010404 | B41: 战略规划与实施 | C41: 0 | D41: 0 | E41: 0 | F41: 0 | G41: =IFERROR((F41-C41)/C41,"") | H41: =IFERROR(F41/D41,"") | I41: =IF(LEN(A41)=3,"是",IF(B41<>"",IF(SUM(C41:F41)<>0,"是","否"),"是")) -> 否 | J41: =IF(LEN(A41)=3,"类",IF(LEN(A41)=5,"款","项")) -> 项
A42: 2010405 | B42: 日常经济运行调节 | C42: 0 | D42: 0 | E42: 0 | F42: 0 | G42: =IFERROR((F42-C42)/C42,"") | H42: =IFERROR(F42/D42,"") | I42: =IF(LEN(A42)=3,"是",IF(B42<>"",IF(SUM(C42:F42)<>0,"是","否"),"是")) -> 否 | J42: =IF(LEN(A42)=3,"类",IF(LEN(A42)=5,"款","项")) -> 项
A43: 2010406 | B43: 社会事业发展规划 | C43: 206 | D43: 195 | E43: 195 | F43: 0 | G43: =IFERROR((F43-C43)/C43,"") -> -1 | H43: =IFERROR(F43/D43,"") -> 0 | I43: =IF(LEN(A43)=3,"是",IF(B43<>"",IF(SUM(C43:F43)<>0,"是","否"),"是")) -> 是 | J43: =IF(LEN(A43)=3,"类",IF(LEN(A43)=5,"款","项")) -> 项
A44: 2010407 | B44: 经济体制改革研究 | C44: 0 | D44: 0 | E44: 0 | F44: 0 | G44: =IFERROR((F44-C44)/C44,"") | H44: =IFERROR(F44/D44,"") | I44: =IF(LEN(A44)=3,"是",IF(B44<>"",IF(SUM(C44:F44)<>0,"是","否"),"是")) -> 否 | J44: =IF(LEN(A44)=3,"类",IF(LEN(A44)=5,"款","项")) -> 项
A45: 2010408 | B45: 物价管理 | C45: 0 | D45: 0 | E45: 0 | F45: 0 | G45: =IFERROR((F45-C45)/C45,"") | H45: =IFERROR(F45/D45,"") | I45: =IF(LEN(A45)=3,"是",IF(B45<>"",IF(SUM(C45:F45)<>0,"是","否"),"是")) -> 否 | J45: =IF(LEN(A45)=3,"类",IF(LEN(A45)=5,"款","项")) -> 项
A46: 2010450 | B46: 事业运行 | C46: 110 | D46: 138 | E46: 138 | F46: 148 | G46: =IFERROR((F46-C46)/C46,"") -> 0.34545455 | H46: =IFERROR(F46/D46,"") -> 1.0724638 | I46: =IF(LEN(A46)=3,"是",IF(B46<>"",IF(SUM(C46:F46)<>0,"是","否"),"是")) -> 是 | J46: =IF(LEN(A46)=3,"类",IF(LEN(A46)=5,"款","项")) -> 项
A47: 2010499 | B47: 其他发展与改革事务支出 | C47: 196 | D47: 193 | E47: 193 | F47: 921 | G47: =IFERROR((F47-C47)/C47,"") -> 3.6989796 | H47: =IFERROR(F47/D47,"") -> 4.7720207 | I47: =IF(LEN(A47)=3,"是",IF(B47<>"",IF(SUM(C47:F47)<>0,"是","否"),"是")) -> 是 | J47: =IF(LEN(A47)=3,"类",IF(LEN(A47)=5,"款","项")) -> 项
A48: 20105 | B48: 统计信息事务 | C48: 792 | D48: =SUM(D49:D58) -> 823 | E48: =SUM(E49:E58) -> 823 | F48: =SUM(F49:F58) -> 791 | G48: =IFERROR((F48-C48)/C48,"") -> -0.0012626263 | H48: =IFERROR(F48/D48,"") -> 0.96111786 | I48: =IF(LEN(A48)=3,"是",IF(B48<>"",IF(SUM(C48:F48)<>0,"是","否"),"是")) -> 是 | J48: =IF(LEN(A48)=3,"类",IF(LEN(A48)=5,"款","项")) -> 款
A49: 2010501 | B49: 行政运行 | C49: 351 | D49: 375 | E49: 375 | F49: 475 | G49: =IFERROR((F49-C49)/C49,"") -> 0.35327635 | H49: =IFERROR(F49/D49,"") -> 1.2666667 | I49: =IF(LEN(A49)=3,"是",IF(B49<>"",IF(SUM(C49:F49)<>0,"是","否"),"是")) -> 是 | J49: =IF(LEN(A49)=3,"类",IF(LEN(A49)=5,"款","项")) -> 项
A50: 2010502 | B50: 一般行政管理事务 | C50: 16 | D50: 33 | E50: 33 | F50: 40 | G50: =IFERROR((F50-C50)/C50,"") -> 1.5 | H50: =IFERROR(F50/D50,"") -> 1.2121212 | I50: =IF(LEN(A50)=3,"是",IF(B50<>"",IF(SUM(C50:F50)<>0,"是","否"),"是")) -> 是 | J50: =IF(LEN(A50)=3,"类",IF(LEN(A50)=5,"款","项")) -> 项
A51: 2010503 | B51: 机关服务 | C51: 0 | D51: 0 | E51: 0 | F51: 0 | G51: =IFERROR((F51-C51)/C51,"") | H51: =IFERROR(F51/D51,"") | I51: =IF(LEN(A51)=3,"是",IF(B51<>"",IF(SUM(C51:F51)<>0,"是","否"),"是")) -> 否 | J51: =IF(LEN(A51)=3,"类",IF(LEN(A51)=5,"款","项")) -> 项
A52: 2010504 | B52: 信息事务 | C52: 0 | D52: 0 | E52: 0 | F52: 0 | G52: =IFERROR((F52-C52)/C52,"") | H52: =IFERROR(F52/D52,"") | I52: =IF(LEN(A52)=3,"是",IF(B52<>"",IF(SUM(C52:F52)<>0,"是","否"),"是")) -> 否 | J52: =IF(LEN(A52)=3,"类",IF(LEN(A52)=5,"款","项")) -> 项
A53: 2010505 | B53: 专项统计业务 | C53: 29 | D53: 0 | E53: 0 | F53: 1 | G53: =IFERROR((F53-C53)/C53,"") -> -0.96551724 | H53: =IFERROR(F53/D53,"") | I53: =IF(LEN(A53)=3,"是",IF(B53<>"",IF(SUM(C53:F53)<>0,"是","否"),"是")) -> 是 | J53: =IF(LEN(A53)=3,"类",IF(LEN(A53)=5,"款","项")) -> 项
A54: 2010506 | B54: 统计管理 | C54: 5 | D54: 5 | E54: 5 | F54: 8 | G54: =IFERROR((F54-C54)/C54,"") -> 0.6 | H54: =IFERROR(F54/D54,"") -> 1.6 | I54: =IF(LEN(A54)=3,"是",IF(B54<>"",IF(SUM(C54:F54)<>0,"是","否"),"是")) -> 是 | J54: =IF(LEN(A54)=3,"类",IF(LEN(A54)=5,"款","项")) -> 项
A55: 2010507 | B55: 专项普查活动 | C55: 53 | D55: 65 | E55: 65 | F55: 65 | G55: =IFERROR((F55-C55)/C55,"") -> 0.22641509 | H55: =IFERROR(F55/D55,"") -> 1 | I55: =IF(LEN(A55)=3,"是",IF(B55<>"",IF(SUM(C55:F55)<>0,"是","否"),"是")) -> 是 | J55: =IF(LEN(A55)=3,"类",IF(LEN(A55)=5,"款","项")) -> 项
A56: 2010508 | B56: 统计抽样调查 | C56: 171 | D56: 165 | E56: 165 | F56: 41 | G56: =IFERROR((F56-C56)/C56,"") -> -0.76023392 | H56: =IFERROR(F56/D56,"") -> 0.24848485 | I56: =IF(LEN(A56)=3,"是",IF(B56<>"",IF(SUM(C56:F56)<>0,"是","否"),"是")) -> 是 | J56: =IF(LEN(A56)=3,"类",IF(LEN(A56)=5,"款","项")) -> 项
A57: 2010550 | B57: 事业运行 | C57: 147 | D57: 160 | E57: 160 | F57: 161 | G57: =IFERROR((F57-C57)/C57,"") -> 0.095238095 | H57: =IFERROR(F57/D57,"") -> 1.00625 | I57: =IF(LEN(A57)=3,"是",IF(B57<>"",IF(SUM(C57:F57)<>0,"是","否"),"是")) -> 是 | J57: =IF(LEN(A57)=3,"类",IF(LEN(A57)=5,"款","项")) -> 项
A58: 2010599 | B58: 其他统计信息事务支出 | C58: 20 | D58: 20 | E58: 20 | F58: 0 | G58: =IFERROR((F58-C58)/C58,"") -> -1 | H58: =IFERROR(F58/D58,"") -> 0 | I58: =IF(LEN(A58)=3,"是",IF(B58<>"",IF(SUM(C58:F58)<>0,"是","否"),"是")) -> 是 | J58: =IF(LEN(A58)=3,"类",IF(LEN(A58)=5,"款","项")) -> 项
A59: 20106 | B59: 财政事务 | C59: 2682 | D59: =SUM(D60:D69) -> 2878 | E59: =SUM(E60:E69) -> 2878 | F59: =SUM(F60:F69) -> 2577 | G59: =IFERROR((F59-C59)/C59,"") -> -0.039149888 | H59: =IFERROR(F59/D59,"") -> 0.89541348 | I59: =IF(LEN(A59)=3,"是",IF(B59<>"",IF(SUM(C59:F59)<>0,"是","否"),"是")) -> 是 | J59: =IF(LEN(A59)=3,"类",IF(LEN(A59)=5,"款","项")) -> 款
A60: 2010601 | B60: 行政运行 | C60: 1505 | D60: 1632 | E60: 1632 | F60: 1436 | G60: =IFERROR((F60-C60)/C60,"") -> -0.045847176 | H60: =IFERROR(F60/D60,"") -> 0.87990196 | I60: =IF(LEN(A60)=3,"是",IF(B60<>"",IF(SUM(C60:F60)<>0,"是","否"),"是")) -> 是 | J60: =IF(LEN(A60)=3,"类",IF(LEN(A60)=5,"款","项")) -> 项
A61: 2010602 | B61: 一般行政管理事务 | C61: 225 | D61: 248 | E61: 248 | F61: 0 | G61: =IFERROR((F61-C61)/C61,"") -> -1 | H61: =IFERROR(F61/D61,"") -> 0 | I61: =IF(LEN(A61)=3,"是",IF(B61<>"",IF(SUM(C61:F61)<>0,"是","否"),"是")) -> 是 | J61: =IF(LEN(A61)=3,"类",IF(LEN(A61)=5,"款","项")) -> 项
A62: 2010603 | B62: 机关服务 | C62: 0 | D62: 0 | E62: 0 | F62: 0 | G62: =IFERROR((F62-C62)/C62,"") | H62: =IFERROR(F62/D62,"") | I62: =IF(LEN(A62)=3,"是",IF(B62<>"",IF(SUM(C62:F62)<>0,"是","否"),"是")) -> 否 | J62: =IF(LEN(A62)=3,"类",IF(LEN(A62)=5,"款","项")) -> 项
A63: 2010604 | B63: 预算改革业务 | C63: 0 | D63: 0 | E63: 0 | F63: 0 | G63: =IFERROR((F63-C63)/C63,"") | H63: =IFERROR(F63/D63,"") | I63: =IF(LEN(A63)=3,"是",IF(B63<>"",IF(SUM(C63:F63)<>0,"是","否"),"是")) -> 否 | J63: =IF(LEN(A63)=3,"类",IF(LEN(A63)=5,"款","项")) -> 项
A64: 2010605 | B64: 财政国库业务 | C64: 0 | D64: 0 | E64: 0 | F64: 0 | G64: =IFERROR((F64-C64)/C64,"") | H64: =IFERROR(F64/D64,"") | I64: =IF(LEN(A64)=3,"是",IF(B64<>"",IF(SUM(C64:F64)<>0,"是","否"),"是")) -> 否 | J64: =IF(LEN(A64)=3,"类",IF(LEN(A64)=5,"款","项")) -> 项
A65: 2010606 | B65: 财政监察 | C65: 0 | D65: 0 | E65: 0 | F65: 0 | G65: =IFERROR((F65-C65)/C65,"") | H65: =IFERROR(F65/D65,"") | I65: =IF(LEN(A65)=3,"是",IF(B65<>"",IF(SUM(C65:F65)<>0,"是","否"),"是")) -> 否 | J65: =IF(LEN(A65)=3,"类",IF(LEN(A65)=5,"款","项")) -> 项
A66: 2010607 | B66: 信息化建设 | C66: 0 | D66: 0 | E66: 0 | F66: 223 | G66: =IFERROR((F66-C66)/C66,"") | H66: =IFERROR(F66/D66,"") | I66: =IF(LEN(A66)=3,"是",IF(B66<>"",IF(SUM(C66:F66)<>0,"是","否"),"是")) -> 是 | J66: =IF(LEN(A66)=3,"类",IF(LEN(A66)=5,"款","项")) -> 项
A67: 2010608 | B67: 财政委托业务支出 | C67: 303 | D67: 305 | E67: 305 | F67: 143 | G67: =IFERROR((F67-C67)/C67,"") -> -0.52805281 | H67: =IFERROR(F67/D67,"") -> 0.46885246 | I67: =IF(LEN(A67)=3,"是",IF(B67<>"",IF(SUM(C67:F67)<>0,"是","否"),"是")) -> 是 | J67: =IF(LEN(A67)=3,"类",IF(LEN(A67)=5,"款","项")) -> 项
A68: 2010650 | B68: 事业运行 | C68: 587 | D68: 630 | E68: 630 | F68: 652 | G68: =IFERROR((F68-C68)/C68,"") -> 0.11073254 | H68: =IFERROR(F68/D68,"") -> 1.0349206 | I68: =IF(LEN(A68)=3,"是",IF(B68<>"",IF(SUM(C68:F68)<>0,"是","否"),"是")) -> 是 | J68: =IF(LEN(A68)=3,"类",IF(LEN(A68)=5,"款","项")) -> 项
A69: 2010699 | B69: 其他财政事务支出 | C69: 62 | D69: 63 | E69: 63 | F69: 123 | G69: =IFERROR((F69-C69)/C69,"") -> 0.98387097 | H69: =IFERROR(F69/D69,"") -> 1.952381 | I69: =IF(LEN(A69)=3,"是",IF(B69<>"",IF(SUM(C69:F69)<>0,"是","否"),"是")) -> 是 | J69: =IF(LEN(A69)=3,"类",IF(LEN(A69)=5,"款","项")) -> 项
A70: 20107 | B70: 税收事务 | C70: 287 | D70: =SUM(D71:D77) -> 350 | E70: =SUM(E71:E77) -> 350 | F70: =SUM(F71:F77) -> 271 | G70: =IFERROR((F70-C70)/C70,"") -> -0.055749129 | H70: =IFERROR(F70/D70,"") -> 0.77428571 | I70: =IF(LEN(A70)=3,"是",IF(B70<>"",IF(SUM(C70:F70)<>0,"是","否"),"是")) -> 是 | J70: =IF(LEN(A70)=3,"类",IF(LEN(A70)=5,"款","项")) -> 款
A71: 2010701 | B71: 行政运行 | C71: 237 | D71: 270 | E71: 270 | F71: 223 | G71: =IFERROR((F71-C71)/C71,"") -> -0.05907173 | H71: =IFERROR(F71/D71,"") -> 0.82592593 | I71: =IF(LEN(A71)=3,"是",IF(B71<>"",IF(SUM(C71:F71)<>0,"是","否"),"是")) -> 是 | J71: =IF(LEN(A71)=3,"类",IF(LEN(A71)=5,"款","项")) -> 项
A72: 2010702 | B72: 一般行政管理事务 | C72: 50 | D72: 80 | E72: 80 | F72: 48 | G72: =IFERROR((F72-C72)/C72,"") -> -0.04 | H72: =IFERROR(F72/D72,"") -> 0.6 | I72: =IF(LEN(A72)=3,"是",IF(B72<>"",IF(SUM(C72:F72)<>0,"是","否"),"是")) -> 是 | J72: =IF(LEN(A72)=3,"类",IF(LEN(A72)=5,"款","项")) -> 项
A73: 2010703 | B73: 机关服务 | C73: 0 | D73: 0 | E73: 0 | F73: 0 | G73: =IFERROR((F73-C73)/C73,"") | H73: =IFERROR(F73/D73,"") | I73: =IF(LEN(A73)=3,"是",IF(B73<>"",IF(SUM(C73:F73)<>0,"是","否"),"是")) -> 否 | J73: =IF(LEN(A73)=3,"类",IF(LEN(A73)=5,"款","项")) -> 项
A74: 2010709 | B74: 信息化建设 | C74: 0 | D74: 0 | E74: 0 | F74: 0 | G74: =IFERROR((F74-C74)/C74,"") | H74: =IFERROR(F74/D74,"") | I74: =IF(LEN(A74)=3,"是",IF(B74<>"",IF(SUM(C74:F74)<>0,"是","否"),"是")) -> 否 | J74: =IF(LEN(A74)=3,"类",IF(LEN(A74)=5,"款","项")) -> 项
A75: 2010710 | B75: 税收业务 | C75: 0 | D75: 0 | E75: 0 | F75: 0 | G75: =IFERROR((F75-C75)/C75,"") | H75: =IFERROR(F75/D75,"") | I75: =IF(LEN(A75)=3,"是",IF(B75<>"",IF(SUM(C75:F75)<>0,"是","否"),"是")) -> 否 | J75: =IF(LEN(A75)=3,"类",IF(LEN(A75)=5,"款","项")) -> 项
A76: 2010750 | B76: 事业运行 | C76: 0 | D76: 0 | E76: 0 | F76: 0 | G76: =IFERROR((F76-C76)/C76,"") | H76: =IFERROR(F76/D76,"") | I76: =IF(LEN(A76)=3,"是",IF(B76<>"",IF(SUM(C76:F76)<>0,"是","否"),"是")) -> 否 | J76: =IF(LEN(A76)=3,"类",IF(LEN(A76)=5,"款","项")) -> 项
A77: 2010799 | B77: 其他税收事务支出 | C77: 0 | D77: 0 | E77: 0 | F77: 0 | G77: =IFERROR((F77-C77)/C77,"") | H77: =IFERROR(F77/D77,"") | I77: =IF(LEN(A77)=3,"是",IF(B77<>"",IF(SUM(C77:F77)<>0,"是","否"),"是")) -> 否 | J77: =IF(LEN(A77)=3,"类",IF(LEN(A77)=5,"款","项")) -> 项
A78: 20108 | B78: 审计事务 | C78: 338 | D78: =SUM(D79:D86) -> 340 | E78: =SUM(E79:E86) -> 340 | F78: =SUM(F79:F86) -> 166 | G78: =IFERROR((F78-C78)/C78,"") -> -0.50887574 | H78: =IFERROR(F78/D78,"") -> 0.48823529 | I78: =IF(LEN(A78)=3,"是",IF(B78<>"",IF(SUM(C78:F78)<>0,"是","否"),"是")) -> 是 | J78: =IF(LEN(A78)=3,"类",IF(LEN(A78)=5,"款","项")) -> 款
A79: 2010801 | B79: 行政运行 | C79: 0 | D79: 0 | E79: 0 | F79: 0 | G79: =IFERROR((F79-C79)/C79,"") | H79: =IFERROR(F79/D79,"") | I79: =IF(LEN(A79)=3,"是",IF(B79<>"",IF(SUM(C79:F79)<>0,"是","否"),"是")) -> 否 | J79: =IF(LEN(A79)=3,"类",IF(LEN(A79)=5,"款","项")) -> 项
A80: 2010802 | B80: 一般行政管理事务 | C80: 0 | D80: 0 | E80: 0 | F80: 0 | G80: =IFERROR((F80-C80)/C80,"") | H80: =IFERROR(F80/D80,"") | I80: =IF(LEN(A80)=3,"是",IF(B80<>"",IF(SUM(C80:F80)<>0,"是","否"),"是")) -> 否 | J80: =IF(LEN(A80)=3,"类",IF(LEN(A80)=5,"款","项")) -> 项
A81: 2010803 | B81: 机关服务 | C81: 0 | D81: 0 | E81: 0 | F81: 0 | G81: =IFERROR((F81-C81)/C81,"") | H81: =IFERROR(F81/D81,"") | I81: =IF(LEN(A81)=3,"是",IF(B81<>"",IF(SUM(C81:F81)<>0,"是","否"),"是")) -> 否 | J81: =IF(LEN(A81)=3,"类",IF(LEN(A81)=5,"款","项")) -> 项
A82: 2010804 | B82: 审计业务 | C82: 320 | D82: 320 | E82: 320 | F82: 151 | G82: =IFERROR((F82-C82)/C82,"") -> -0.528125 | H82: =IFERROR(F82/D82,"") -> 0.471875 | I82: =IF(LEN(A82)=3,"是",IF(B82<>"",IF(SUM(C82:F82)<>0,"是","否"),"是")) -> 是 | J82: =IF(LEN(A82)=3,"类",IF(LEN(A82)=5,"款","项")) -> 项
A83: 2010805 | B83: 审计管理 | C83: 0 | D83: 0 | E83: 0 | F83: 0 | G83: =IFERROR((F83-C83)/C83,"") | H83: =IFERROR(F83/D83,"") | I83: =IF(LEN(A83)=3,"是",IF(B83<>"",IF(SUM(C83:F83)<>0,"是","否"),"是")) -> 否 | J83: =IF(LEN(A83)=3,"类",IF(LEN(A83)=5,"款","项")) -> 项
A84: 2010806 | B84: 信息化建设 | C84: 0 | D84: 0 | E84: 0 | F84: 0 | G84: =IFERROR((F84-C84)/C84,"") | H84: =IFERROR(F84/D84,"") | I84: =IF(LEN(A84)=3,"是",IF(B84<>"",IF(SUM(C84:F84)<>0,"是","否"),"是")) -> 否 | J84: =IF(LEN(A84)=3,"类",IF(LEN(A84)=5,"款","项")) -> 项
A85: 2010850 | B85: 事业运行 | C85: 18 | D85: 20 | E85: 20 | F85: 15 | G85: =IFERROR((F85-C85)/C85,"") -> -0.16666667 | H85: =IFERROR(F85/D85,"") -> 0.75 | I85: =IF(LEN(A85)=3,"是",IF(B85<>"",IF(SUM(C85:F85)<>0,"是","否"),"是")) -> 是 | J85: =IF(LEN(A85)=3,"类",IF(LEN(A85)=5,"款","项")) -> 项
A86: 2010899 | B86: 其他审计事务支出 | C86: 0 | D86: 0 | E86: 0 | F86: 0 | G86: =IFERROR((F86-C86)/C86,"") | H86: =IFERROR(F86/D86,"") | I86: =IF(LEN(A86)=3,"是",IF(B86<>"",IF(SUM(C86:F86)<>0,"是","否"),"是")) -> 否 | J86: =IF(LEN(A86)=3,"类",IF(LEN(A86)=5,"款","项")) -> 项
A87: 20109 | B87: 海关事务 | C87: 98 | D87: =SUM(D88:D99) -> 95 | E87: =SUM(E88:E99) -> 95 | F87: =SUM(F88:F99) -> 97 | G87: =IFERROR((F87-C87)/C87,"") -> -0.010204082 | H87: =IFERROR(F87/D87,"") -> 1.0210526 | I87: =IF(LEN(A87)=3,"是",IF(B87<>"",IF(SUM(C87:F87)<>0,"是","否"),"是")) -> 是 | J87: =IF(LEN(A87)=3,"类",IF(LEN(A87)=5,"款","项")) -> 款
A88: 2010901 | B88: 行政运行 | C88: 0 | D88: 0 | E88: 0 | F88: 2 | G88: =IFERROR((F88-C88)/C88,"") | H88: =IFERROR(F88/D88,"") | I88: =IF(LEN(A88)=3,"是",IF(B88<>"",IF(SUM(C88:F88)<>0,"是","否"),"是")) -> 是 | J88: =IF(LEN(A88)=3,"类",IF(LEN(A88)=5,"款","项")) -> 项
A89: 2010902 | B89: 一般行政管理事务 | C89: 98 | D89: 95 | E89: 95 | F89: 95 | G89: =IFERROR((F89-C89)/C89,"") -> -0.030612245 | H89: =IFERROR(F89/D89,"") -> 1 | I89: =IF(LEN(A89)=3,"是",IF(B89<>"",IF(SUM(C89:F89)<>0,"是","否"),"是")) -> 是 | J89: =IF(LEN(A89)=3,"类",IF(LEN(A89)=5,"款","项")) -> 项
A90: 2010903 | B90: 机关服务 | C90: 0 | D90: 0 | E90: 0 | F90: 0 | G90: =IFERROR((F90-C90)/C90,"") | H90: =IFERROR(F90/D90,"") | I90: =IF(LEN(A90)=3,"是",IF(B90<>"",IF(SUM(C90:F90)<>0,"是","否"),"是")) -> 否 | J90: =IF(LEN(A90)=3,"类",IF(LEN(A90)=5,"款","项")) -> 项
A91: 2010905 | B91: 缉私办案 | C91: 0 | D91: 0 | E91: 0 | F91: 0 | G91: =IFERROR((F91-C91)/C91,"") | H91: =IFERROR(F91/D91,"") | I91: =IF(LEN(A91)=3,"是",IF(B91<>"",IF(SUM(C91:F91)<>0,"是","否"),"是")) -> 否 | J91: =IF(LEN(A91)=3,"类",IF(LEN(A91)=5,"款","项")) -> 项
A92: 2010907 | B92: 口岸管理 | C92: 0 | D92: 0 | E92: 0 | F92: 0 | G92: =IFERROR((F92-C92)/C92,"") | H92: =IFERROR(F92/D92,"") | I92: =IF(LEN(A92)=3,"是",IF(B92<>"",IF(SUM(C92:F92)<>0,"是","否"),"是")) -> 否 | J92: =IF(LEN(A92)=3,"类",IF(LEN(A92)=5,"款","项")) -> 项
A93: 2010908 | B93: 信息化建设 | C93: 0 | D93: 0 | E93: 0 | F93: 0 | G93: =IFERROR((F93-C93)/C93,"") | H93: =IFERROR(F93/D93,"") | I93: =IF(LEN(A93)=3,"是",IF(B93<>"",IF(SUM(C93:F93)<>0,"是","否"),"是")) -> 否 | J93: =IF(LEN(A93)=3,"类",IF(LEN(A93)=5,"款","项")) -> 项
A94: 2010909 | B94: 海关关务 | C94: 0 | D94: 0 | E94: 0 | F94: 0 | G94: =IFERROR((F94-C94)/C94,"") | H94: =IFERROR(F94/D94,"") | I94: =IF(LEN(A94)=3,"是",IF(B94<>"",IF(SUM(C94:F94)<>0,"是","否"),"是")) -> 否 | J94: =IF(LEN(A94)=3,"类",IF(LEN(A94)=5,"款","项")) -> 项
A95: 2010910 | B95: 关税征管 | C95: 0 | D95: 0 | E95: 0 | F95: 0 | G95: =IFERROR((F95-C95)/C95,"") | H95: =IFERROR(F95/D95,"") | I95: =IF(LEN(A95)=3,"是",IF(B95<>"",IF(SUM(C95:F95)<>0,"是","否"),"是")) -> 否 | J95: =IF(LEN(A95)=3,"类",IF(LEN(A95)=5,"款","项")) -> 项
A96: 2010911 | B96: 海关监管 | C96: 0 | D96: 0 | E96: 0 | F96: 0 | G96: =IFERROR((F96-C96)/C96,"") | H96: =IFERROR(F96/D96,"") | I96: =IF(LEN(A96)=3,"是",IF(B96<>"",IF(SUM(C96:F96)<>0,"是","否"),"是")) -> 否 | J96: =IF(LEN(A96)=3,"类",IF(LEN(A96)=5,"款","项")) -> 项
A97: 2010912 | B97: 检验检疫 | C97: 0 | D97: 0 | E97: 0 | F97: 0 | G97: =IFERROR((F97-C97)/C97,"") | H97: =IFERROR(F97/D97,"") | I97: =IF(LEN(A97)=3,"是",IF(B97<>"",IF(SUM(C97:F97)<>0,"是","否"),"是")) -> 否 | J97: =IF(LEN(A97)=3,"类",IF(LEN(A97)=5,"款","项")) -> 项
A98: 2010950 | B98: 事业运行 | C98: 0 | D98: 0 | E98: 0 | F98: 0 | G98: =IFERROR((F98-C98)/C98,"") | H98: =IFERROR(F98/D98,"") | I98: =IF(LEN(A98)=3,"是",IF(B98<>"",IF(SUM(C98:F98)<>0,"是","否"),"是")) -> 否 | J98: =IF(LEN(A98)=3,"类",IF(LEN(A98)=5,"款","项")) -> 项
A99: 2010999 | B99: 其他海关事务支出 | C99: 0 | D99: 0 | E99: 0 | F99: 0 | G99: =IFERROR((F99-C99)/C99,"") | H99: =IFERROR(F99/D99,"") | I99: =IF(LEN(A99)=3,"是",IF(B99<>"",IF(SUM(C99:F99)<>0,"是","否"),"是")) -> 否 | J99: =IF(LEN(A99)=3,"类",IF(LEN(A99)=5,"款","项")) -> 项
A100: 20111 | B100: 纪检监察事务 | C100: 8071 | D100: =SUM(D101:D108) -> 8225 | E100: =SUM(E101:E108) -> 8225 | F100: =SUM(F101:F108) -> 5216 | G100: =IFERROR((F100-C100)/C100,"") -> -0.3537356 | H100: =IFERROR(F100/D100,"") -> 0.63416413 | I100: =IF(LEN(A100)=3,"是",IF(B100<>"",IF(SUM(C100:F100)<>0,"是","否"),"是")) -> 是 | J100: =IF(LEN(A100)=3,"类",IF(LEN(A100)=5,"款","项")) -> 款
...

Sheet 05
A1: 2025年市本级预备费安排情况表
A2: 表五 | C2: 单位：万元
A3: 序号 | B3: 项 目 | C3: 金 额 | D3: 打印
A4: 合 计 | C4: =SUM(C5:C10) -> 5800 | D4: =IF(C4<>0,"是","否") -> 是
A5: 1 | B5: 世界银行云南城建项目还本付息专项资金 | C5: 2086.74 | D5: =IF(C5<>0,"是","否") -> 是
A6: 2 | B6: 新增化企业账款专项补助资金 | C6: 1184.15 | D6: =IF(C6<>0,"是","否") -> 是
A7: 3 | B7: 永宾高速公路征地拆迁缺口资金 | C7: 849.86 | D7: =IF(C7<>0,"是","否") -> 是
A8: 4 | B8: 专项任务经费（319专项工作任务经费） | C8: 120.53 | D8: =IF(C8<>0,"是","否") -> 是
A9: 5 | B9: 新增丽江市技工学校综合教学楼项目代建管理经费 | C9: 63.47 | D9: =IF(C9<>0,"是","否") -> 是
A10: 6 | B10: 金山高新区管委会专项债券本息偿还资金 | C10: 1495.25 | D10: =IF(C10<>0,"是","否") -> 是

Sheet 06
B1: 2025年丽江市政府性基金预算收入执行情况表
B2: 表六 | H2: 单位：万元
A3: 科目编码 | B3: 项目 | C3: 2024年决算数 | D3: 2025年 | G3: 比较
D4: 预算数 | E4: 调整预算数 | F4: 执行数 | G4: 比2024年决算数增长% | H4: 完成2025年预算数的% | I4: 打印
A5: 1030102 | B5: 一、农网还贷资金收入 | C5: 0 | G5: =IFERROR((F5-C5)/C5,"") | H5: =IFERROR(F5/D5,"") | I5: =IF(LEN(A5)=7,"是",IF(B5<>"",IF(SUM(C5:F5)<>0,"是","否"),"是")) -> 是
A6: 1030129 | B6: 二、国家电影事业发展专项资金收入 | C6: 0 | G6: =IFERROR((F6-C6)/C6,"") | H6: =IFERROR(F6/D6,"") | I6: =IF(LEN(A6)=7,"是",IF(B6<>"",IF(SUM(C6:F6)<>0,"是","否"),"是")) -> 是
A7: 1030146 | B7: 三、国有土地收益基金收入 | C7: 0 | G7: =IFERROR((F7-C7)/C7,"") | H7: =IFERROR(F7/D7,"") | I7: =IF(LEN(A7)=7,"是",IF(B7<>"",IF(SUM(C7:F7)<>0,"是","否"),"是")) -> 是
A8: 1030147 | B8: 四、农业土地开发资金收入 | C8: 0 | G8: =IFERROR((F8-C8)/C8,"") | H8: =IFERROR(F8/D8,"") | I8: =IF(LEN(A8)=7,"是",IF(B8<>"",IF(SUM(C8:F8)<>0,"是","否"),"是")) -> 是
A9: 1030148 | B9: 五、国有土地使用权出让收入 | C9: 52985 | D9: =SUM(D10:D14) -> 108037 | E9: =SUM(E10:E14) -> 108037 | F9: =SUM(F10:F14) -> 42707 | G9: =IFERROR((F9-C9)/C9,"") -> -0.19397943 | H9: =IFERROR(F9/D9,"") -> 0.39529976 | I9: =IF(LEN(A9)=7,"是",IF(B9<>"",IF(SUM(C9:F9)<>0,"是","否"),"是")) -> 是
A10: 103014801 | B10: 土地出让价款收入 | C10: 49891 | D10: 105052 | E10: 105052 | F10: 39565 | G10: =IFERROR((F10-C10)/C10,"") -> -0.2069712 | H10: =IFERROR(F10/D10,"") -> 0.37662301 | I10: =IF(LEN(A10)=7,"是",IF(B10<>"",IF(SUM(C10:F10)<>0,"是","否"),"是")) -> 是
A11: 103014802 | B11: 补缴的土地价款 | C11: 4296 | D11: 2985 | E11: 2985 | F11: 2914 | G11: =IFERROR((F11-C11)/C11,"") -> -0.3216946 | H11: =IFERROR(F11/D11,"") -> 0.97621441 | I11: =IF(LEN(A11)=7,"是",IF(B11<>"",IF(SUM(C11:F11)<>0,"是","否"),"是")) -> 是
A12: 103014803 | B12: 划拨土地收入 | C12: 173 | F12: 1644 | G12: =IFERROR((F12-C12)/C12,"") -> 8.5028902 | H12: =IFERROR(F12/D12,"") | I12: =IF(LEN(A12)=7,"是",IF(B12<>"",IF(SUM(C12:F12)<>0,"是","否"),"是")) -> 是
A13: 103014898 | B13: 缴纳新增建设用地土地有偿使用费 | C13: -1375 | F13: -1416 | G13: =-IFERROR((F13-C13)/C13,"") -> -0.029818182 | H13: =IFERROR(F13/D13,"") | I13: =IF(LEN(A13)=7,"是",IF(B13<>"",IF(SUM(C13:F13)<>0,"是","否"),"是")) -> 是
A14: 103014899 | B14: 其他土地出让收入 | C14: 0 | G14: =IFERROR((F14-C14)/C14,"") | H14: =IFERROR(F14/D14,"") | I14: =IF(LEN(A14)=7,"是",IF(B14<>"",IF(SUM(C14:F14)<>0,"是","否"),"是")) -> 否
A15: 1030150 | B15: 六、大中型水库库区基金收入 | C15: 0 | G15: =IFERROR((F15-C15)/C15,"") | H15: =IFERROR(F15/D15,"") | I15: =IF(LEN(A15)=7,"是",IF(B15<>"",IF(SUM(C15:F15)<>0,"是","否"),"是")) -> 是
A16: 1030155 | B16: 七、彩票公益金收入 | C16: 7407 | D16: =SUM(D17:D18) -> 7500 | E16: =SUM(E17:E18) -> 7500 | F16: =SUM(F17:F18) -> 7703 | G16: =IFERROR((F16-C16)/C16,"") -> 0.039962198 | H16: =IFERROR(F16/D16,"") -> 1.0270667 | I16: =IF(LEN(A16)=7,"是",IF(B16<>"",IF(SUM(C16:F16)<>0,"是","否"),"是")) -> 是
A17: 103015501 | B17: 福利彩票公益金收入 | C17: 3972 | D17: 4050 | E17: 4050 | F17: 4021 | G17: =IFERROR((F17-C17)/C17,"") -> 0.012336354 | H17: =IFERROR(F17/D17,"") -> 0.99283951 | I17: =IF(LEN(A17)=7,"是",IF(B17<>"",IF(SUM(C17:F17)<>0,"是","否"),"是")) -> 是
A18: 103015502 | B18: 体育彩票公益金收入 | C18: 3435 | D18: 3450 | E18: 3450 | F18: 3682 | G18: =IFERROR((F18-C18)/C18,"") -> 0.071906841 | H18: =IFERROR(F18/D18,"") -> 1.0672464 | I18: =IF(LEN(A18)=7,"是",IF(B18<>"",IF(SUM(C18:F18)<>0,"是","否"),"是")) -> 是
A19: 1030156 | B19: 八、城市基础设施配套费收入 | C19: 816 | D19: 750 | E19: 750 | F19: 629 | G19: =IFERROR((F19-C19)/C19,"") -> -0.22916667 | H19: =IFERROR(F19/D19,"") -> 0.83866667 | I19: =IF(LEN(A19)=7,"是",IF(B19<>"",IF(SUM(C19:F19)<>0,"是","否"),"是")) -> 是
A20: 1030157 | B20: 九、小型水库移民扶助基金收入 | C20: 0 | G20: =IFERROR((F20-C20)/C20,"") | H20: =IFERROR(F20/D20,"") | I20: =IF(LEN(A20)=7,"是",IF(B20<>"",IF(SUM(C20:F20)<>0,"是","否"),"是")) -> 是
A21: 1030158 | B21: 十、国家重大水利工程建设基金收入 | C21: 0 | G21: =IFERROR((F21-C21)/C21,"") | H21: =IFERROR(F21/D21,"") | I21: =IF(LEN(A21)=7,"是",IF(B21<>"",IF(SUM(C21:F21)<>0,"是","否"),"是")) -> 是
A22: 1030159 | B22: 十一、车辆通行费 | C22: 0 | G22: =IFERROR((F22-C22)/C22,"") | H22: =IFERROR(F22/D22,"") | I22: =IF(LEN(A22)=7,"是",IF(B22<>"",IF(SUM(C22:F22)<>0,"是","否"),"是")) -> 是
A23: 1030178 | B23: 十二、污水处理费收入 | C23: 0 | G23: =IFERROR((F23-C23)/C23,"") | H23: =IFERROR(F23/D23,"") | I23: =IF(LEN(A23)=7,"是",IF(B23<>"",IF(SUM(C23:F23)<>0,"是","否"),"是")) -> 是
A24: 1030180 | B24: 十三、彩票发行机构和彩票销售机构的业务费用 | C24: 0 | G24: =IFERROR((F24-C24)/C24,"") | H24: =IFERROR(F24/D24,"") | I24: =IF(LEN(A24)=7,"是",IF(B24<>"",IF(SUM(C24:F24)<>0,"是","否"),"是")) -> 是
A25: 1030199 | B25: 十四、其他政府性基金收入 | C25: 0 | G25: =IFERROR((F25-C25)/C25,"") | H25: =IFERROR(F25/D25,"") | I25: =IF(LEN(A25)=7,"是",IF(B25<>"",IF(SUM(C25:F25)<>0,"是","否"),"是")) -> 是
A26: 10310 | B26: 十五、专项债券对应项目专项收入 | C26: 90125 | D26: 118385 | E26: 118385 | F26: 119674 | G26: =IFERROR((F26-C26)/C26,"") -> 0.32786685 | H26: =IFERROR(F26/D26,"") -> 1.0108882 | I26: =IF(LEN(A26)=7,"是",IF(B26<>"",IF(SUM(C26:F26)<>0,"是","否"),"是")) -> 是
G27: =IFERROR((F27-C27)/C27,"") | H27: =IFERROR(F27/D27,"") | I27: =IF(LEN(A27)=7,"是",IF(B27<>"",IF(SUM(C27:F27)<>0,"是","否"),"是")) -> 是
B28: 全市政府性基金预算收入 | C28: =C5+C6+C7+C8+C9+C15+C16+C19+C20+C21+C22+C23+C24+C25+C26 -> 151333 | D28: =D5+D6+D7+D8+D9+D15+D16+D19+D20+D21+D22+D23+D24+D25+D26 -> 234672 | E28: =E5+E6+E7+E8+E9+E15+E16+E19+E20+E21+E22+E23+E24+E25+E26 -> 234672 | F28: =F5+F6+F7+F8+F9+F15+F16+F19+F20+F21+F22+F23+F24+F25+F26 -> 170713 | G28: =IFERROR((F28-C28)/C28,"") -> 0.12806196 | H28: =IFERROR(F28/D28,"") -> 0.72745364 | I28: =IF(LEN(A28)=7,"是",IF(B28<>"",IF(SUM(C28:F28)<>0,"是","否"),"是")) -> 是
A29: 105 | B29: 地方政府专项债务收入 | C29: 419670 | D29: 234030 | E29: 234030 | F29: 487330 | G29: =IFERROR((F29-C29)/C29,"") -> 0.16122191 | H29: =IFERROR(F29/D29,"") -> 2.0823399 | I29: =IF(LEN(A29)=7,"是",IF(B29<>"",IF(SUM(C29:F29)<>0,"是","否"),"是")) -> 是
A30: 110 | B30: 转移性收入 | C30: =C31+C33+C34 -> 115750 | D30: =D31+D33+D34 -> 146484 | E30: =E31+E33+E34 -> 146484 | F30: =F31+F33+F34 -> 114053 | G30: =IFERROR((F30-C30)/C30,"") -> -0.014660907 | H30: =IFERROR(F30/D30,"") -> 0.77860381 | I30: =IF(LEN(A30)=7,"是",IF(B30<>"",IF(SUM(C30:F30)<>0,"是","否"),"是")) -> 是
A31: 11004 | B31: 政府性基金转移支付收入 | C31: =C32 -> 71831 | D31: =D32 -> 73006 | E31: =E32 -> 73006 | F31: =F32 -> 40064 | G31: =IFERROR((F31-C31)/C31,"") -> -0.44224638 | H31: =IFERROR(F31/D31,"") -> 0.54877681 | I31: =IF(LEN(A31)=7,"是",IF(B31<>"",IF(SUM(C31:F31)<>0,"是","否"),"是")) -> 是
A32: 1100402 | B32: 政府性基金补助收入 | C32: 71831 | D32: 73006 | E32: 73006 | F32: 40064 | G32: =IFERROR((F32-C32)/C32,"") -> -0.44224638 | H32: =IFERROR(F32/D32,"") -> 0.54877681 | I32: =IF(LEN(A32)=7,"是",IF(B32<>"",IF(SUM(C32:F32)<>0,"是","否"),"是")) -> 是
A33: 11008 | B33: 上年结余收入 | C33: 39971 | D33: 73478 | E33: 73478 | F33: 73989 | G33: =IFERROR((F33-C33)/C33,"") -> 0.85106702 | H33: =IFERROR(F33/D33,"") -> 1.0069545 | I33: =IF(LEN(A33)=7,"是",IF(B33<>"",IF(SUM(C33:F33)<>0,"是","否"),"是")) -> 是
A34: 11009 | B34: 调入资金 | C34: 3948 | G34: =IFERROR((F34-C34)/C34,"") -> -1 | H34: =IFERROR(F34/D34,"") | I34: =IF(LEN(A34)=7,"是",IF(B34<>"",IF(SUM(C34:F34)<>0,"是","否"),"是")) -> 是
B35: 各项收入合计 | C35: =SUM(C28:C30) -> 686753 | D35: =SUM(D28:D30) -> 615186 | E35: =SUM(E28:E30) -> 615186 | F35: =SUM(F28:F30) -> 772096 | G35: =IFERROR((F35-C35)/C35,"") -> 0.1242703 | H35: =IFERROR(F35/D35,"") -> 1.2550611 | I35: =IF(LEN(A35)=7,"是",IF(B35<>"",IF(SUM(C35:F35)<>0,"是","否"),"是")) -> 是

Sheet 07
B1: 2025年丽江市政府性基金预算支出执行情况表
B2: 表七 | H2: 单位：万元
A3: 科目编码 | B3: 项目 | C3: 2024年决算数 | D3: 2025年 | G3: 比较
D4: 预算数 | E4: 调整预算数 | F4: 执行数 | G4: 比2024年决算数增长% | H4: 完成2025年预算数的% | I4: 打印 | J4: 类-款-项
A5: 205 | B5: 一、教育支出 | C5: 0 | F5: 0 | G5: =IFERROR((F5-C5)/C5,"") | H5: =IFERROR(F5/D5,"") | I5: =IF(LEN(A5)=3,"是",IF(B5<>"",IF(SUM(C5:F5)<>0,"是","否"),"是")) -> 是 | J5: =IF(LEN(A5)=3,"类",IF(LEN(A5)=5,"款","项")) -> 类
A6: 20598 | B6: 超长期特别国债安排的支出 | C6: 0 | F6: =VLOOKUP(A6,'[5]2基金部分支出'!$A$5:$D$333,4,FALSE) -> 0 | G6: =IFERROR((F6-C6)/C6,"") | H6: =IFERROR(F6/D6,"") | I6: =IF(LEN(A6)=3,"是",IF(B6<>"",IF(SUM(C6:F6)<>0,"是","否"),"是")) -> 否 | J6: =IF(LEN(A6)=3,"类",IF(LEN(A6)=5,"款","项")) -> 款
A7: 2059801 | B7: 基础教育 | C7: 0 | F7: =VLOOKUP(A7,'[5]2基金部分支出'!$A$5:$D$333,4,FALSE) -> 0 | G7: =IFERROR((F7-C7)/C7,"") | H7: =IFERROR(F7/D7,"") | I7: =IF(LEN(A7)=3,"是",IF(B7<>"",IF(SUM(C7:F7)<>0,"是","否"),"是")) -> 否 | J7: =IF(LEN(A7)=3,"类",IF(LEN(A7)=5,"款","项")) -> 项
A8: 2059802 | B8: 高等教育 | C8: 0 | F8: =VLOOKUP(A8,'[5]2基金部分支出'!$A$5:$D$333,4,FALSE) -> 0 | G8: =IFERROR((F8-C8)/C8,"") | H8: =IFERROR(F8/D8,"") | I8: =IF(LEN(A8)=3,"是",IF(B8<>"",IF(SUM(C8:F8)<>0,"是","否"),"是")) -> 否 | J8: =IF(LEN(A8)=3,"类",IF(LEN(A8)=5,"款","项")) -> 项
A9: 2059803 | B9: 职业教育 | C9: 0 | F9: =VLOOKUP(A9,'[5]2基金部分支出'!$A$5:$D$333,4,FALSE) -> 0 | G9: =IFERROR((F9-C9)/C9,"") | H9: =IFERROR(F9/D9,"") | I9: =IF(LEN(A9)=3,"是",IF(B9<>"",IF(SUM(C9:F9)<>0,"是","否"),"是")) -> 否 | J9: =IF(LEN(A9)=3,"类",IF(LEN(A9)=5,"款","项")) -> 项
A10: 2059804 | B10: 特殊教育 | C10: 0 | F10: =VLOOKUP(A10,'[5]2基金部分支出'!$A$5:$D$333,4,FALSE) -> 0 | G10: =IFERROR((F10-C10)/C10,"") | H10: =IFERROR(F10/D10,"") | I10: =IF(LEN(A10)=3,"是",IF(B10<>"",IF(SUM(C10:F10)<>0,"是","否"),"是")) -> 否 | J10: =IF(LEN(A10)=3,"类",IF(LEN(A10)=5,"款","项")) -> 项
A11: 2059899 | B11: 其他教育支出 | C11: 0 | F11: =VLOOKUP(A11,'[5]2基金部分支出'!$A$5:$D$333,4,FALSE) -> 0 | G11: =IFERROR((F11-C11)/C11,"") | H11: =IFERROR(F11/D11,"") | I11: =IF(LEN(A11)=3,"是",IF(B11<>"",IF(SUM(C11:F11)<>0,"是","否"),"是")) -> 否 | J11: =IF(LEN(A11)=3,"类",IF(LEN(A11)=5,"款","项")) -> 项
A12: 206 | B12: 二、科学技术支出 | C12: 0 | F12: 0 | G12: =IFERROR((F12-C12)/C12,"") | H12: =IFERROR(F12/D12,"") | I12: =IF(LEN(A12)=3,"是",IF(B12<>"",IF(SUM(C12:F12)<>0,"是","否"),"是")) -> 是 | J12: =IF(LEN(A12)=3,"类",IF(LEN(A12)=5,"款","项")) -> 类
A13: 20698 | B13: 超长期特别国债安排的支出 | C13: 0 | F13: =VLOOKUP(A13,'[5]2基金部分支出'!$A$5:$D$333,4,FALSE) -> 0 | G13: =IFERROR((F13-C13)/C13,"") | H13: =IFERROR(F13/D13,"") | I13: =IF(LEN(A13)=3,"是",IF(B13<>"",IF(SUM(C13:F13)<>0,"是","否"),"是")) -> 否 | J13: =IF(LEN(A13)=3,"类",IF(LEN(A13)=5,"款","项")) -> 款
A14: 2069801 | B14: 基础研究 | C14: 0 | F14: =VLOOKUP(A14,'[5]2基金部分支出'!$A$5:$D$333,4,FALSE) -> 0 | G14: =IFERROR((F14-C14)/C14,"") | H14: =IFERROR(F14/D14,"") | I14: =IF(LEN(A14)=3,"是",IF(B14<>"",IF(SUM(C14:F14)<>0,"是","否"),"是")) -> 否 | J14: =IF(LEN(A14)=3,"类",IF(LEN(A14)=5,"款","项")) -> 项
A15: 2069802 | B15: 应用研究 | C15: 0 | F15: =VLOOKUP(A15,'[5]2基金部分支出'!$A$5:$D$333,4,FALSE) -> 0 | G15: =IFERROR((F15-C15)/C15,"") | H15: =IFERROR(F15/D15,"") | I15: =IF(LEN(A15)=3,"是",IF(B15<>"",IF(SUM(C15:F15)<>0,"是","否"),"是")) -> 否 | J15: =IF(LEN(A15)=3,"类",IF(LEN(A15)=5,"款","项")) -> 项
A16: 2069803 | B16: 技术研究与开发 | C16: 0 | F16: =VLOOKUP(A16,'[5]2基金部分支出'!$A$5:$D$333,4,FALSE) -> 0 | G16: =IFERROR((F16-C16)/C16,"") | H16: =IFERROR(F16/D16,"") | I16: =IF(LEN(A16)=3,"是",IF(B16<>"",IF(SUM(C16:F16)<>0,"是","否"),"是")) -> 否 | J16: =IF(LEN(A16)=3,"类",IF(LEN(A16)=5,"款","项")) -> 项
A17: 2069804 | B17: 科技条件与服务 | C17: 0 | F17: =VLOOKUP(A17,'[5]2基金部分支出'!$A$5:$D$333,4,FALSE) -> 0 | G17: =IFERROR((F17-C17)/C17,"") | H17: =IFERROR(F17/D17,"") | I17: =IF(LEN(A17)=3,"是",IF(B17<>"",IF(SUM(C17:F17)<>0,"是","否"),"是")) -> 否 | J17: =IF(LEN(A17)=3,"类",IF(LEN(A17)=5,"款","项")) -> 项
A18: 2069805 | B18: 科技重大项目 | C18: 0 | F18: =VLOOKUP(A18,'[5]2基金部分支出'!$A$5:$D$333,4,FALSE) -> 0 | G18: =IFERROR((F18-C18)/C18,"") | H18: =IFERROR(F18/D18,"") | I18: =IF(LEN(A18)=3,"是",IF(B18<>"",IF(SUM(C18:F18)<>0,"是","否"),"是")) -> 否 | J18: =IF(LEN(A18)=3,"类",IF(LEN(A18)=5,"款","项")) -> 项
A19: 2069899 | B19: 其他科技支出 | C19: 0 | F19: =VLOOKUP(A19,'[5]2基金部分支出'!$A$5:$D$333,4,FALSE) -> 0 | G19: =IFERROR((F19-C19)/C19,"") | H19: =IFERROR(F19/D19,"") | I19: =IF(LEN(A19)=3,"是",IF(B19<>"",IF(SUM(C19:F19)<>0,"是","否"),"是")) -> 否 | J19: =IF(LEN(A19)=3,"类",IF(LEN(A19)=5,"款","项")) -> 项
A20: 207 | B20: 三、文化旅游体育与传媒支出 | C20: =C21+C27+C33+C36 -> 19 | D20: =D21+D27+D33+D36 -> 0 | E20: =E21+E27+E33+E36 -> 0 | F20: =F21+F27+F33+F36 -> 1375 | G20: =IFERROR((F20-C20)/C20,"") -> 71.368421 | H20: =IFERROR(F20/D20,"") | I20: =IF(LEN(A20)=3,"是",IF(B20<>"",IF(SUM(C20:F20)<>0,"是","否"),"是")) -> 是 | J20: =IF(LEN(A20)=3,"类",IF(LEN(A20)=5,"款","项")) -> 类
A21: 20707 | B21: 国家电影事业发展专项资金安排的支出 | C21: =SUM(C22:C26) -> 19 | D21: =SUM(D22:D26) -> 0 | E21: =SUM(E22:E26) -> 0 | F21: =SUM(F22:F26) -> 2 | G21: =IFERROR((F21-C21)/C21,"") -> -0.89473684 | H21: =IFERROR(F21/D21,"") | I21: =IF(LEN(A21)=3,"是",IF(B21<>"",IF(SUM(C21:F21)<>0,"是","否"),"是")) -> 是 | J21: =IF(LEN(A21)=3,"类",IF(LEN(A21)=5,"款","项")) -> 款
A22: 2070701 | B22: 资助国产影片放映 | C22: 19 | F22: 1 | G22: =IFERROR((F22-C22)/C22,"") -> -0.94736842 | H22: =IFERROR(F22/D22,"") | I22: =IF(LEN(A22)=3,"是",IF(B22<>"",IF(SUM(C22:F22)<>0,"是","否"),"是")) -> 是 | J22: =IF(LEN(A22)=3,"类",IF(LEN(A22)=5,"款","项")) -> 项
A23: 2070702 | B23: 资助影院建设 | C23: 0 | F23: 0 | G23: =IFERROR((F23-C23)/C23,"") | H23: =IFERROR(F23/D23,"") | I23: =IF(LEN(A23)=3,"是",IF(B23<>"",IF(SUM(C23:F23)<>0,"是","否"),"是")) -> 否 | J23: =IF(LEN(A23)=3,"类",IF(LEN(A23)=5,"款","项")) -> 项
A24: 2070703 | B24: 资助少数民族语电影译制 | C24: 0 | F24: 0 | G24: =IFERROR((F24-C24)/C24,"") | H24: =IFERROR(F24/D24,"") | I24: =IF(LEN(A24)=3,"是",IF(B24<>"",IF(SUM(C24:F24)<>0,"是","否"),"是")) -> 否 | J24: =IF(LEN(A24)=3,"类",IF(LEN(A24)=5,"款","项")) -> 项
A25: 2070704 | B25: 购买农村电影公益性放映版权服务 | C25: 0 | F25: 0 | G25: =IFERROR((F25-C25)/C25,"") | H25: =IFERROR(F25/D25,"") | I25: =IF(LEN(A25)=3,"是",IF(B25<>"",IF(SUM(C25:F25)<>0,"是","否"),"是")) -> 否 | J25: =IF(LEN(A25)=3,"类",IF(LEN(A25)=5,"款","项")) -> 项
A26: 2070799 | B26: 其他国家电影事业发展专项资金支出 | C26: 0 | F26: 1 | G26: =IFERROR((F26-C26)/C26,"") | H26: =IFERROR(F26/D26,"") | I26: =IF(LEN(A26)=3,"是",IF(B26<>"",IF(SUM(C26:F26)<>0,"是","否"),"是")) -> 是 | J26: =IF(LEN(A26)=3,"类",IF(LEN(A26)=5,"款","项")) -> 项
A27: 20709 | B27: 旅游发展基金支出 | C27: =SUM(C28:C32) -> 0 | D27: =SUM(D28:D32) -> 0 | E27: =SUM(E28:E32) -> 0 | F27: =SUM(F28:F32) -> 133 | G27: =IFERROR((F27-C27)/C27,"") | H27: =IFERROR(F27/D27,"") | I27: =IF(LEN(A27)=3,"是",IF(B27<>"",IF(SUM(C27:F27)<>0,"是","否"),"是")) -> 是 | J27: =IF(LEN(A27)=3,"类",IF(LEN(A27)=5,"款","项")) -> 款
A28: 2070901 | B28: 宣传促销 | C28: 0 | F28: 60 | G28: =IFERROR((F28-C28)/C28,"") | H28: =IFERROR(F28/D28,"") | I28: =IF(LEN(A28)=3,"是",IF(B28<>"",IF(SUM(C28:F28)<>0,"是","否"),"是")) -> 是 | J28: =IF(LEN(A28)=3,"类",IF(LEN(A28)=5,"款","项")) -> 项
A29: 2070902 | B29: 行业规划 | C29: 0 | F29: 0 | G29: =IFERROR((F29-C29)/C29,"") | H29: =IFERROR(F29/D29,"") | I29: =IF(LEN(A29)=3,"是",IF(B29<>"",IF(SUM(C29:F29)<>0,"是","否"),"是")) -> 否 | J29: =IF(LEN(A29)=3,"类",IF(LEN(A29)=5,"款","项")) -> 项
A30: 2070903 | B30: 旅游事业补助 | C30: 0 | F30: 16 | G30: =IFERROR((F30-C30)/C30,"") | H30: =IFERROR(F30/D30,"") | I30: =IF(LEN(A30)=3,"是",IF(B30<>"",IF(SUM(C30:F30)<>0,"是","否"),"是")) -> 是 | J30: =IF(LEN(A30)=3,"类",IF(LEN(A30)=5,"款","项")) -> 项
A31: 2070904 | B31: 地方旅游开发项目补助 | C31: 0 | F31: 57 | G31: =IFERROR((F31-C31)/C31,"") | H31: =IFERROR(F31/D31,"") | I31: =IF(LEN(A31)=3,"是",IF(B31<>"",IF(SUM(C31:F31)<>0,"是","否"),"是")) -> 是 | J31: =IF(LEN(A31)=3,"类",IF(LEN(A31)=5,"款","项")) -> 项
A32: 2070999 | B32: 其他旅游发展基金支出 | F32: 0 | G32: =IFERROR((F32-C32)/C32,"") | H32: =IFERROR(F32/D32,"") | I32: =IF(LEN(A32)=3,"是",IF(B32<>"",IF(SUM(C32:F32)<>0,"是","否"),"是")) -> 否 | J32: =IF(LEN(A32)=3,"类",IF(LEN(A32)=5,"款","项")) -> 项
A33: 20710 | B33: 国家电影事业发展专项资金对应专项债务收入安排的支出 | C33: 0 | F33: 0 | G33: =IFERROR((F33-C33)/C33,"") | H33: =IFERROR(F33/D33,"") | I33: =IF(LEN(A33)=3,"是",IF(B33<>"",IF(SUM(C33:F33)<>0,"是","否"),"是")) -> 否 | J33: =IF(LEN(A33)=3,"类",IF(LEN(A33)=5,"款","项")) -> 款
A34: 2071001 | B34: 资助城市影院 | C34: 0 | F34: 0 | G34: =IFERROR((F34-C34)/C34,"") | H34: =IFERROR(F34/D34,"") | I34: =IF(LEN(A34)=3,"是",IF(B34<>"",IF(SUM(C34:F34)<>0,"是","否"),"是")) -> 否 | J34: =IF(LEN(A34)=3,"类",IF(LEN(A34)=5,"款","项")) -> 项
A35: 2071099 | B35: 其他国家电影事业发展专项资金对应专项债务收入支出 | C35: 0 | F35: 0 | G35: =IFERROR((F35-C35)/C35,"") | H35: =IFERROR(F35/D35,"") | I35: =IF(LEN(A35)=3,"是",IF(B35<>"",IF(SUM(C35:F35)<>0,"是","否"),"是")) -> 否 | J35: =IF(LEN(A35)=3,"类",IF(LEN(A35)=5,"款","项")) -> 项
A36: 20798 | B36: 超长期特别国债安排的支出 | C36: =SUM(C37:C42) -> 0 | D36: =SUM(D37:D42) -> 0 | E36: =SUM(E37:E42) -> 0 | F36: =SUM(F37:F42) -> 1240 | G36: =IFERROR((F36-C36)/C36,"") | H36: =IFERROR(F36/D36,"") | I36: =IF(LEN(A36)=3,"是",IF(B36<>"",IF(SUM(C36:F36)<>0,"是","否"),"是")) -> 是 | J36: =IF(LEN(A36)=3,"类",IF(LEN(A36)=5,"款","项")) -> 款
A37: 2079801 | B37: 文化和旅游 | F37: 1240 | G37: =IFERROR((F37-C37)/C37,"") | H37: =IFERROR(F37/D37,"") | I37: =IF(LEN(A37)=3,"是",IF(B37<>"",IF(SUM(C37:F37)<>0,"是","否"),"是")) -> 是 | J37: =IF(LEN(A37)=3,"类",IF(LEN(A37)=5,"款","项")) -> 项
A38: 2079802 | B38: 文物 | F38: 0 | G38: =IFERROR((F38-C38)/C38,"") | H38: =IFERROR(F38/D38,"") | I38: =IF(LEN(A38)=3,"是",IF(B38<>"",IF(SUM(C38:F38)<>0,"是","否"),"是")) -> 否 | J38: =IF(LEN(A38)=3,"类",IF(LEN(A38)=5,"款","项")) -> 项
A39: 2079803 | B39: 体育 | F39: 0 | G39: =IFERROR((F39-C39)/C39,"") | H39: =IFERROR(F39/D39,"") | I39: =IF(LEN(A39)=3,"是",IF(B39<>"",IF(SUM(C39:F39)<>0,"是","否"),"是")) -> 否 | J39: =IF(LEN(A39)=3,"类",IF(LEN(A39)=5,"款","项")) -> 项
A40: 2079804 | B40: 新闻出版电影 | F40: 0 | G40: =IFERROR((F40-C40)/C40,"") | H40: =IFERROR(F40/D40,"") | I40: =IF(LEN(A40)=3,"是",IF(B40<>"",IF(SUM(C40:F40)<>0,"是","否"),"是")) -> 否 | J40: =IF(LEN(A40)=3,"类",IF(LEN(A40)=5,"款","项")) -> 项
A41: 2079805 | B41: 广播电视 | F41: 0 | G41: =IFERROR((F41-C41)/C41,"") | H41: =IFERROR(F41/D41,"") | I41: =IF(LEN(A41)=3,"是",IF(B41<>"",IF(SUM(C41:F41)<>0,"是","否"),"是")) -> 否 | J41: =IF(LEN(A41)=3,"类",IF(LEN(A41)=5,"款","项")) -> 项
A42: 2079899 | B42: 其他文化旅游体育与传媒支出 | F42: 0 | G42: =IFERROR((F42-C42)/C42,"") | H42: =IFERROR(F42/D42,"") | I42: =IF(LEN(A42)=3,"是",IF(B42<>"",IF(SUM(C42:F42)<>0,"是","否"),"是")) -> 否 | J42: =IF(LEN(A42)=3,"类",IF(LEN(A42)=5,"款","项")) -> 项
A43: 208 | B43: 四、社会保障和就业支出 | C43: 0 | F43: 0 | G43: =IFERROR((F43-C43)/C43,"") | H43: =IFERROR(F43/D43,"") | I43: =IF(LEN(A43)=3,"是",IF(B43<>"",IF(SUM(C43:F43)<>0,"是","否"),"是")) -> 是 | J43: =IF(LEN(A43)=3,"类",IF(LEN(A43)=5,"款","项")) -> 类
A44: 20898 | B44: 超长期特别国债安排的支出 | C44: 0 | F44: 0 | G44: =IFERROR((F44-C44)/C44,"") | H44: =IFERROR(F44/D44,"") | I44: =IF(LEN(A44)=3,"是",IF(B44<>"",IF(SUM(C44:F44)<>0,"是","否"),"是")) -> 否 | J44: =IF(LEN(A44)=3,"类",IF(LEN(A44)=5,"款","项")) -> 款
A45: 2089801 | B45: 养老机构及服务设施 | C45: 0 | F45: 0 | G45: =IFERROR((F45-C45)/C45,"") | H45: =IFERROR(F45/D45,"") | I45: =IF(LEN(A45)=3,"是",IF(B45<>"",IF(SUM(C45:F45)<>0,"是","否"),"是")) -> 否 | J45: =IF(LEN(A45)=3,"类",IF(LEN(A45)=5,"款","项")) -> 项
A46: 2089802 | B46: 公共就业服务设施 | C46: 0 | F46: 0 | G46: =IFERROR((F46-C46)/C46,"") | H46: =IFERROR(F46/D46,"") | I46: =IF(LEN(A46)=3,"是",IF(B46<>"",IF(SUM(C46:F46)<>0,"是","否"),"是")) -> 否 | J46: =IF(LEN(A46)=3,"类",IF(LEN(A46)=5,"款","项")) -> 项
A47: 2089899 | B47: 其他社会保险和就业支出 | C47: 0 | F47: 0 | G47: =IFERROR((F47-C47)/C47,"") | H47: =IFERROR(F47/D47,"") | I47: =IF(LEN(A47)=3,"是",IF(B47<>"",IF(SUM(C47:F47)<>0,"是","否"),"是")) -> 否 | J47: =IF(LEN(A47)=3,"类",IF(LEN(A47)=5,"款","项")) -> 项
A48: 210 | B48: 五、卫生健康支出 | C48: 0 | F48: 0 | G48: =IFERROR((F48-C48)/C48,"") | H48: =IFERROR(F48/D48,"") | I48: =IF(LEN(A48)=3,"是",IF(B48<>"",IF(SUM(C48:F48)<>0,"是","否"),"是")) -> 是 | J48: =IF(LEN(A48)=3,"类",IF(LEN(A48)=5,"款","项")) -> 类
A49: 21098 | B49: 超长期特别国债安排的支出 | C49: 0 | F49: 0 | G49: =IFERROR((F49-C49)/C49,"") | H49: =IFERROR(F49/D49,"") | I49: =IF(LEN(A49)=3,"是",IF(B49<>"",IF(SUM(C49:F49)<>0,"是","否"),"是")) -> 否 | J49: =IF(LEN(A49)=3,"类",IF(LEN(A49)=5,"款","项")) -> 款
A50: 2109801 | B50: 公立医院 | C50: 0 | F50: 0 | G50: =IFERROR((F50-C50)/C50,"") | H50: =IFERROR(F50/D50,"") | I50: =IF(LEN(A50)=3,"是",IF(B50<>"",IF(SUM(C50:F50)<>0,"是","否"),"是")) -> 否 | J50: =IF(LEN(A50)=3,"类",IF(LEN(A50)=5,"款","项")) -> 项
A51: 2109802 | B51: 基层医疗卫生机构 | C51: 0 | F51: 0 | G51: =IFERROR((F51-C51)/C51,"") | H51: =IFERROR(F51/D51,"") | I51: =IF(LEN(A51)=3,"是",IF(B51<>"",IF(SUM(C51:F51)<>0,"是","否"),"是")) -> 否 | J51: =IF(LEN(A51)=3,"类",IF(LEN(A51)=5,"款","项")) -> 项
A52: 2109803 | B52: 公共卫生机构 | C52: 0 | F52: 0 | G52: =IFERROR((F52-C52)/C52,"") | H52: =IFERROR(F52/D52,"") | I52: =IF(LEN(A52)=3,"是",IF(B52<>"",IF(SUM(C52:F52)<>0,"是","否"),"是")) -> 否 | J52: =IF(LEN(A52)=3,"类",IF(LEN(A52)=5,"款","项")) -> 项
A53: 2109804 | B53: 托育机构 | C53: 0 | F53: 0 | G53: =IFERROR((F53-C53)/C53,"") | H53: =IFERROR(F53/D53,"") | I53: =IF(LEN(A53)=3,"是",IF(B53<>"",IF(SUM(C53:F53)<>0,"是","否"),"是")) -> 否 | J53: =IF(LEN(A53)=3,"类",IF(LEN(A53)=5,"款","项")) -> 项
A54: 2109899 | B54: 其他卫生健康支出 | C54: 0 | F54: 0 | G54: =IFERROR((F54-C54)/C54,"") | H54: =IFERROR(F54/D54,"") | I54: =IF(LEN(A54)=3,"是",IF(B54<>"",IF(SUM(C54:F54)<>0,"是","否"),"是")) -> 否 | J54: =IF(LEN(A54)=3,"类",IF(LEN(A54)=5,"款","项")) -> 项
... A70: 2119899 | B70: 其他节能环保支出 | C70: 0 | F70: 0 | G70: =IFERROR((F70-C70)/C70,"") | H70: =IFERROR(F70/D70,"") | I70: =IF(LEN(A70)=3,"是",IF(B70<>"",IF(SUM(C70:F70)<>0,"是","否"),"是")) -> 否 | J70: =IF(LEN(A70)=3,"类",IF(LEN(A70)=5,"款","项")) -> 项
A71: 212 | B71: 七、城乡社区支出 | C71: 38675 | D71: =D72+D88+D92+D93+D99+D103+D107+D111+D117+D120+D129 -> 61457 | E71: =E72+E88+E92+E93+E99+E103+E107+E111+E117+E120+E129 -> 61457 | F71: =F72+F88+F92+F93+F99+F103+F107+F111+F117+F120+F129 -> 84906 | G71: =IFERROR((F71-C71)/C71,"") -> 1.1953717 | H71: =IFERROR(F71/D71,"") -> 1.3815513 | I71: =IF(LEN(A71)=3,"是",IF(B71<>"",IF(SUM(C71:F71)<>0,"是","否"),"是")) -> 是 | J71: =IF(LEN(A71)=3,"类",IF(LEN(A71)=5,"款","项")) -> 类
A72: 21208 | B72: 国有土地使用权出让收入安排的支出 | C72: 26463 | D72: =SUM(D73:D87) -> 32929 | E72: =SUM(E73:E87) -> 32929 | F72: =SUM(F73:F87) -> 33021 | G72: =IFERROR((F72-C72)/C72,"") -> 0.24781771 | H72: =IFERROR(F72/D72,"") -> 1.0027939 | I72: =IF(LEN(A72)=3,"是",IF(B72<>"",IF(SUM(C72:F72)<>0,"是","否"),"是")) -> 是 | J72: =IF(LEN(A72)=3,"类",IF(LEN(A72)=5,"款","项")) -> 款
A73: 2120801 | B73: 征地和拆迁补偿支出 | C73: 6073 | D73: 5614 | E73: 5614 | F73: 5018 | G73: =IFERROR((F73-C73)/C73,"") -> -0.17371974 | H73: =IFERROR(F73/D73,"") -> 0.89383684 | I73: =IF(LEN(A73)=3,"是",IF(B73<>"",IF(SUM(C73:F73)<>0,"是","否"),"是")) -> 是 | J73: =IF(LEN(A73)=3,"类",IF(LEN(A73)=5,"款","项")) -> 项
A74: 2120802 | B74: 土地开发支出 | C74: 1335 | D74: 1325 | E74: 1325 | F74: 6984 | G74: =IFERROR((F74-C74)/C74,"") -> 4.2314607 | H74: =IFERROR(F74/D74,"") -> 5.2709434 | I74: =IF(LEN(A74)=3,"是",IF(B74<>"",IF(SUM(C74:F74)<>0,"是","否"),"是")) -> 是 | J74: =IF(LEN(A74)=3,"类",IF(LEN(A74)=5,"款","项")) -> 项
A75: 2120803 | B75: 城市建设支出 | C75: 114 | D75: 220 | E75: 220 | F75: 0 | G75: =IFERROR((F75-C75)/C75,"") -> -1 | H75: =IFERROR(F75/D75,"") -> 0 | I75: =IF(LEN(A75)=3,"是",IF(B75<>"",IF(SUM(C75:F75)<>0,"是","否"),"是")) -> 是 | J75: =IF(LEN(A75)=3,"类",IF(LEN(A75)=5,"款","项")) -> 项
A76: 2120804 | B76: 农村基础设施建设支出 | C76: 1377 | D76: 1325 | E76: 1325 | F76: 828 | G76: =IFERROR((F76-C76)/C76,"") -> -0.39869281 | H76: =IFERROR(F76/D76,"") -> 0.62490566 | I76: =IF(LEN(A76)=3,"是",IF(B76<>"",IF(SUM(C76:F76)<>0,"是","否"),"是")) -> 是 | J76: =IF(LEN(A76)=3,"类",IF(LEN(A76)=5,"款","项")) -> 项
A77: 2120805 | B77: 补助被征地农民支出 | C77: 632 | D77: 412 | E77: 412 | F77: 8 | G77: =IFERROR((F77-C77)/C77,"") -> -0.98734177 | H77: =IFERROR(F77/D77,"") -> 0.019417476 | I77: =IF(LEN(A77)=3,"是",IF(B77<>"",IF(SUM(C77:F77)<>0,"是","否"),"是")) -> 是 | J77: =IF(LEN(A77)=3,"类",IF(LEN(A77)=5,"款","项")) -> 项
A78: 2120806 | B78: 土地出让业务支出 | C78: 252 | D78: 180 | E78: 180 | F78: 220 | G78: =IFERROR((F78-C78)/C78,"") -> -0.12698413 | H78: =IFERROR(F78/D78,"") -> 1.2222222 | I78: =IF(LEN(A78)=3,"是",IF(B78<>"",IF(SUM(C78:F78)<>0,"是","否"),"是")) -> 是 | J78: =IF(LEN(A78)=3,"类",IF(LEN(A78)=5,"款","项")) -> 项
A79: 2120807 | B79: 廉租住房支出 | C79: 0 | F79: 0 | G79: =IFERROR((F79-C79)/C79,"") | H79: =IFERROR(F79/D79,"") | I79: =IF(LEN(A79)=3,"是",IF(B79<>"",IF(SUM(C79:F79)<>0,"是","否"),"是")) -> 否 | J79: =IF(LEN(A79)=3,"类",IF(LEN(A79)=5,"款","项")) -> 项
A80: 2120809 | B80: 支付破产或改制企业职工安置费 | C80: 0 | F80: 0 | G80: =IFERROR((F80-C80)/C80,"") | H80: =IFERROR(F80/D80,"") | I80: =IF(LEN(A80)=3,"是",IF(B80<>"",IF(SUM(C80:F80)<>0,"是","否"),"是")) -> 否 | J80: =IF(LEN(A80)=3,"类",IF(LEN(A80)=5,"款","项")) -> 项
A81: 2120810 | B81: 棚户区改造支出 | C81: 0 | F81: 0 | G81: =IFERROR((F81-C81)/C81,"") | H81: =IFERROR(F81/D81,"") | I81: =IF(LEN(A81)=3,"是",IF(B81<>"",IF(SUM(C81:F81)<>0,"是","否"),"是")) -> 否 | J81: =IF(LEN(A81)=3,"类",IF(LEN(A81)=5,"款","项")) -> 项
A82: 2120811 | B82: 公共租赁住房支出 | C82: 0 | F82: 0 | G82: =IFERROR((F82-C82)/C82,"") | H82: =IFERROR(F82/D82,"") | I82: =IF(LEN(A82)=3,"是",IF(B82<>"",IF(SUM(C82:F82)<>0,"是","否"),"是")) -> 否 | J82: =IF(LEN(A82)=3,"类",IF(LEN(A82)=5,"款","项")) -> 项
A83: 2120813 | B83: 保障性住房租金补贴 | C83: 0 | F83: 0 | G83: =IFERROR((F83-C83)/C83,"") | H83: =IFERROR(F83/D83,"") | I83: =IF(LEN(A83)=3,"是",IF(B83<>"",IF(SUM(C83:F83)<>0,"是","否"),"是")) -> 否 | J83: =IF(LEN(A83)=3,"类",IF(LEN(A83)=5,"款","项")) -> 项
A84: 2120814 | B84: 农业生产发展支出 | C84: 2066 | D84: 5320 | E84: 5320 | F84: 3383 | G84: =IFERROR((F84-C84)/C84,"") -> 0.6374637 | H84: =IFERROR(F84/D84,"") -> 0.63590226 | I84: =IF(LEN(A84)=3,"是",IF(B84<>"",IF(SUM(C84:F84)<>0,"是","否"),"是")) -> 是 | J84: =IF(LEN(A84)=3,"类",IF(LEN(A84)=5,"款","项")) -> 项
A85: 2120815 | B85: 农村社会事业支出 | C85: 1060 | D85: 2390 | E85: 2390 | F85: 1426 | G85: =IFERROR((F85-C85)/C85,"") -> 0.34528302 | H85: =IFERROR(F85/D85,"") -> 0.59665272 | I85: =IF(LEN(A85)=3,"是",IF(B85<>"",IF(SUM(C85:F85)<>0,"是","否"),"是")) -> 是 | J85: =IF(LEN(A85)=3,"类",IF(LEN(A85)=5,"款","项")) -> 项
A86: 2120816 | B86: 农业农村生态环境支出 | C86: 500 | D86: 62 | E86: 62 | F86: 92 | G86: =IFERROR((F86-C86)/C86,"") -> -0.816 | H86: =IFERROR(F86/D86,"") -> 1.483871 | I86: =IF(LEN(A86)=3,"是",IF(B86<>"",IF(SUM(C86:F86)<>0,"是","否"),"是")) -> 是 | J86: =IF(LEN(A86)=3,"类",IF(LEN(A86)=5,"款","项")) -> 项
A87: 2120899 | B87: 其他国有土地使用权出让收入安排的支出 | C87: 13054 | D87: 16081 | E87: 16081 | F87: 15062 | G87: =IFERROR((F87-C87)/C87,"") -> 0.15382258 | H87: =IFERROR(F87/D87,"") -> 0.93663329 | I87: =IF(LEN(A87)=3,"是",IF(B87<>"",IF(SUM(C87:F87)<>0,"是","否"),"是")) -> 是 | J87: =IF(LEN(A87)=3,"类",IF(LEN(A87)=5,"款","项")) -> 项
A88: 21210 | B88: 国有土地收益基金安排的支出 | C88: 0 | F88: 0 | G88: =IFERROR((F88-C88)/C88,"") | H88: =IFERROR(F88/D88,"") | I88: =IF(LEN(A88)=3,"是",IF(B88<>"",IF(SUM(C88:F88)<>0,"是","否"),"是")) -> 否 | J88: =IF(LEN(A88)=3,"类",IF(LEN(A88)=5,"款","项")) -> 款
A89: 2121001 | B89: 征地和拆迁补偿支出 | C89: 0 | F89: 0 | G89: =IFERROR((F89-C89)/C89,"") | H89: =IFERROR(F89/D89,"") | I89: =IF(LEN(A89)=3,"是",IF(B89<>"",IF(SUM(C89:F89)<>0,"是","否"),"是")) -> 否 | J89: =IF(LEN(A89)=3,"类",IF(LEN(A89)=5,"款","项")) -> 项
A90: 2121002 | B90: 土地开发支出 | C90: 0 | F90: 0 | G90: =IFERROR((F90-C90)/C90,"") | H90: =IFERROR(F90/D90,"") | I90: =IF(LEN(A90)=3,"是",IF(B90<>"",IF(SUM(C90:F90)<>0,"是","否"),"是")) -> 否 | J90: =IF(LEN(A90)=3,"类",IF(LEN(A90)=5,"款","项")) -> 项
A91: 2121099 | B91: 其他国有土地收益基金支出 | C91: 0 | F91: 0 | G91: =IFERROR((F91-C91)/C91,"") | H91: =IFERROR(F91/D91,"") | I91: =IF(LEN(A91)=3,"是",IF(B91<>"",IF(SUM(C91:F91)<>0,"是","否"),"是")) -> 否 | J91: =IF(LEN(A91)=3,"类",IF(LEN(A91)=5,"款","项")) -> 项
A92: 21211 | B92: 农业土地开发资金安排的支出 | C92: 0 | F92: 0 | G92: =IFERROR((F92-C92)/C92,"") | H92: =IFERROR(F92/D92,"") | I92: =IF(LEN(A92)=3,"是",IF(B92<>"",IF(SUM(C92:F92)<>0,"是","否"),"是")) -> 否 | J92: =IF(LEN(A92)=3,"类",IF(LEN(A92)=5,"款","项")) -> 款
A93: 21213 | B93: 城市基础设施配套费安排的支出 | C93: 310 | D93: =SUM(D94:D98) -> 100 | E93: =SUM(E94:E98) -> 100 | F93: =SUM(F94:F98) -> 55 | G93: =IFERROR((F93-C93)/C93,"") -> -0.82258065 | H93: =IFERROR(F93/D93,"") -> 0.55 | I93: =IF(LEN(A93)=3,"是",IF(B93<>"",IF(SUM(C93:F93)<>0,"是","否"),"是")) -> 是 | J93: =IF(LEN(A93)=3,"类",IF(LEN(A93)=5,"款","项")) -> 款
A94: 2121301 | B94: 城市公共设施 | C94: 0 | F94: 0 | G94: =IFERROR((F94-C94)/C94,"") | H94: =IFERROR(F94/D94,"") | I94: =IF(LEN(A94)=3,"是",IF(B94<>"",IF(SUM(C94:F94)<>0,"是","否"),"是")) -> 否 | J94: =IF(LEN(A94)=3,"类",IF(LEN(A94)=5,"款","项")) -> 项
A95: 2121302 | B95: 城市环境卫生 | C95: 0 | F95: 0 | G95: =IFERROR((F95-C95)/C95,"") | H95: =IFERROR(F95/D95,"") | I95: =IF(LEN(A95)=3,"是",IF(B95<>"",IF(SUM(C95:F95)<>0,"是","否"),"是")) -> 否 | J95: =IF(LEN(A95)=3,"类",IF(LEN(A95)=5,"款","项")) -> 项
A96: 2121303 | B96: 公有房屋 | C96: 0 | F96: 0 | G96: =IFERROR((F96-C96)/C96,"") | H96: =IFERROR(F96/D96,"") | I96: =IF(LEN(A96)=3,"是",IF(B96<>"",IF(SUM(C96:F96)<>0,"是","否"),"是")) -> 否 | J96: =IF(LEN(A96)=3,"类",IF(LEN(A96)=5,"款","项")) -> 项
A97: 2121304 | B97: 城市防洪 | C97: 0 | F97: 0 | G97: =IFERROR((F97-C97)/C97,"") | H97: =IFERROR(F97/D97,"") | I97: =IF(LEN(A97)=3,"是",IF(B97<>"",IF(SUM(C97:F97)<>0,"是","否"),"是")) -> 否 | J97: =IF(LEN(A97)=3,"类",IF(LEN(A97)=5,"款","项")) -> 项
A98: 2121399 | B98: 其他城市基础设施配套费安排的支出 | C98: 310 | D98: 100 | E98: 100 | F98: 55 | G98: =IFERROR((F98-C98)/C98,"") -> -0.82258065 | H98: =IFERROR(F98/D98,"") -> 0.55 | I98: =IF(LEN(A98)=3,"是",IF(B98<>"",IF(SUM(C98:F98)<>0,"是","否"),"是")) -> 是 | J98: =IF(LEN(A98)=3,"类",IF(LEN(A98)=5,"款","项")) -> 项
A99: 21214 | B99: 污水处理费收入安排的支出 | C99: 0 | F99: 0 | G99: =IFERROR((F99-C99)/C99,"") | H99: =IFERROR(F99/D99,"") | I99: =IF(LEN(A99)=3,"是",IF(B99<>"",IF(SUM(C99:F99)<>0,"是","否"),"是")) -> 否 | J99: =IF(LEN(A99)=3,"类",IF(LEN(A99)=5,"款","项")) -> 款
A100: 2121401 | B100: 污水处理设施建设和运营 | C100: 0 | F100: 0 | G100: =IFERROR((F100-C100)/C100,"") | H100: =IFERROR(F100/D100,"") | I100: =IF(LEN(A100)=3,"是",IF(B100<>"",IF(SUM(C100:F100)<>0,"是","否"),"是")) -> 否 | J100: =IF(LEN(A100)=3,"类",IF(LEN(A100)=5,"款","项")) -> 项
A101: 2121402 | B101: 代征手续费 | C101: 0 | F101: 0 | G101: =IFERROR((F101-C101)/C101,"") | H101: =IFERROR(F101/D101,"") | I101: =IF(LEN(A101)=3,"是",IF(B101<>"",IF(SUM(C101:F101)<>0,"是","否"),"是")) -> 否 | J101: =IF(LEN(A101)=3,"类",IF(LEN(A101)=5,"款","项")) -> 项
A102: 2121499 | B102: 其他污水处理费安排的支出 | C102: 0 | F102: 0 | G102: =IFERROR((F102-C102)/C102,"") | H102: =IFERROR(F102/D102,"") | I102: =IF(LEN(A102)=3,"是",IF(B102<>"",IF(SUM(C102:F102)<>0,"是","否"),"是")) -> 否 | J102: =IF(LEN(A102)=3,"类",IF(LEN(A102)=5,"款","项")) -> 项
A103: 21215 | B103: 土地储备专项债券收入安排的支出 | C103: 0 | F103: 17600 | G103: =IFERROR((F103-C103)/C103,"") | H103: =IFERROR(F103/D103,"") | I103: =IF(LEN(A103)=3,"是",IF(B103<>"",IF(SUM(C103:F103)<>0,"是","否"),"是")) -> 是 | J103: =IF(LEN(A103)=3,"类",IF(LEN(A103)=5,"款","项")) -> 款
A104: 2121501 | B104: 征地和拆迁补偿支出 | C104: 0 | F104: 17600 | G104: =IFERROR((F104-C104)/C104,"") | H104: =IFERROR(F104/D104,"") | I104: =IF(LEN(A104)=3,"是",IF(B104<>"",IF(SUM(C104:F104)<>0,"是","否"),"是")) -> 是 | J104: =IF(LEN(A104)=3,"类",IF(LEN(A104)=5,"款","项")) -> 项
A105: 2121502 | B105: 土地开发支出 | C105: 0 | F105: 0 | G105: =IFERROR((F105-C105)/C105,"") | H105: =IFERROR(F105/D105,"") | I105: =IF(LEN(A105)=3,"是",IF(B105<>"",IF(SUM(C105:F105)<>0,"是","否"),"是")) -> 否 | J105: =IF(LEN(A105)=3,"类",IF(LEN(A105)=5,"款","项")) -> 项
A106: 2121599 | B106: 其他土地储备专项债券收入安排的支出 | C106: 0 | F106: 0 | G106: =IFERROR((F106-C106)/C106,"") | H106: =IFERROR(F106/D106,"") | I106: =IF(LEN(A106)=3,"是",IF(B106<>"",IF(SUM(C106:F106)<>0,"是","否"),"是")) -> 否 | J106: =IF(LEN(A106)=3,"类",IF(LEN(A106)=5,"款","项")) -> 项
A107: 21216 | B107: 棚户区改造专项债券收入安排的支出 | C107: 0 | F107: 0 | G107: =IFERROR((F107-C107)/C107,"") | H107: =IFERROR(F107/D107,"") | I107: =IF(LEN(A107)=3,"是",IF(B107<>"",IF(SUM(C107:F107)<>0,"是","否"),"是")) -> 否 | J107: =IF(LEN(A107)=3,"类",IF(LEN(A107)=5,"款","项")) -> 款
A108: 2121601 | B108: 征地和拆迁补偿支出 | C108: 0 | F108: 0 | G108: =IFERROR((F108-C108)/C108,"") | H108: =IFERROR(F108/D108,"") | I108: =IF(LEN(A108)=3,"是",IF(B108<>"",IF(SUM(C108:F108)<>0,"是","否"),"是")) -> 否 | J108: =IF(LEN(A108)=3,"类",IF(LEN(A108)=5,"款","项")) -> 项
A109: 2121602 | B109: 土地开发支出 | C109: 0 | F109: 0 | G109: =IFERROR((F109-C109)/C109,"") | H109: =IFERROR(F109/D109,"") | I109: =IF(LEN(A109)=3,"是",IF(B109<>"",IF(SUM(C109:F109)<>0,"是","否"),"是")) -> 否 | J109: =IF(LEN(A109)=3,"类",IF(LEN(A109)=5,"款","项")) -> 项
A110: 2121699 | B110: 其他棚户区改造专项债券收入安排的支出 | C110: 0 | F110: 0 | G110: =IFERROR((F110-C110)/C110,"") | H110: =IFERROR(F110/D110,"") | I110: =IF(LEN(A110)=3,"是",IF(B110<>"",IF(SUM(C110:F110)<>0,"是","否"),"是")) -> 否 | J110: =IF(LEN(A110)=3,"类",IF(LEN(A110)=5,"款","项")) -> 项
... A128: 2121999 | B128: 其他国有土地使用权出让收入对应专项债务收入安排的支出 | C128: 0 | F128: 0 | G128: =IFERROR((F128-C128)/C128,"") | H128: =IFERROR(F128/D128,"") | I128: =IF(LEN(A128)=3,"是",IF(B128<>"",IF(SUM(C128:F128)<>0,"是","否"),"是")) -> 否 | J128: =IF(LEN(A128)=3,"类",IF(LEN(A128)=5,"款","项")) -> 项
A129: 21298 | B129: 超长期特别国债安排的支出 | C129: 11902 | D129: =SUM(D130:D131) -> 28428 | E129: =SUM(E130:E131) -> 28428 | F129: =SUM(F130:F131) -> 34230 | G129: =IFERROR((F129-C129)/C129,"") -> 1.8759872 | H129: =IFERROR(F129/D129,"") -> 1.2040946 | I129: =IF(LEN(A129)=3,"是",IF(B129<>"",IF(SUM(C129:F129)<>0,"是","否"),"是")) -> 是 | J129: =IF(LEN(A129)=3,"类",IF(LEN(A129)=5,"款","项")) -> 款
A130: 2129801 | B130: 城乡社区公共设施 | C130: 7372 | D130: 28428 | E130: 28428 | F130: 32799 | G130: =IFERROR((F130-C130)/C130,"") -> 3.4491319 | H130: =IFERROR(F130/D130,"") -> 1.1537569 | I130: =IF(LEN(A130)=3,"是",IF(B130<>"",IF(SUM(C130:F130)<>0,"是","否"),"是")) -> 是 | J130: =IF(LEN(A130)=3,"类",IF(LEN(A130)=5,"款","项")) -> 项
A131: 2129899 | B131: 其他城乡社区支出 | C131: 4530 | F131: 1431 | G131: =IFERROR((F131-C131)/C131,"") -> -0.68410596 | H131: =IFERROR(F131/D131,"") | I131: =IF(LEN(A131)=3,"是",IF(B131<>"",IF(SUM(C131:F131)<>0,"是","否"),"是")) -> 是 | J131: =IF(LEN(A131)=3,"类",IF(LEN(A131)=5,"款","项")) -> 项
A132: 213 | B132: 八、农林水支出 | C132: 7534 | D132: =D133+D138+D143+D148+D151+D156+D160+D164+D167 -> 5462 | E132: =E133+E138+E143+E148+E151+E156+E160+E164+E167 -> 5462 | F132: =F133+F138+F143+F148+F151+F156+F160+F164+F167 -> 12025 | G132: =IFERROR((F132-C132)/C132,"") -> 0.59609769 | H132: =IFERROR(F132/D132,"") -> 2.2015745 | I132: =IF(LEN(A132)=3,"是",IF(B132<>"",IF(SUM(C132:F132)<>0,"是","否"),"是")) -> 是 | J132: =IF(LEN(A132)=3,"类",IF(LEN(A132)=5,"款","项")) -> 类
...

Sheet 08
B1: 2025年市本级政府性基金预算收入执行情况表
B2: 表八 | H2: 单位：万元
A3: 科目编码 | B3: 项目 | C3: 2024年决算数 | D3: 2025年 | G3: 比较
D4: 预算数 | E4: 调整预算数 | F4: 执行数 | G4: 比2024年决算数增长% | H4: 完成2025年预算数的% | I4: 打印
A5: 1030102 | B5: 一、农网还贷资金收入 | C5: 0 | G5: =IFERROR((F5-C5)/C5,"") | H5: =IFERROR(F5/D5,"") | I5: =IF(LEN(A5)=7,"是",IF(B5<>"",IF(SUM(C5:F5)<>0,"是","否"),"是")) -> 是
A6: 1030129 | B6: 二、国家电影事业发展专项资金收入 | C6: 0 | G6: =IFERROR((F6-C6)/C6,"") | H6: =IFERROR(F6/D6,"") | I6: =IF(LEN(A6)=7,"是",IF(B6<>"",IF(SUM(C6:F6)<>0,"是","否"),"是")) -> 是
A7: 1030146 | B7: 三、国有土地收益基金收入 | C7: 0 | G7: =IFERROR((F7-C7)/C7,"") | H7: =IFERROR(F7/D7,"") | I7: =IF(LEN(A7)=7,"是",IF(B7<>"",IF(SUM(C7:F7)<>0,"是","否"),"是")) -> 是
A8: 1030147 | B8: 四、农业土地开发资金收入 | C8: 0 | G8: =IFERROR((F8-C8)/C8,"") | H8: =IFERROR(F8/D8,"") | I8: =IF(LEN(A8)=7,"是",IF(B8<>"",IF(SUM(C8:F8)<>0,"是","否"),"是")) -> 是
A9: 1030148 | B9: 五、国有土地使用权出让收入 | C9: 9556 | D9: =SUM(D10:D14) -> 42027 | E9: =SUM(E10:E14) -> 22379 | F9: =SUM(F10:F14) -> 6396 | G9: =IFERROR((F9-C9)/C9,"") -> -0.33068229 | H9: =IFERROR(F9/D9,"") -> 0.15218788 | I9: =IF(LEN(A9)=7,"是",IF(B9<>"",IF(SUM(C9:F9)<>0,"是","否"),"是")) -> 是
A10: 103014801 | B10: 土地出让价款收入 | C10: 8957 | D10: 39527 | E10: 19879 | F10: 6396 | G10: =IFERROR((F10-C10)/C10,"") -> -0.28592163 | H10: =IFERROR(F10/D10,"") -> 0.16181344 | I10: =IF(LEN(A10)=7,"是",IF(B10<>"",IF(SUM(C10:F10)<>0,"是","否"),"是")) -> 是
A11: 103014802 | B11: 补缴的土地价款 | C11: 599 | D11: 2500 | E11: 2500 | G11: =IFERROR((F11-C11)/C11,"") -> -1 | H11: =IFERROR(F11/D11,"") -> 0 | I11: =IF(LEN(A11)=7,"是",IF(B11<>"",IF(SUM(C11:F11)<>0,"是","否"),"是")) -> 是
A12: 103014803 | B12: 划拨土地收入 | C12: 0 | G12: =IFERROR((F12-C12)/C12,"") | H12: =IFERROR(F12/D12,"") | I12: =IF(LEN(A12)=7,"是",IF(B12<>"",IF(SUM(C12:F12)<>0,"是","否"),"是")) -> 否
A13: 103014898 | B13: 缴纳新增建设用地土地有偿使用费 | C13: 0 | G13: =IFERROR((F13-C13)/C13,"") | H13: =IFERROR(F13/D13,"") | I13: =IF(LEN(A13)=7,"是",IF(B13<>"",IF(SUM(C13:F13)<>0,"是","否"),"是")) -> 否
A14: 103014899 | B14: 其他土地出让收入 | C14: 0 | G14: =IFERROR((F14-C14)/C14,"") | H14: =IFERROR(F14/D14,"") | I14: =IF(LEN(A14)=7,"是",IF(B14<>"",IF(SUM(C14:F14)<>0,"是","否"),"是")) -> 否
A15: 1030150 | B15: 六、大中型水库库区基金收入 | C15: 0 | G15: =IFERROR((F15-C15)/C15,"") | H15: =IFERROR(F15/D15,"") | I15: =IF(LEN(A15)=7,"是",IF(B15<>"",IF(SUM(C15:F15)<>0,"是","否"),"是")) -> 是
A16: 1030155 | B16: 七、彩票公益金收入 | C16: 7407 | D16: =SUM(D17:D18) -> 7500 | E16: =SUM(E17:E18) -> 7500 | F16: =SUM(F17:F18) -> 7703 | G16: =IFERROR((F16-C16)/C16,"") -> 0.039962198 | H16: =IFERROR(F16/D16,"") -> 1.0270667 | I16: =IF(LEN(A16)=7,"是",IF(B16<>"",IF(SUM(C16:F16)<>0,"是","否"),"是")) -> 是
A17: 103015501 | B17: 福利彩票公益金收入 | C17: 3972 | D17: 4050 | E17: 4050 | F17: 4021 | G17: =IFERROR((F17-C17)/C17,"") -> 0.012336354 | H17: =IFERROR(F17/D17,"") -> 0.99283951 | I17: =IF(LEN(A17)=7,"是",IF(B17<>"",IF(SUM(C17:F17)<>0,"是","否"),"是")) -> 是
A18: 103015502 | B18: 体育彩票公益金收入 | C18: 3435 | D18: 3450 | E18: 3450 | F18: 3682 | G18: =IFERROR((F18-C18)/C18,"") -> 0.071906841 | H18: =IFERROR(F18/D18,"") -> 1.0672464 | I18: =IF(LEN(A18)=7,"是",IF(B18<>"",IF(SUM(C18:F18)<>0,"是","否"),"是")) -> 是
A19: 1030156 | B19: 八、城市基础设施配套费收入 | C19: 177 | F19: 295 | G19: =IFERROR((F19-C19)/C19,"") -> 0.66666667 | H19: =IFERROR(F19/D19,"") | I19: =IF(LEN(A19)=7,"是",IF(B19<>"",IF(SUM(C19:F19)<>0,"是","否"),"是")) -> 是
A20: 1030157 | B20: 九、小型水库移民扶助基金收入 | C20: 0 | G20: =IFERROR((F20-C20)/C20,"") | H20: =IFERROR(F20/D20,"") | I20: =IF(LEN(A20)=7,"是",IF(B20<>"",IF(SUM(C20:F20)<>0,"是","否"),"是")) -> 是
A21: 1030158 | B21: 十、国家重大水利工程建设基金收入 | C21: 0 | G21: =IFERROR((F21-C21)/C21,"") | H21: =IFERROR(F21/D21,"") | I21: =IF(LEN(A21)=7,"是",IF(B21<>"",IF(SUM(C21:F21)<>0,"是","否"),"是")) -> 是
A22: 1030159 | B22: 十一、车辆通行费 | C22: 0 | G22: =IFERROR((F22-C22)/C22,"") | H22: =IFERROR(F22/D22,"") | I22: =IF(LEN(A22)=7,"是",IF(B22<>"",IF(SUM(C22:F22)<>0,"是","否"),"是")) -> 是
A23: 1030178 | B23: 十二、污水处理费收入 | C23: 0 | G23: =IFERROR((F23-C23)/C23,"") | H23: =IFERROR(F23/D23,"") | I23: =IF(LEN(A23)=7,"是",IF(B23<>"",IF(SUM(C23:F23)<>0,"是","否"),"是")) -> 是
A24: 1030180 | B24: 十三、彩票发行机构和彩票销售机构的业务费用 | C24: 0 | G24: =IFERROR((F24-C24)/C24,"") | H24: =IFERROR(F24/D24,"") | I24: =IF(LEN(A24)=7,"是",IF(B24<>"",IF(SUM(C24:F24)<>0,"是","否"),"是")) -> 是
A25: 1030199 | B25: 十四、其他政府性基金收入 | C25: 0 | G25: =IFERROR((F25-C25)/C25,"") | H25: =IFERROR(F25/D25,"") | I25: =IF(LEN(A25)=7,"是",IF(B25<>"",IF(SUM(C25:F25)<>0,"是","否"),"是")) -> 是
A26: 10310 | B26: 十五、专项债券对应项目专项收入 | C26: 19298 | D26: 20930 | E26: 20930 | F26: 26034 | G26: =IFERROR((F26-C26)/C26,"") -> 0.34905172 | H26: =IFERROR(F26/D26,"") -> 1.2438605 | I26: =IF(LEN(A26)=7,"是",IF(B26<>"",IF(SUM(C26:F26)<>0,"是","否"),"是")) -> 是
G27: =IFERROR((F27-C27)/C27,"") | H27: =IFERROR(F27/D27,"") | I27: =IF(LEN(A27)=7,"是",IF(B27<>"",IF(SUM(C27:F27)<>0,"是","否"),"是")) -> 是
B28: 市本级政府性基金预算收入 | C28: =C5+C6+C7+C8+C9+C15+C16+C19+C20+C21+C22+C23+C24+C25+C26 -> 36438 | D28: =D5+D6+D7+D8+D9+D15+D16+D19+D20+D21+D22+D23+D24+D25+D26 -> 70457 | E28: =E5+E6+E7+E8+E9+E15+E16+E19+E20+E21+E22+E23+E24+E25+E26 -> 50809 | F28: =F5+F6+F7+F8+F9+F15+F16+F19+F20+F21+F22+F23+F24+F25+F26 -> 40428 | G28: =IFERROR((F28-C28)/C28,"") -> 0.10950107 | H28: =IFERROR(F28/D28,"") -> 0.57379678 | I28: =IF(LEN(A28)=7,"是",IF(B28<>"",IF(SUM(C28:F28)<>0,"是","否"),"是")) -> 是
A29: 105 | B29: 地方政府专项债务收入 | C29: 419670 | D29: 234030 | E29: 487330 | F29: 487330 | G29: =IFERROR((F29-C29)/C29,"") -> 0.16122191 | H29: =IFERROR(F29/D29,"") -> 2.0823399 | I29: =IF(LEN(A29)=7,"是",IF(B29<>"",IF(SUM(C29:F29)<>0,"是","否"),"是")) -> 是
A30: 110 | B30: 转移性收入 | C30: =C31+C33+C34+C35 -> 78228 | D30: =D31+D33+D34+D35 -> 84352 | E30: =E31+E33+E34+E35 -> 84352 | F30: =F31+F33+F34+F35 -> 49133 | G30: =IFERROR((F30-C30)/C30,"") -> -0.37192565 | H30: =IFERROR(F30/D30,"") -> 0.58247582 | I30: =IF(LEN(A30)=7,"是",IF(B30<>"",IF(SUM(C30:F30)<>0,"是","否"),"是")) -> 是
A31: 11004 | B31: 政府性基金转移支付收入 | C31: =C32 -> 71831 | D31: =D32 -> 73006 | E31: =E32 -> 73006 | F31: =F32 -> 40064 | G31: =IFERROR((F31-C31)/C31,"") -> -0.44224638 | H31: =IFERROR(F31/D31,"") -> 0.54877681 | I31: =IF(LEN(A31)=7,"是",IF(B31<>"",IF(SUM(C31:F31)<>0,"是","否"),"是")) -> 是
A32: 1100401 | B32: 政府性基金补助收入 | C32: 71831 | D32: 73006 | E32: 73006 | F32: 40064 | G32: =IFERROR((F32-C32)/C32,"") -> -0.44224638 | H32: =IFERROR(F32/D32,"") -> 0.54877681 | I32: =IF(LEN(A32)=7,"是",IF(B32<>"",IF(SUM(C32:F32)<>0,"是","否"),"是")) -> 是
A33: 11006 | B33: 上解收入 | C33: 1759 | D33: 3912 | E33: 3912 | F33: 1635 | G33: =IFERROR((F33-C33)/C33,"") -> -0.070494599 | H33: =IFERROR(F33/D33,"") -> 0.41794479 | I33: =IF(LEN(A33)=7,"是",IF(B33<>"",IF(SUM(C33:F33)<>0,"是","否"),"是")) -> 是
A34: 11008 | B34: 上年结余收入 | C34: 4638 | D34: 7434 | E34: 7434 | F34: 7434 | G34: =IFERROR((F34-C34)/C34,"") -> 0.60284605 | H34: =IFERROR(F34/D34,"") -> 1 | I34: =IF(LEN(A34)=7,"是",IF(B34<>"",IF(SUM(C34:F34)<>0,"是","否"),"是")) -> 是
A35: 11009 | B35: 调入资金 | C35: 0 | G35: =IFERROR((F35-C35)/C35,"") | H35: =IFERROR(F35/D35,"") | I35: =IF(LEN(A35)=7,"是",IF(B35<>"",IF(SUM(C35:F35)<>0,"是","否"),"是")) -> 否
B36: 各项收入合计 | C36: =SUM(C28:C30) -> 534336 | D36: =SUM(D28:D30) -> 388839 | E36: =SUM(E28:E30) -> 622491 | F36: =SUM(F28:F30) -> 576891 | G36: =IFERROR((F36-C36)/C36,"") -> 0.0796409 | H36: =IFERROR(F36/D36,"") -> 1.4836243 | I36: =IF(LEN(A36)=7,"是",IF(B36<>"",IF(SUM(C36:F36)<>0,"是","否"),"是")) -> 是

Sheet 09
B1: 2025年市本级政府性基金预算支出执行情况表
B2: 表九 | H2: 单位：万元
A3: 科目编码 | B3: 项目 | C3: 2024年决算数 | D3: 2025年 | G3: 比较
D4: 预算数 | E4: 调整预算数 | F4: 执行数 | G4: 比2024年决算数增长% | H4: 完成2025年预算数的% | I4: 打印 | J4: 类
A5: 205 | B5: 一、教育支出 | C5: 0 | F5: 0 | G5: =IFERROR((F5-C5)/C5,"") | H5: =IFERROR(F5/D5,"") | I5: =IF(LEN(A5)=3,"是",IF(B5<>"",IF(SUM(C5:F5)<>0,"是","否"),"是")) -> 是 | J5: =IF(LEN(A5)=3,"类",IF(LEN(A5)=5,"款","项")) -> 类
A6: 20598 | B6: 超长期特别国债安排的支出 | C6: 0 | F6: 0 | G6: =IFERROR((F6-C6)/C6,"") | H6: =IFERROR(F6/D6,"") | I6: =IF(LEN(A6)=3,"是",IF(B6<>"",IF(SUM(C6:F6)<>0,"是","否"),"是")) -> 否 | J6: =IF(LEN(A6)=3,"类",IF(LEN(A6)=5,"款","项")) -> 款
A7: 2059801 | B7: 基础教育 | C7: 0 | F7: 0 | G7: =IFERROR((F7-C7)/C7,"") | H7: =IFERROR(F7/D7,"") | I7: =IF(LEN(A7)=3,"是",IF(B7<>"",IF(SUM(C7:F7)<>0,"是","否"),"是")) -> 否 | J7: =IF(LEN(A7)=3,"类",IF(LEN(A7)=5,"款","项")) -> 项
A8: 2059802 | B8: 高等教育 | C8: 0 | F8: 0 | G8: =IFERROR((F8-C8)/C8,"") | H8: =IFERROR(F8/D8,"") | I8: =IF(LEN(A8)=3,"是",IF(B8<>"",IF(SUM(C8:F8)<>0,"是","否"),"是")) -> 否 | J8: =IF(LEN(A8)=3,"类",IF(LEN(A8)=5,"款","项")) -> 项
A9: 2059803 | B9: 职业教育 | C9: 0 | F9: 0 | G9: =IFERROR((F9-C9)/C9,"") | H9: =IFERROR(F9/D9,"") | I9: =IF(LEN(A9)=3,"是",IF(B9<>"",IF(SUM(C9:F9)<>0,"是","否"),"是")) -> 否 | J9: =IF(LEN(A9)=3,"类",IF(LEN(A9)=5,"款","项")) -> 项
A10: 2059804 | B10: 特殊教育 | C10: 0 | F10: 0 | G10: =IFERROR((F10-C10)/C10,"") | H10: =IFERROR(F10/D10,"") | I10: =IF(LEN(A10)=3,"是",IF(B10<>"",IF(SUM(C10:F10)<>0,"是","否"),"是")) -> 否 | J10: =IF(LEN(A10)=3,"类",IF(LEN(A10)=5,"款","项")) -> 项
A11: 2059899 | B11: 其他教育支出 | C11: 0 | F11: 0 | G11: =IFERROR((F11-C11)/C11,"") | H11: =IFERROR(F11/D11,"") | I11: =IF(LEN(A11)=3,"是",IF(B11<>"",IF(SUM(C11:F11)<>0,"是","否"),"是")) -> 否 | J11: =IF(LEN(A11)=3,"类",IF(LEN(A11)=5,"款","项")) -> 项
A12: 206 | B12: 二、科学技术支出 | C12: 0 | F12: 0 | G12: =IFERROR((F12-C12)/C12,"") | H12: =IFERROR(F12/D12,"") | I12: =IF(LEN(A12)=3,"是",IF(B12<>"",IF(SUM(C12:F12)<>0,"是","否"),"是")) -> 是 | J12: =IF(LEN(A12)=3,"类",IF(LEN(A12)=5,"款","项")) -> 类
A13: 20698 | B13: 超长期特别国债安排的支出 | C13: 0 | F13: 0 | G13: =IFERROR((F13-C13)/C13,"") | H13: =IFERROR(F13/D13,"") | I13: =IF(LEN(A13)=3,"是",IF(B13<>"",IF(SUM(C13:F13)<>0,"是","否"),"是")) -> 否 | J13: =IF(LEN(A13)=3,"类",IF(LEN(A13)=5,"款","项")) -> 款
A14: 2069801 | B14: 基础研究 | C14: 0 | F14: 0 | G14: =IFERROR((F14-C14)/C14,"") | H14: =IFERROR(F14/D14,"") | I14: =IF(LEN(A14)=3,"是",IF(B14<>"",IF(SUM(C14:F14)<>0,"是","否"),"是")) -> 否 | J14: =IF(LEN(A14)=3,"类",IF(LEN(A14)=5,"款","项")) -> 项
A15: 2069802 | B15: 应用研究 | C15: 0 | F15: 0 | G15: =IFERROR((F15-C15)/C15,"") | H15: =IFERROR(F15/D15,"") | I15: =IF(LEN(A15)=3,"是",IF(B15<>"",IF(SUM(C15:F15)<>0,"是","否"),"是")) -> 否 | J15: =IF(LEN(A15)=3,"类",IF(LEN(A15)=5,"款","项")) -> 项
A16: 2069803 | B16: 技术研究与开发 | C16: 0 | F16: 0 | G16: =IFERROR((F16-C16)/C16,"") | H16: =IFERROR(F16/D16,"") | I16: =IF(LEN(A16)=3,"是",IF(B16<>"",IF(SUM(C16:F16)<>0,"是","否"),"是")) -> 否 | J16: =IF(LEN(A16)=3,"类",IF(LEN(A16)=5,"款","项")) -> 项
... A35: 2071099 | B35: 其他国家电影事业发展专项资金对应专项债务收入支出 | C35: 0 | F35: 0 | G35: =IFERROR((F35-C35)/C35,"") | H35: =IFERROR(F35/D35,"") | I35: =IF(LEN(A35)=3,"是",IF(B35<>"",IF(SUM(C35:F35)<>0,"是","否"),"是")) -> 否 | J35: =IF(LEN(A35)=3,"类",IF(LEN(A35)=5,"款","项")) -> 项
A36: 20798 | B36: 超长期特别国债安排的支出 | F36: 0 | G36: =IFERROR((F36-C36)/C36,"") | H36: =IFERROR(F36/D36,"") | I36: =IF(LEN(A36)=3,"是",IF(B36<>"",IF(SUM(C36:F36)<>0,"是","否"),"是")) -> 否 | J36: =IF(LEN(A36)=3,"类",IF(LEN(A36)=5,"款","项")) -> 款
A37: 2079801 | B37: 文化和旅游 | F37: 0 | G37: =IFERROR((F37-C37)/C37,"") | H37: =IFERROR(F37/D37,"") | I37: =IF(LEN(A37)=3,"是",IF(B37<>"",IF(SUM(C37:F37)<>0,"是","否"),"是")) -> 否 | J37: =IF(LEN(A37)=3,"类",IF(LEN(A37)=5,"款","项")) -> 项
A38: 2079802 | B38: 文物 | F38: 0 | G38: =IFERROR((F38-C38)/C38,"") | H38: =IFERROR(F38/D38,"") | I38: =IF(LEN(A38)=3,"是",IF(B38<>"",IF(SUM(C38:F38)<>0,"是","否"),"是")) -> 否 | J38: =IF(LEN(A38)=3,"类",IF(LEN(A38)=5,"款","项")) -> 项
A39: 2079803 | B39: 体育 | F39: 0 | G39: =IFERROR((F39-C39)/C39,"") | H39: =IFERROR(F39/D39,"") | I39: =IF(LEN(A39)=3,"是",IF(B39<>"",IF(SUM(C39:F39)<>0,"是","否"),"是")) -> 否 | J39: =IF(LEN(A39)=3,"类",IF(LEN(A39)=5,"款","项")) -> 项
A40: 2079804 | B40: 新闻出版电影 | F40: 0 | G40: =IFERROR((F40-C40)/C40,"") | H40: =IFERROR(F40/D40,"") | I40: =IF(LEN(A40)=3,"是",IF(B40<>"",IF(SUM(C40:F40)<>0,"是","否"),"是")) -> 否 | J40: =IF(LEN(A40)=3,"类",IF(LEN(A40)=5,"款","项")) -> 项
A41: 2079805 | B41: 广播电视 | F41: 0 | G41: =IFERROR((F41-C41)/C41,"") | H41: =IFERROR(F41/D41,"") | I41: =IF(LEN(A41)=3,"是",IF(B41<>"",IF(SUM(C41:F41)<>0,"是","否"),"是")) -> 否 | J41: =IF(LEN(A41)=3,"类",IF(LEN(A41)=5,"款","项")) -> 项
A42: 2079899 | B42: 其他文化旅游体育与传媒支出 | F42: 0 | G42: =IFERROR((F42-C42)/C42,"") | H42: =IFERROR(F42/D42,"") | I42: =IF(LEN(A42)=3,"是",IF(B42<>"",IF(SUM(C42:F42)<>0,"是","否"),"是")) -> 否 | J42: =IF(LEN(A42)=3,"类",IF(LEN(A42)=5,"款","项")) -> 项
A43: 208 | B43: 四、社会保障和就业支出 | C43: 0 | F43: 0 | G43: =IFERROR((F43-C43)/C43,"") | H43: =IFERROR(F43/D43,"") | I43: =IF(LEN(A43)=3,"是",IF(B43<>"",IF(SUM(C43:F43)<>0,"是","否"),"是")) -> 是 | J43: =IF(LEN(A43)=3,"类",IF(LEN(A43)=5,"款","项")) -> 类
A44: 20898 | B44: 超长期特别国债安排的支出 | C44: 0 | F44: 0 | G44: =IFERROR((F44-C44)/C44,"") | H44: =IFERROR(F44/D44,"") | I44: =IF(LEN(A44)=3,"是",IF(B44<>"",IF(SUM(C44:F44)<>0,"是","否"),"是")) -> 否 | J44: =IF(LEN(A44)=3,"类",IF(LEN(A44)=5,"款","项")) -> 款
A45: 2089801 | B45: 养老机构及服务设施 | C45: 0 | F45: 0 | G45: =IFERROR((F45-C45)/C45,"") | H45: =IFERROR(F45/D45,"") | I45: =IF(LEN(A45)=3,"是",IF(B45<>"",IF(SUM(C45:F45)<>0,"是","否"),"是")) -> 否 | J45: =IF(LEN(A45)=3,"类",IF(LEN(A45)=5,"款","项")) -> 项
A46: 2089802 | B46: 公共就业服务设施 | C46: 0 | F46: 0 | G46: =IFERROR((F46-C46)/C46,"") | H46: =IFERROR(F46/D46,"") | I46: =IF(LEN(A46)=3,"是",IF(B46<>"",IF(SUM(C46:F46)<>0,"是","否"),"是")) -> 否 | J46: =IF(LEN(A46)=3,"类",IF(LEN(A46)=5,"款","项")) -> 项
A47: 2089899 | B47: 其他社会保险和就业支出 | C47: 0 | F47: 0 | G47: =IFERROR((F47-C47)/C47,"") | H47: =IFERROR(F47/D47,"") | I47: =IF(LEN(A47)=3,"是",IF(B47<>"",IF(SUM(C47:F47)<>0,"是","否"),"是")) -> 否 | J47: =IF(LEN(A47)=3,"类",IF(LEN(A47)=5,"款","项")) -> 项
A48: 210 | B48: 五、卫生健康支出 | C48: 0 | F48: 0 | G48: =IFERROR((F48-C48)/C48,"") | H48: =IFERROR(F48/D48,"") | I48: =IF(LEN(A48)=3,"是",IF(B48<>"",IF(SUM(C48:F48)<>0,"是","否"),"是")) -> 是 | J48: =IF(LEN(A48)=3,"类",IF(LEN(A48)=5,"款","项")) -> 类
A49: 21098 | B49: 超长期特别国债安排的支出 | C49: 0 | F49: 0 | G49: =IFERROR((F49-C49)/C49,"") | H49: =IFERROR(F49/D49,"") | I49: =IF(LEN(A49)=3,"是",IF(B49<>"",IF(SUM(C49:F49)<>0,"是","否"),"是")) -> 否 | J49: =IF(LEN(A49)=3,"类",IF(LEN(A49)=5,"款","项")) -> 款
A50: 2109801 | B50: 公立医院 | C50: 0 | F50: 0 | G50: =IFERROR((F50-C50)/C50,"") | H50: =IFERROR(F50/D50,"") | I50: =IF(LEN(A50)=3,"是",IF(B50<>"",IF(SUM(C50:F50)<>0,"是","否"),"是")) -> 否 | J50: =IF(LEN(A50)=3,"类",IF(LEN(A50)=5,"款","项")) -> 项
A51: 2109802 | B51: 基层医疗卫生机构 | C51: 0 | F51: 0 | G51: =IFERROR((F51-C51)/C51,"") | H51: =IFERROR(F51/D51,"") | I51: =IF(LEN(A51)=3,"是",IF(B51<>"",IF(SUM(C51:F51)<>0,"是","否"),"是")) -> 否 | J51: =IF(LEN(A51)=3,"类",IF(LEN(A51)=5,"款","项")) -> 项
A52: 2109803 | B52: 公共卫生机构 | C52: 0 | F52: 0 | G52: =IFERROR((F52-C52)/C52,"") | H52: =IFERROR(F52/D52,"") | I52: =IF(LEN(A52)=3,"是",IF(B52<>"",IF(SUM(C52:F52)<>0,"是","否"),"是")) -> 否 | J52: =IF(LEN(A52)=3,"类",IF(LEN(A52)=5,"款","项")) -> 项
A53: 2109804 | B53: 托育机构 | C53: 0 | F53: 0 | G53: =IFERROR((F53-C53)/C53,"") | H53: =IFERROR(F53/D53,"") | I53: =IF(LEN(A53)=3,"是",IF(B53<>"",IF(SUM(C53:F53)<>0,"是","否"),"是")) -> 否 | J53: =IF(LEN(A53)=3,"类",IF(LEN(A53)=5,"款","项")) -> 项
A54: 2109899 | B54: 其他卫生健康支出 | C54: 0 | F54: 0 | G54: =IFERROR((F54-C54)/C54,"") | H54: =IFERROR(F54/D54,"") | I54: =IF(LEN(A54)=3,"是",IF(B54<>"",IF(SUM(C54:F54)<>0,"是","否"),"是")) -> 否 | J54: =IF(LEN(A54)=3,"类",IF(LEN(A54)=5,"款","项")) -> 项
... A70: 2119899 | B70: 其他节能环保支出 | C70: 0 | F70: 0 | G70: =IFERROR((F70-C70)/C70,"") | H70: =IFERROR(F70/D70,"") | I70: =IF(LEN(A70)=3,"是",IF(B70<>"",IF(SUM(C70:F70)<>0,"是","否"),"是")) -> 否 | J70: =IF(LEN(A70)=3,"类",IF(LEN(A70)=5,"款","项")) -> 项
A71: 212 | B71: 七、城乡社区支出 | C71: 6239 | D71: =D72+D88+D92+D93+D99+D103+D107+D111+D117+D120+D129 -> 12712 | E71: =E72+E88+E92+E93+E99+E103+E107+E111+E117+E120+E129 -> 12712 | F71: =F72+F88+F92+F93+F99+F103+F107+F111+F117+F120+F129 -> 2255 | G71: =IFERROR((F71-C71)/C71,"") -> -0.63856387 | H71: =IFERROR(F71/D71,"") -> 0.17739144 | I71: =IF(LEN(A71)=3,"是",IF(B71<>"",IF(SUM(C71:F71)<>0,"是","否"),"是")) -> 是 | J71: =IF(LEN(A71)=3,"类",IF(LEN(A71)=5,"款","项")) -> 类
A72: 21208 | B72: 国有土地使用权出让收入安排的支出 | C72: 1572 | D72: =SUM(D73:D87) -> 10499 | E72: =SUM(E73:E87) -> 10499 | F72: =SUM(F73:F87) -> 2255 | G72: =IFERROR((F72-C72)/C72,"") -> 0.43447837 | H72: =IFERROR(F72/D72,"") -> 0.21478236 | I72: =IF(LEN(A72)=3,"是",IF(B72<>"",IF(SUM(C72:F72)<>0,"是","否"),"是")) -> 是 | J72: =IF(LEN(A72)=3,"类",IF(LEN(A72)=5,"款","项")) -> 款
A73: 2120801 | B73: 征地和拆迁补偿支出 | C73: 0 | F73: 0 | G73: =IFERROR((F73-C73)/C73,"") | H73: =IFERROR(F73/D73,"") | I73: =IF(LEN(A73)=3,"是",IF(B73<>"",IF(SUM(C73:F73)<>0,"是","否"),"是")) -> 否 | J73: =IF(LEN(A73)=3,"类",IF(LEN(A73)=5,"款","项")) -> 项
A74: 2120802 | B74: 土地开发支出 | C74: 800 | D74: 8649 | E74: 8649 | F74: 2200 | G74: =IFERROR((F74-C74)/C74,"") -> 1.75 | H74: =IFERROR(F74/D74,"") -> 0.25436467 | I74: =IF(LEN(A74)=3,"是",IF(B74<>"",IF(SUM(C74:F74)<>0,"是","否"),"是")) -> 是 | J74: =IF(LEN(A74)=3,"类",IF(LEN(A74)=5,"款","项")) -> 项
A75: 2120803 | B75: 城市建设支出 | C75: 0 | F75: 0 | G75: =IFERROR((F75-C75)/C75,"") | H75: =IFERROR(F75/D75,"") | I75: =IF(LEN(A75)=3,"是",IF(B75<>"",IF(SUM(C75:F75)<>0,"是","否"),"是")) -> 否 | J75: =IF(LEN(A75)=3,"类",IF(LEN(A75)=5,"款","项")) -> 项
A76: 2120804 | B76: 农村基础设施建设支出 | C76: 0 | F76: 0 | G76: =IFERROR((F76-C76)/C76,"") | H76: =IFERROR(F76/D76,"") | I76: =IF(LEN(A76)=3,"是",IF(B76<>"",IF(SUM(C76:F76)<>0,"是","否"),"是")) -> 否 | J76: =IF(LEN(A76)=3,"类",IF(LEN(A76)=5,"款","项")) -> 项
A77: 2120805 | B77: 补助被征地农民支出 | C77: 0 | F77: 0 | G77: =IFERROR((F77-C77)/C77,"") | H77: =IFERROR(F77/D77,"") | I77: =IF(LEN(A77)=3,"是",IF(B77<>"",IF(SUM(C77:F77)<>0,"是","否"),"是")) -> 否 | J77: =IF(LEN(A77)=3,"类",IF(LEN(A77)=5,"款","项")) -> 项
A78: 2120806 | B78: 土地出让业务支出 | C78: 98 | D78: 150 | E78: 150 | F78: 55 | G78: =IFERROR((F78-C78)/C78,"") -> -0.43877551 | H78: =IFERROR(F78/D78,"") -> 0.36666667 | I78: =IF(LEN(A78)=3,"是",IF(B78<>"",IF(SUM(C78:F78)<>0,"是","否"),"是")) -> 是 | J78: =IF(LEN(A78)=3,"类",IF(LEN(A78)=5,"款","项")) -> 项
A79: 2120807 | B79: 廉租住房支出 | C79: 0 | F79: 0 | G79: =IFERROR((F79-C79)/C79,"") | H79: =IFERROR(F79/D79,"") | I79: =IF(LEN(A79)=3,"是",IF(B79<>"",IF(SUM(C79:F79)<>0,"是","否"),"是")) -> 否 | J79: =IF(LEN(A79)=3,"类",IF(LEN(A79)=5,"款","项")) -> 项
A80: 2120809 | B80: 支付破产或改制企业职工安置费 | C80: 0 | F80: 0 | G80: =IFERROR((F80-C80)/C80,"") | H80: =IFERROR(F80/D80,"") | I80: =IF(LEN(A80)=3,"是",IF(B80<>"",IF(SUM(C80:F80)<>0,"是","否"),"是")) -> 否 | J80: =IF(LEN(A80)=3,"类",IF(LEN(A80)=5,"款","项")) -> 项
A81: 2120810 | B81: 棚户区改造支出 | C81: 0 | F81: 0 | G81: =IFERROR((F81-C81)/C81,"") | H81: =IFERROR(F81/D81,"") | I81: =IF(LEN(A81)=3,"是",IF(B81<>"",IF(SUM(C81:F81)<>0,"是","否"),"是")) -> 否 | J81: =IF(LEN(A81)=3,"类",IF(LEN(A81)=5,"款","项")) -> 项
A82: 2120811 | B82: 公共租赁住房支出 | C82: 0 | F82: 0 | G82: =IFERROR((F82-C82)/C82,"") | H82: =IFERROR(F82/D82,"") | I82: =IF(LEN(A82)=3,"是",IF(B82<>"",IF(SUM(C82:F82)<>0,"是","否"),"是")) -> 否 | J82: =IF(LEN(A82)=3,"类",IF(LEN(A82)=5,"款","项")) -> 项
A83: 2120813 | B83: 保障性住房租金补贴 | C83: 0 | F83: 0 | G83: =IFERROR((F83-C83)/C83,"") | H83: =IFERROR(F83/D83,"") | I83: =IF(LEN(A83)=3,"是",IF(B83<>"",IF(SUM(C83:F83)<>0,"是","否"),"是")) -> 否 | J83: =IF(LEN(A83)=3,"类",IF(LEN(A83)=5,"款","项")) -> 项
A84: 2120814 | B84: 农业生产发展支出 | C84: 674 | D84: 1200 | E84: 1200 | F84: 0 | G84: =IFERROR((F84-C84)/C84,"") -> -1 | H84: =IFERROR(F84/D84,"") -> 0 | I84: =IF(LEN(A84)=3,"是",IF(B84<>"",IF(SUM(C84:F84)<>0,"是","否"),"是")) -> 是 | J84: =IF(LEN(A84)=3,"类",IF(LEN(A84)=5,"款","项")) -> 项
A85: 2120815 | B85: 农村社会事业支出 | C85: 0 | D85: 500 | E85: 500 | F85: 0 | G85: =IFERROR((F85-C85)/C85,"") | H85: =IFERROR(F85/D85,"") -> 0 | I85: =IF(LEN(A85)=3,"是",IF(B85<>"",IF(SUM(C85:F85)<>0,"是","否"),"是")) -> 是 | J85: =IF(LEN(A85)=3,"类",IF(LEN(A85)=5,"款","项")) -> 项
A86: 2120816 | B86: 农业农村生态环境支出 | C86: 0 | F86: 0 | G86: =IFERROR((F86-C86)/C86,"") | H86: =IFERROR(F86/D86,"") | I86: =IF(LEN(A86)=3,"是",IF(B86<>"",IF(SUM(C86:F86)<>0,"是","否"),"是")) -> 否 | J86: =IF(LEN(A86)=3,"类",IF(LEN(A86)=5,"款","项")) -> 项
A87: 2120899 | B87: 其他国有土地使用权出让收入安排的支出 | C87: 0 | F87: 0 | G87: =IFERROR((F87-C87)/C87,"") | H87: =IFERROR(F87/D87,"") | I87: =IF(LEN(A87)=3,"是",IF(B87<>"",IF(SUM(C87:F87)<>0,"是","否"),"是")) -> 否 | J87: =IF(LEN(A87)=3,"类",IF(LEN(A87)=5,"款","项")) -> 项
A88: 21210 | B88: 国有土地收益基金安排的支出 | C88: 0 | F88: 0 | G88: =IFERROR((F88-C88)/C88,"") | H88: =IFERROR(F88/D88,"") | I88: =IF(LEN(A88)=3,"是",IF(B88<>"",IF(SUM(C88:F88)<>0,"是","否"),"是")) -> 否 | J88: =IF(LEN(A88)=3,"类",IF(LEN(A88)=5,"款","项")) -> 款
A89: 2121001 | B89: 征地和拆迁补偿支出 | C89: 0 | F89: 0 | G89: =IFERROR((F89-C89)/C89,"") | H89: =IFERROR(F89/D89,"") | I89: =IF(LEN(A89)=3,"是",IF(B89<>"",IF(SUM(C89:F89)<>0,"是","否"),"是")) -> 否 | J89: =IF(LEN(A89)=3,"类",IF(LEN(A89)=5,"款","项")) -> 项
A90: 2121002 | B90: 土地开发支出 | C90: 0 | F90: 0 | G90: =IFERROR((F90-C90)/C90,"") | H90: =IFERROR(F90/D90,"") | I90: =IF(LEN(A90)=3,"是",IF(B90<>"",IF(SUM(C90:F90)<>0,"是","否"),"是")) -> 否 | J90: =IF(LEN(A90)=3,"类",IF(LEN(A90)=5,"款","项")) -> 项
A91: 2121099 | B91: 其他国有土地收益基金支出 | C91: 0 | F91: 0 | G91: =IFERROR((F91-C91)/C91,"") | H91: =IFERROR(F91/D91,"") | I91: =IF(LEN(A91)=3,"是",IF(B91<>"",IF(SUM(C91:F91)<>0,"是","否"),"是")) -> 否 | J91: =IF(LEN(A91)=3,"类",IF(LEN(A91)=5,"款","项")) -> 项
A92: 21211 | B92: 农业土地开发资金安排的支出 | C92: 0 | F92: 0 | G92: =IFERROR((F92-C92)/C92,"") | H92: =IFERROR(F92/D92,"") | I92: =IF(LEN(A92)=3,"是",IF(B92<>"",IF(SUM(C92:F92)<>0,"是","否"),"是")) -> 否 | J92: =IF(LEN(A92)=3,"类",IF(LEN(A92)=5,"款","项")) -> 款
A93: 21213 | B93: 城市基础设施配套费安排的支出 | C93: 137 | F93: 0 | G93: =IFERROR((F93-C93)/C93,"") -> -1 | H93: =IFERROR(F93/D93,"") | I93: =IF(LEN(A93)=3,"是",IF(B93<>"",IF(SUM(C93:F93)<>0,"是","否"),"是")) -> 是 | J93: =IF(LEN(A93)=3,"类",IF(LEN(A93)=5,"款","项")) -> 款
A94: 2121301 | B94: 城市公共设施 | C94: 0 | F94: 0 | G94: =IFERROR((F94-C94)/C94,"") | H94: =IFERROR(F94/D94,"") | I94: =IF(LEN(A94)=3,"是",IF(B94<>"",IF(SUM(C94:F94)<>0,"是","否"),"是")) -> 否 | J94: =IF(LEN(A94)=3,"类",IF(LEN(A94)=5,"款","项")) -> 项
A95: 2121302 | B95: 城市环境卫生 | C95: 0 | F95: 0 | G95: =IFERROR((F95-C95)/C95,"") | H95: =IFERROR(F95/D95,"") | I95: =IF(LEN(A95)=3,"是",IF(B95<>"",IF(SUM(C95:F95)<>0,"是","否"),"是")) -> 否 | J95: =IF(LEN(A95)=3,"类",IF(LEN(A95)=5,"款","项")) -> 项
A96: 2121303 | B96: 公有房屋 | C96: 0 | F96: 0 | G96: =IFERROR((F96-C96)/C96,"") | H96: =IFERROR(F96/D96,"") | I96: =IF(LEN(A96)=3,"是",IF(B96<>"",IF(SUM(C96:F96)<>0,"是","否"),"是")) -> 否 | J96: =IF(LEN(A96)=3,"类",IF(LEN(A96)=5,"款","项")) -> 项
A97: 2121304 | B97: 城市防洪 | C97: 0 | F97: 0 | G97: =IFERROR((F97-C97)/C97,"") | H97: =IFERROR(F97/D97,"") | I97: =IF(LEN(A97)=3,"是",IF(B97<>"",IF(SUM(C97:F97)<>0,"是","否"),"是")) -> 否 | J97: =IF(LEN(A97)=3,"类",IF(LEN(A97)=5,"款","项")) -> 项
... A128: 2121999 | B128: 其他国有土地使用权出让收入对应专项债务收入安排的支出 | C128: 0 | F128: 0 | G128: =IFERROR((F128-C128)/C128,"") | H128: =IFERROR(F128/D128,"") | I128: =IF(LEN(A128)=3,"是",IF(B128<>"",IF(SUM(C128:F128)<>0,"是","否"),"是")) -> 否 | J128: =IF(LEN(A128)=3,"类",IF(LEN(A128)=5,"款","项")) -> 项
A129: 21298 | B129: 超长期特别国债安排的支出 | C129: 4530 | D129: =SUM(D130:D131) -> 2213 | E129: =SUM(E130:E131) -> 2213 | F129: 0 | G129: =IFERROR((F129-C129)/C129,"") -> -1 | H129: =IFERROR(F129/D129,"") -> 0 | I129: =IF(LEN(A129)=3,"是",IF(B129<>"",IF(SUM(C129:F129)<>0,"是","否"),"是")) -> 是 | J129: =IF(LEN(A129)=3,"类",IF(LEN(A129)=5,"款","项")) -> 款
A130: 2129801 | B130: 城乡社区公共设施 | C130: 0 | F130: 0 | G130: =IFERROR((F130-C130)/C130,"") | H130: =IFERROR(F130/D130,"") | I130: =IF(LEN(A130)=3,"是",IF(B130<>"",IF(SUM(C130:F130)<>0,"是","否"),"是")) -> 否 | J130: =IF(LEN(A130)=3,"类",IF(LEN(A130)=5,"款","项")) -> 项
A131: 2129899 | B131: 其他城乡社区支出 | C131: 4530 | D131: 2213 | E131: 2213 | F131: 0 | G131: =IFERROR((F131-C131)/C131,"") -> -1 | H131: =IFERROR(F131/D131,"") -> 0 | I131: =IF(LEN(A131)=3,"是",IF(B131<>"",IF(SUM(C131:F131)<>0,"是","否"),"是")) -> 是 | J131: =IF(LEN(A131)=3,"类",IF(LEN(A131)=5,"款","项")) -> 项
A132: 213 | B132: 八、农林水支出 | C132: 35 | D132: =D133+D138+D143+D148+D151+D156 -> 50 | E132: =E133+E138+E143+E148+E151+E156 -> 50 | F132: =F133+F138+F143+F148+F151+F156 -> 224 | G132: =IFERROR((F132-C132)/C132,"") -> 5.4 | H132: =IFERROR(F132/D132,"") -> 4.48 | I132: =IF(LEN(A132)=3,"是",IF(B132<>"",IF(SUM(C132:F132)<>0,"是","否"),"是")) -> 是 | J132: =IF(LEN(A132)=3,"类",IF(LEN(A132)=5,"款","项")) -> 类
A133: 21366 | B133: 大中型水库库区基金安排的支出 | C133: 35 | D133: =SUM(D134:D137) -> 50 | E133: =SUM(E134:E137) -> 50 | F133: =SUM(F134:F137) -> 224 | G133: =IFERROR((F133-C133)/C133,"") -> 5.4 | H133: =IFERROR(F133/D133,"") -> 4.48 | I133: =IF(LEN(A133)=3,"是",IF(B133<>"",IF(SUM(C133:F133)<>0,"是","否"),"是")) -> 是 | J133: =IF(LEN(A133)=3,"类",IF(LEN(A133)=5,"款","项")) -> 款
A134: 2136601 | B134: 基础设施建设和经济发展 | C134: 35 | D134: 50 | E134: 50 | F134: 224 | G134: =IFERROR((F134-C134)/C134,"") -> 5.4 | H134: =IFERROR(F134/D134,"") -> 4.48 | I134: =IF(LEN(A134)=3,"是",IF(B134<>"",IF(SUM(C134:F134)<>0,"是","否"),"是")) -> 是 | J134: =IF(LEN(A134)=3,"类",IF(LEN(A134)=5,"款","项")) -> 项
A135: 2136602 | B135: 解决移民遗留问题 | C135: 0 | F135: 0 | G135: =IFERROR((F135-C135)/C135,"") | H135: =IFERROR(F135/D135,"") | I135: =IF(LEN(A135)=3,"是",IF(B135<>"",IF(SUM(C135:F135)<>0,"是","否"),"是")) -> 否 | J135: =IF(LEN(A135)=3,"类",IF(LEN(A135)=5,"款","项")) -> 项
A136: 2136603 | B136: 库区防护工程维护 | C136: 0 | F136: 0 | G136: =IFERROR((F136-C136)/C136,"") | H136: =IFERROR(F136/D136,"") | I136: =IF(LEN(A136)=3,"是",IF(B136<>"",IF(SUM(C136:F136)<>0,"是","否"),"是")) -> 否 | J136: =IF(LEN(A136)=3,"类",IF(LEN(A136)=5,"款","项")) -> 项
A137: 2136699 | B137: 其他大中型水库库区基金支出 | C137: 0 | F137: 0 | G137: =IFERROR((F137-C137)/C137,"") | H137: =IFERROR(F137/D137,"") | I137: =IF(LEN(A137)=3,"是",IF(B137<>"",IF(SUM(C137:F137)<>0,"是","否"),"是")) -> 否 | J137: =IF(LEN(A137)=3,"类",IF(LEN(A137)=5,"款","项")) -> 项
A138: 21367 | B138: 三峡水库库区基金支出 | C138: 0 | F138: 0 | G138: =IFERROR((F138-C138)/C138,"") | H138: =IFERROR(F138/D138,"") | I138: =IF(LEN(A138)=3,"是",IF(B138<>"",IF(SUM(C138:F138)<>0,"是","否"),"是")) -> 否 | J138: =IF(LEN(A138)=3,"类",IF(LEN(A138)=5,"款","项")) -> 款
A139: 2136701 | B139: 基础设施建设和经济发展 | C139: 0 | F139: 0 | G139: =IFERROR((F139-C139)/C139,"") | H139: =IFERROR(F139/D139,"") | I139: =IF(LEN(A139)=3,"是",IF(B139<>"",IF(SUM(C139:F139)<>0,"是","否"),"是")) -> 否 | J139: =IF(LEN(A139)=3,"类",IF(LEN(A139)=5,"款","项")) -> 项
A140: 2136702 | B140: 解决移民遗留问题 | C140: 0 | F140: 0 | G140: =IFERROR((F140-C140)/C140,"") | H140: =IFERROR(F140/D140,"") | I140: =IF(LEN(A140)=3,"是",IF(B140<>"",IF(SUM(C140:F140)<>0,"是","否"),"是")) -> 否 | J140: =IF(LEN(A140)=3,"类",IF(LEN(A140)=5,"款","项")) -> 项
A141: 2136703 | B141: 库区维护和管理 | C141: 0 | F141: 0 | G141: =IFERROR((F141-C141)/C141,"") | H141: =IFERROR(F141/D141,"") | I141: =IF(LEN(A141)=3,"是",IF(B141<>"",IF(SUM(C141:F141)<>0,"是","否"),"是")) -> 否 | J141: =IF(LEN(A141)=3,"类",IF(LEN(A141)=5,"款","项")) -> 项
A142: 2136799 | B142: 其他三峡水库库区基金支出 | C142: 0 | F142: 0 | G142: =IFERROR((F142-C142)/C142,"") | H142: =IFERROR(F142/D142,"") | I142: =IF(LEN(A142)=3,"是",IF(B142<>"",IF(SUM(C142:F142)<>0,"是","否"),"是")) -> 否 | J142: =IF(LEN(A142)=3,"类",IF(LEN(A142)=5,"款","项")) -> 项
A143: 21369 | B143: 国家重大水利工程建设基金安排的支出 | C143: 0 | F143: 0 | G143: =IFERROR((F143-C143)/C143,"") | H143: =IFERROR(F143/D143,"") | I143: =IF(LEN(A143)=3,"是",IF(B143<>"",IF(SUM(C143:F143)<>0,"是","否"),"是")) -> 否 | J143: =IF(LEN(A143)=3,"类",IF(LEN(A143)=5,"款","项")) -> 款
A144: 2136901 | B144: 南水北调工程建设 | C144: 0 | F144: 0 | G144: =IFERROR((F144-C144)/C144,"") | H144: =IFERROR(F144/D144,"") | I144: =IF(LEN(A144)=3,"是",IF(B144<>"",IF(SUM(C144:F144)<>0,"是","否"),"是")) -> 否 | J144: =IF(LEN(A144)=3,"类",IF(LEN(A144)=5,"款","项")) -> 项
A145: 2136902 | B145: 三峡后续工作 | C145: 0 | F145: 0 | G145: =IFERROR((F145-C145)/C145,"") | H145: =IFERROR(F145/D145,"") | I145: =IF(LEN(A145)=3,"是",IF(B145<>"",IF(SUM(C145:F145)<>0,"是","否"),"是")) -> 否 | J145: =IF(LEN(A145)=3,"类",IF(LEN(A145)=5,"款","项")) -> 项
A146: 2136903 | B146: 地方重大水利工程建设 | C146: 0 | F146: 0 | G146: =IFERROR((F146-C146)/C146,"") | H146: =IFERROR(F146/D146,"") | I146: =IF(LEN(A146)=3,"是",IF(B146<>"",IF(SUM(C146:F146)<>0,"是","否"),"是")) -> 否 | J146: =IF(LEN(A146)=3,"类",IF(LEN(A146)=5,"款","项")) -> 项
... A209: 2149899 | B209: 其他交通运输支出 | C209: 0 | F209: 0 | G209: =IFERROR((F209-C209)/C209,"") | H209: =IFERROR(F209/D209,"") | I209: =IF(LEN(A209)=3,"是",IF(B209<>"",IF(SUM(C209:F209)<>0,"是","否"),"是")) -> 否 | J209: =IF(LEN(A209)=3,"类",IF(LEN(A209)=5,"款","项")) -> 项
A210: 215 | B210: 十、资源勘探工业信息等支出 | C210: 153 | D210: =D211+D214 -> 24 | E210: =E211+E214 -> 24 | F210: =F211+F214 -> 44 | G210: =IFERROR((F210-C210)/C210,"") -> -0.7124183 | H210: =IFERROR(F210/D210,"") -> 1.8333333 | I210: =IF(LEN(A210)=3,"是",IF(B210<>"",IF(SUM(C210:F210)<>0,"是","否"),"是")) -> 是 | J210: =IF(LEN(A210)=3,"类",IF(LEN(A210)=5,"款","项")) -> 类
A211: 21562 | B211: 农网还贷资金支出 | C211: 0 | F211: 0 | G211: =IFERROR((F211-C211)/C211,"") | H211: =IFERROR(F211/D211,"") | I211: =IF(LEN(A211)=3,"是",IF(B211<>"",IF(SUM(C211:F211)<>0,"是","否"),"是")) -> 否 | J211: =IF(LEN(A211)=3,"类",IF(LEN(A211)=5,"款","项")) -> 款
A212: 2156202 | B212: 地方农网还贷资金支出 | C212: 0 | F212: 0 | G212: =IFERROR((F212-C212)/C212,"") | H212: =IFERROR(F212/D212,"") | I212: =IF(LEN(A212)=3,"是",IF(B212<>"",IF(SUM(C212:F212)<>0,"是","否"),"是")) -> 否 | J212: =IF(LEN(A212)=3,"类",IF(LEN(A212)=5,"款","项")) -> 项
A213: 2156299 | B213: 其他农网还贷资金支出 | C213: 0 | F213: 0 | G213: =IFERROR((F213-C213)/C213,"") | H213: =IFERROR(F213/D213,"") | I213: =IF(LEN(A213)=3,"是",IF(B213<>"",IF(SUM(C213:F213)<>0,"是","否"),"是")) -> 否 | J213: =IF(LEN(A213)=3,"类",IF(LEN(A213)=5,"款","项")) -> 项
A214: 21598 | B214: 超长期特别国债安排的支出 | C214: 153 | D214: =SUM(D215:D218) -> 24 | E214: =SUM(E215:E218) -> 24 | F214: =SUM(F215:F218) -> 44 | G214: =IFERROR((F214-C214)/C214,"") -> -0.7124183 | H214: =IFERROR(F214/D214,"") -> 1.8333333 | I214: =IF(LEN(A214)=3,"是",IF(B214<>"",IF(SUM(C214:F214)<>0,"是","否"),"是")) -> 是 | J214: =IF(LEN(A214)=3,"类",IF(LEN(A214)=5,"款","项")) -> 款
A215: 2159801 | B215: 资源勘探开发 | C215: 0 | F215: 0 | G215: =IFERROR((F215-C215)/C215,"") | H215: =IFERROR(F215/D215,"") | I215: =IF(LEN(A215)=3,"是",IF(B215<>"",IF(SUM(C215:F215)<>0,"是","否"),"是")) -> 否 | J215: =IF(LEN(A215)=3,"类",IF(LEN(A215)=5,"款","项")) -> 项
A216: 2159802 | B216: 制造业 | C216: 153 | D216: 24 | E216: 24 | F216: 44 | G216: =IFERROR((F216-C216)/C216,"") -> -0.7124183 | H216: =IFERROR(F216/D216,"") -> 1.8333333 | I216: =IF(LEN(A216)=3,"是",IF(B216<>"",IF(SUM(C216:F216)<>0,"是","否"),"是")) -> 是 | J216: =IF(LEN(A216)=3,"类",IF(LEN(A216)=5,"款","项")) -> 项
A217: 2159803 | B217: 工业和信息产业 | C217: 0 | F217: 0 | G217: =IFERROR((F217-C217)/C217,"") | H217: =IFERROR(F217/D217,"") | I217: =IF(LEN(A217)=3,"是",IF(B217<>"",IF(SUM(C217:F217)<>0,"是","否"),"是")) -> 否 | J217: =IF(LEN(A217)=3,"类",IF(LEN(A217)=5,"款","项")) -> 项
A218: 2159899 | B218: 其他资源勘探工业信息等支出 | C218: 0 | F218: 0 | G218: =IFERROR((F218-C218)/C218,"") | H218: =IFERROR(F218/D218,"") | I218: =IF(LEN(A218)=3,"是",IF(B218<>"",IF(SUM(C218:F218)<>0,"是","否"),"是")) -> 否 | J218: =IF(LEN(A218)=3,"类",IF(LEN(A218)=5,"款","项")) -> 项
A219: 217 | B219: 十一、金融支出 | C219: 0 | G219: =IFERROR((F219-C219)/C219,"") | H219: =IFERROR(F219/D219,"") | I219: =IF(LEN(A219)=3,"是",IF(B219<>"",IF(SUM(C219:F219)<>0,"是","否"),"是")) -> 是 | J219: =IF(LEN(A219)=3,"类",IF(LEN(A219)=5,"款","项")) -> 类
A220: 21704 | B220: 金融调控支出 | C220: 0 | G220: =IFERROR((F220-C220)/C220,"") | H220: =IFERROR(F220/D220,"") | I220: =IF(LEN(A220)=3,"是",IF(B220<>"",IF(SUM(C220:F220)<>0,"是","否"),"是")) -> 否 | J220: =IF(LEN(A220)=3,"类",IF(LEN(A220)=5,"款","项")) -> 款
A221: 2170402 | B221: 中央特别国债经营基金支出 | C221: 0 | G221: =IFERROR((F221-C221)/C221,"") | H221: =IFERROR(F221/D221,"") | I221: =IF(LEN(A221)=3,"是",IF(B221<>"",IF(SUM(C221:F221)<>0,"是","否"),"是")) -> 否 | J221: =IF(LEN(A221)=3,"类",IF(LEN(A221)=5,"款","项")) -> 项
A222: 2170403 | B222: 中央特别国债经营基金财务支出 | C222: 0 | G222: =IFERROR((F222-C222)/C222,"") | H222: =IFERROR(F222/D222,"") | I222: =IF(LEN(A222)=3,"是",IF(B222<>"",IF(SUM(C222:F222)<>0,"是","否"),"是")) -> 否 | J222: =IF(LEN(A222)=3,"类",IF(LEN(A222)=5,"款","项")) -> 项
A223: 2170404 | B223: 中央金融机构注资特别国债支出 | C223: 0 | G223: =IFERROR((F223-C223)/C223,"") | H223: =IFERROR(F223/D223,"") | I223: =IF(LEN(A223)=3,"是",IF(B223<>"",IF(SUM(C223:F223)<>0,"是","否"),"是")) -> 否 | J223: =IF(LEN(A223)=3,"类",IF(LEN(A223)=5,"款","项")) -> 项
A224: 220 | B224: 十二、自然资源海洋气象等支出 | C224: 0 | F224: 0 | G224: =IFERROR((F224-C224)/C224,"") | H224: =IFERROR(F224/D224,"") | I224: =IF(LEN(A224)=3,"是",IF(B224<>"",IF(SUM(C224:F224)<>0,"是","否"),"是")) -> 是 | J224: =IF(LEN(A224)=3,"类",IF(LEN(A224)=5,"款","项")) -> 类
A225: 22006 | B225: 耕地保护考核奖惩基金支出 | C225: 0 | F225: 0 | G225: =IFERROR((F225-C225)/C225,"") | H225: =IFERROR(F225/D225,"") | I225: =IF(LEN(A225)=3,"是",IF(B225<>"",IF(SUM(C225:F225)<>0,"是","否"),"是")) -> 否 | J225: =IF(LEN(A225)=3,"类",IF(LEN(A225)=5,"款","项")) -> 款
...

Sheet 10
A1: 2025年丽江市国有资本经营预算收入执行情况表
A2: 表十 | F2: 单位：万元
A3: 项 目 | B3: 2024年决算数 | C3: 2025年 | E3: 比较
C4: 预算数 | D4: 执行数 | E4: 比2024年决算数增长% | F4: 完成2025年预算数的% | G4: 打印
A5: 利润收入 | B5: =SUM(B6:B24) -> 0 | C5: =SUM(C6:C24) -> 0 | E5: =IFERROR((D5-B5)/B5,"") | F5: =IFERROR(D5/C5,"") | G5: =IF(A5<>"",IF(SUM(B5:D5)<>0,"是","否"),"是") -> 否
A6: 电力企业利润收入 | B6: 0 | E6: =IFERROR((D6-B6)/B6,"") | F6: =IFERROR(D6/C6,"") | G6: =IF(A6<>"",IF(SUM(B6:D6)<>0,"是","否"),"是") -> 否
A7: 运输企业利润收入 | B7: 0 | E7: =IFERROR((D7-B7)/B7,"") | F7: =IFERROR(D7/C7,"") | G7: =IF(A7<>"",IF(SUM(B7:D7)<>0,"是","否"),"是") -> 否
A8: 投资服务企业利润收入 | B8: 0 | E8: =IFERROR((D8-B8)/B8,"") | F8: =IFERROR(D8/C8,"") | G8: =IF(A8<>"",IF(SUM(B8:D8)<>0,"是","否"),"是") -> 否
A9: 贸易企业利润收入 | B9: 0 | E9: =IFERROR((D9-B9)/B9,"") | F9: =IFERROR(D9/C9,"") | G9: =IF(A9<>"",IF(SUM(B9:D9)<>0,"是","否"),"是") -> 否
A10: 建筑施工企业利润收入 | B10: 0 | E10: =IFERROR((D10-B10)/B10,"") | F10: =IFERROR(D10/C10,"") | G10: =IF(A10<>"",IF(SUM(B10:D10)<>0,"是","否"),"是") -> 否
A11: 房地产企业利润收入 | B11: 0 | E11: =IFERROR((D11-B11)/B11,"") | F11: =IFERROR(D11/C11,"") | G11: =IF(A11<>"",IF(SUM(B11:D11)<>0,"是","否"),"是") -> 否
A12: 建材企业利润收入 | B12: 0 | E12: =IFERROR((D12-B12)/B12,"") | F12: =IFERROR(D12/C12,"") | G12: =IF(A12<>"",IF(SUM(B12:D12)<>0,"是","否"),"是") -> 否
A13: 医药企业利润收入 | B13: 0 | E13: =IFERROR((D13-B13)/B13,"") | F13: =IFERROR(D13/C13,"") | G13: =IF(A13<>"",IF(SUM(B13:D13)<>0,"是","否"),"是") -> 否
A14: 农林牧渔企业利润收入 | B14: 0 | E14: =IFERROR((D14-B14)/B14,"") | F14: =IFERROR(D14/C14,"") | G14: =IF(A14<>"",IF(SUM(B14:D14)<>0,"是","否"),"是") -> 否
A15: 军工企业利润收入 | B15: 0 | E15: =IFERROR((D15-B15)/B15,"") | F15: =IFERROR(D15/C15,"") | G15: =IF(A15<>"",IF(SUM(B15:D15)<>0,"是","否"),"是") -> 否
A16: 转制科研院所利润收入 | B16: 0 | E16: =IFERROR((D16-B16)/B16,"") | F16: =IFERROR(D16/C16,"") | G16: =IF(A16<>"",IF(SUM(B16:D16)<>0,"是","否"),"是") -> 否
A17: 地质勘查企业利润收入 | B17: 0 | E17: =IFERROR((D17-B17)/B17,"") | F17: =IFERROR(D17/C17,"") | G17: =IF(A17<>"",IF(SUM(B17:D17)<>0,"是","否"),"是") -> 否
... A24: 其他国有资本经营预算企业利润收入 | B24: 0 | E24: =IFERROR((D24-B24)/B24,"") | F24: =IFERROR(D24/C24,"") | G24: =IF(A24<>"",IF(SUM(B24:D24)<>0,"是","否"),"是") -> 否
A25: 股利、股息收入 | B25: =SUM(B26:B29) -> 6911 | C25: =SUM(C26:C29) -> 2000 | D25: =SUM(D26:D29) -> 3042 | E25: =IFERROR((D25-B25)/B25,"") -> -0.55983215 | F25: =IFERROR(D25/C25,"") -> 1.521 | G25: =IF(A25<>"",IF(SUM(B25:D25)<>0,"是","否"),"是") -> 是
A26: 国有控股公司股利、股息收入 | B26: 79 | D26: 99 | E26: =IFERROR((D26-B26)/B26,"") -> 0.25316456 | F26: =IFERROR(D26/C26,"") | G26: =IF(A26<>"",IF(SUM(B26:D26)<>0,"是","否"),"是") -> 是
A27: 国有参股公司股利、股息收入 | B27: 4921 | C27: 2000 | D27: 2943 | E27: =IFERROR((D27-B27)/B27,"") -> -0.40195082 | F27: =IFERROR(D27/C27,"") -> 1.4715 | G27: =IF(A27<>"",IF(SUM(B27:D27)<>0,"是","否"),"是") -> 是
A28: 金融企业股利、股息收入（国资预算） | B28: 0 | E28: =IFERROR((D28-B28)/B28,"") | F28: =IFERROR(D28/C28,"") | G28: =IF(A28<>"",IF(SUM(B28:D28)<>0,"是","否"),"是") -> 否
A29: 其他国有资本经营预算企业股利、股息收入 | B29: 1911 | E29: =IFERROR((D29-B29)/B29,"") -> -1 | F29: =IFERROR(D29/C29,"") | G29: =IF(A29<>"",IF(SUM(B29:D29)<>0,"是","否"),"是") -> 是
A30: 产权转让收入 | B30: 0 | C30: =SUM(C31:C33) -> 0 | E30: =IFERROR((D30-B30)/B30,"") | F30: =IFERROR(D30/C30,"") | G30: =IF(A30<>"",IF(SUM(B30:D30)<>0,"是","否"),"是") -> 否
A31: 国有股权、股份转让收入 | B31: 0 | E31: =IFERROR((D31-B31)/B31,"") | F31: =IFERROR(D31/C31,"") | G31: =IF(A31<>"",IF(SUM(B31:D31)<>0,"是","否"),"是") -> 否
A32: 国有独资企业产权转让收入 | B32: 0 | E32: =IFERROR((D32-B32)/B32,"") | F32: =IFERROR(D32/C32,"") | G32: =IF(A32<>"",IF(SUM(B32:D32)<>0,"是","否"),"是") -> 否
A33: 其他国有资本经营预算企业产权转让收入 | B33: 0 | E33: =IFERROR((D33-B33)/B33,"") | F33: =IFERROR(D33/C33,"") | G33: =IF(A33<>"",IF(SUM(B33:D33)<>0,"是","否"),"是") -> 否
A34: 清算收入 | B34: 0 | C34: =SUM(C35:C37) -> 0 | E34: =IFERROR((D34-B34)/B34,"") | F34: =IFERROR(D34/C34,"") | G34: =IF(A34<>"",IF(SUM(B34:D34)<>0,"是","否"),"是") -> 否
A35: 国有股权、股份清算收入 | B35: 0 | E35: =IFERROR((D35-B35)/B35,"") | F35: =IFERROR(D35/C35,"") | G35: =IF(A35<>"",IF(SUM(B35:D35)<>0,"是","否"),"是") -> 否
A36: 国有独资企业清算收入 | B36: 0 | E36: =IFERROR((D36-B36)/B36,"") | F36: =IFERROR(D36/C36,"") | G36: =IF(A36<>"",IF(SUM(B36:D36)<>0,"是","否"),"是") -> 否
A37: 其他国有资本经营预算企业清算收入 | B37: 0 | E37: =IFERROR((D37-B37)/B37,"") | F37: =IFERROR(D37/C37,"") | G37: =IF(A37<>"",IF(SUM(B37:D37)<>0,"是","否"),"是") -> 否
A38: 其他国有资本经营预算收入 | B38: 0 | E38: =IFERROR((D38-B38)/B38,"") | F38: =IFERROR(D38/C38,"") | G38: =IF(A38<>"",IF(SUM(B38:D38)<>0,"是","否"),"是") -> 否
A39: 全市国有资本经营收入 | B39: =SUM(B5,B25,B30,B34,B38) -> 6911 | C39: =SUM(C5,C25,C30,C34,C38) -> 2000 | D39: =SUM(D5,D25,D30,D34,D38) -> 3042 | E39: =IFERROR((D39-B39)/B39,"") -> -0.55983215 | F39: =IFERROR(D39/C39,"") -> 1.521 | G39: =IF(A39<>"",IF(SUM(B39:D39)<>0,"是","否"),"是") -> 是
A40: 转移性收入 | B40: 47 | C40: 47 | D40: 47 | E40: =IFERROR((D40-B40)/B40,"") -> 0 | F40: =IFERROR(D40/C40,"") -> 1 | G40: =IF(A40<>"",IF(SUM(B40:D40)<>0,"是","否"),"是") -> 是
A41: 上年结转 | B41: 79 | C41: 61 | D41: 61 | E41: =IFERROR((D41-B41)/B41,"") -> -0.2278481 | F41: =IFERROR(D41/C41,"") -> 1 | G41: =IF(A41<>"",IF(SUM(B41:D41)<>0,"是","否"),"是") -> 是
A42: 账务调整收入 | B42: 0 | E42: =IFERROR((D42-B42)/B42,"") | F42: =IFERROR(D42/C42,"") | G42: =IF(A42<>"",IF(SUM(B42:D42)<>0,"是","否"),"是") -> 否
A43: 各项收入合计 | B43: =SUM(B39:B42) -> 7037 | C43: =SUM(C39:C42) -> 2108 | D43: =SUM(D39:D42) -> 3150 | E43: =IFERROR((D43-B43)/B43,"") -> -0.55236607 | F43: =IFERROR(D43/C43,"") -> 1.4943074 | G43: =IF(A43<>"",IF(SUM(B43:D43)<>0,"是","否"),"是") -> 是

Sheet 11
A1: 2025年丽江市国有资本经营预算支出执行情况表
A2: 表十一 | F2: 单位：万元
A3: 项目 | B3: 2024年决算数 | C3: 2025年 | E3: 比较
C4: 预算数 | D4: 执行数 | E4: 比2024年决算数增长% | F4: 完成2025年预算数的% | G4: 打印
A5: 解决历史遗留问题及改革成本支出 | B5: =SUM(B6:B11) -> 916 | C5: =SUM(C6:C11) -> 380 | D5: =SUM(D6:D11) -> 271 | E5: =IFERROR((D5-B5)/B5,"") -> -0.70414847 | F5: =IFERROR(D5/C5,"") -> 0.71315789 | G5: =IF(A5<>"",IF(SUM(B5:D5)<>0,"是","否"),"是") -> 是
A6: “三供一业”移交补助支出 | B6: 0 | E6: =IFERROR((D6-B6)/B6,"") | F6: =IFERROR(D6/C6,"") | G6: =IF(A6<>"",IF(SUM(B6:D6)<>0,"是","否"),"是") -> 否
A7: 国有企业办职教幼教补助支出 | B7: 0 | E7: =IFERROR((D7-B7)/B7,"") | F7: =IFERROR(D7/C7,"") | G7: =IF(A7<>"",IF(SUM(B7:D7)<>0,"是","否"),"是") -> 否
A8: 国有企业退休人员社会化管理补助支出 | B8: 56 | C8: 108 | D8: 21 | E8: =IFERROR((D8-B8)/B8,"") -> -0.625 | F8: =IFERROR(D8/C8,"") -> 0.19444444 | G8: =IF(A8<>"",IF(SUM(B8:D8)<>0,"是","否"),"是") -> 是
A9: 国有企业改革成本支出 | B9: 0 | E9: =IFERROR((D9-B9)/B9,"") | F9: =IFERROR(D9/C9,"") | G9: =IF(A9<>"",IF(SUM(B9:D9)<>0,"是","否"),"是") -> 否
A10: 离休干部医药费补助支出 | B10: 0 | E10: =IFERROR((D10-B10)/B10,"") | F10: =IFERROR(D10/C10,"") | G10: =IF(A10<>"",IF(SUM(B10:D10)<>0,"是","否"),"是") -> 否
A11: 其他解决历史遗留问题及改革成本支出 | B11: 860 | C11: 272 | D11: 250 | E11: =IFERROR((D11-B11)/B11,"") -> -0.70930233 | F11: =IFERROR(D11/C11,"") -> 0.91911765 | G11: =IF(A11<>"",IF(SUM(B11:D11)<>0,"是","否"),"是") -> 是
A12: 国有企业资本金注入 | B12: =SUM(B13:B17) -> 405 | C12: =SUM(C13:C17) -> 0 | D12: =SUM(D13:D17) -> 0 | E12: =IFERROR((D12-B12)/B12,"") -> -1 | F12: =IFERROR(D12/C12,"") | G12: =IF(A12<>"",IF(SUM(B12:D12)<>0,"是","否"),"是") -> 是
A13: 国有经济结构调整支出 | B13: 0 | E13: =IFERROR((D13-B13)/B13,"") | F13: =IFERROR(D13/C13,"") | G13: =IF(A13<>"",IF(SUM(B13:D13)<>0,"是","否"),"是") -> 否
A14: 公益性设施投资支出 | B14: 0 | E14: =IFERROR((D14-B14)/B14,"") | F14: =IFERROR(D14/C14,"") | G14: =IF(A14<>"",IF(SUM(B14:D14)<>0,"是","否"),"是") -> 否
A15: 前瞻性战略性产业发展支出 | B15: 0 | E15: =IFERROR((D15-B15)/B15,"") | F15: =IFERROR(D15/C15,"") | G15: =IF(A15<>"",IF(SUM(B15:D15)<>0,"是","否"),"是") -> 否
A16: 生态环境保护支出 | B16: 0 | E16: =IFERROR((D16-B16)/B16,"") | F16: =IFERROR(D16/C16,"") | G16: =IF(A16<>"",IF(SUM(B16:D16)<>0,"是","否"),"是") -> 否
A17: 其他国有企业资本金注入 | B17: 405 | E17: =IFERROR((D17-B17)/B17,"") -> -1 | F17: =IFERROR(D17/C17,"") | G17: =IF(A17<>"",IF(SUM(B17:D17)<>0,"是","否"),"是") -> 是
A18: 国有企业政策性补贴 | B18: =SUM(B19:B19) -> 0 | C18: =SUM(C19:C19) -> 0 | E18: =IFERROR((D18-B18)/B18,"") | F18: =IFERROR(D18/C18,"") | G18: =IF(A18<>"",IF(SUM(B18:D18)<>0,"是","否"),"是") -> 否
A19: 国有企业政策性补贴（项） | B19: 0 | E19: =IFERROR((D19-B19)/B19,"") | F19: =IFERROR(D19/C19,"") | G19: =IF(A19<>"",IF(SUM(B19:D19)<>0,"是","否"),"是") -> 否
A20: 金融国有资本经营预算支出 | B20: =SUM(B21:B21) -> 0 | C20: =SUM(C21:C21) -> 0 | E20: =IFERROR((D20-B20)/B20,"") | F20: =IFERROR(D20/C20,"") | G20: =IF(A20<>"",IF(SUM(B20:D20)<>0,"是","否"),"是") -> 否
A21: 其他金融国有资本经营预算支出 | B21: 0 | E21: =IFERROR((D21-B21)/B21,"") | F21: =IFERROR(D21/C21,"") | G21: =IF(A21<>"",IF(SUM(B21:D21)<>0,"是","否"),"是") -> 否
A22: 其他国有资本经营预算支出 | B22: =SUM(B23:B23) -> 0 | C22: =SUM(C23:C23) -> 167 | D22: =SUM(D23:D23) -> 103 | E22: =IFERROR((D22-B22)/B22,"") | F22: =IFERROR(D22/C22,"") -> 0.61676647 | G22: =IF(A22<>"",IF(SUM(B22:D22)<>0,"是","否"),"是") -> 是
A23: 其他国有资本经营预算支出（项） | B23: 0 | C23: 167 | D23: 103 | E23: =IFERROR((D23-B23)/B23,"") | F23: =IFERROR(D23/C23,"") -> 0.61676647 | G23: =IF(A23<>"",IF(SUM(B23:D23)<>0,"是","否"),"是") -> 是
A24: 全市国有资本经营支出 | B24: =SUM(B5,B12,B18,B20,B22) -> 1321 | C24: =SUM(C5,C12,C18,C20,C22) -> 547 | D24: =SUM(D5,D12,D18,D20,D22) -> 374 | E24: =IFERROR((D24-B24)/B24,"") -> -0.71688115 | F24: =IFERROR(D24/C24,"") -> 0.68372943 | G24: =IF(A24<>"",IF(SUM(B24:D24)<>0,"是","否"),"是") -> 是
A25: 转移性支出 | B25: =SUM(B26:B27) -> 5655 | C25: =SUM(C26:C27) -> 1561 | D25: =SUM(D26:D27) -> 2716 | E25: =IFERROR((D25-B25)/B25,"") -> -0.51971706 | F25: =IFERROR(D25/C25,"") -> 1.7399103 | G25: =IF(A25<>"",IF(SUM(B25:D25)<>0,"是","否"),"是") -> 是
A26: 国有资本经营预算转移支付 | B26: 0 | E26: =IFERROR((D26-B26)/B26,"") | F26: =IFERROR(D26/C26,"") | G26: =IF(A26<>"",IF(SUM(B26:D26)<>0,"是","否"),"是") -> 否
A27: 调出资金 | B27: 5655 | C27: 1561 | D27: 2716 | E27: =IFERROR((D27-B27)/B27,"") -> -0.51971706 | F27: =IFERROR(D27/C27,"") -> 1.7399103 | G27: =IF(A27<>"",IF(SUM(B27:D27)<>0,"是","否"),"是") -> 是
A28: 结转下年 | B28: 61 | D28: 60 | E28: =IFERROR((D28-B28)/B28,"") -> -0.016393443 | F28: =IFERROR(D28/C28,"") | G28: =IF(A28<>"",IF(SUM(B28:D28)<>0,"是","否"),"是") -> 是
A29: 各项支出合计 | B29: =SUM(B24:B25,B28) -> 7037 | C29: =SUM(C24:C25,C28) -> 2108 | D29: =SUM(D24:D25,D28) -> 3150 | E29: =IFERROR((D29-B29)/B29,"") -> -0.55236607 | F29: =IFERROR(D29/C29,"") -> 1.4943074 | G29: =IF(A29<>"",IF(SUM(B29:D29)<>0,"是","否"),"是") -> 是

Sheet 12
A1: 2025年市本级国有资本经营预算收入执行情况表
A2: 表十二 | F2: 单位：万元
A3: 项 目 | B3: 2024年决算数 | C3: 2025年 | E3: 比较
C4: 预算数 | D4: 执行数 | E4: 比2024年决算数增长% | F4: 完成2025年预算数的% | G4: 打印
A5: 利润收入 | B5: =SUM(B6:B21) -> 0 | C5: =SUM(C6:C21) -> 0 | D5: =SUM(D6:D21) -> 0 | E5: =IFERROR((D5-B5)/B5,"") | F5: =IFERROR(D5/C5,"") | G5: =IF(A5<>"",IF(SUM(B5:D5)<>0,"是","否"),"是") -> 否
A6: 电力企业利润收入 | B6: 0 | E6: =IFERROR((D6-B6)/B6,"") | F6: =IFERROR(D6/C6,"") | G6: =IF(A6<>"",IF(SUM(B6:D6)<>0,"是","否"),"是") -> 否
A7: 运输企业利润收入 | B7: 0 | E7: =IFERROR((D7-B7)/B7,"") | F7: =IFERROR(D7/C7,"") | G7: =IF(A7<>"",IF(SUM(B7:D7)<>0,"是","否"),"是") -> 否
A8: 投资服务企业利润收入 | B8: 0 | E8: =IFERROR((D8-B8)/B8,"") | F8: =IFERROR(D8/C8,"") | G8: =IF(A8<>"",IF(SUM(B8:D8)<>0,"是","否"),"是") -> 否
A9: 贸易企业利润收入 | B9: 0 | E9: =IFERROR((D9-B9)/B9,"") | F9: =IFERROR(D9/C9,"") | G9: =IF(A9<>"",IF(SUM(B9:D9)<>0,"是","否"),"是") -> 否
A10: 建筑施工企业利润收入 | B10: 0 | E10: =IFERROR((D10-B10)/B10,"") | F10: =IFERROR(D10/C10,"") | G10: =IF(A10<>"",IF(SUM(B10:D10)<>0,"是","否"),"是") -> 否
A11: 农林牧渔企业利润收入 | B11: 0 | E11: =IFERROR((D11-B11)/B11,"") | F11: =IFERROR(D11/C11,"") | G11: =IF(A11<>"",IF(SUM(B11:D11)<>0,"是","否"),"是") -> 否
A12: 军工企业利润收入 | B12: 0 | E12: =IFERROR((D12-B12)/B12,"") | F12: =IFERROR(D12/C12,"") | G12: =IF(A12<>"",IF(SUM(B12:D12)<>0,"是","否"),"是") -> 否
A13: 转制科研院所利润收入 | B13: 0 | E13: =IFERROR((D13-B13)/B13,"") | F13: =IFERROR(D13/C13,"") | G13: =IF(A13<>"",IF(SUM(B13:D13)<>0,"是","否"),"是") -> 否
A14: 地质勘查企业利润收入 | B14: 0 | E14: =IFERROR((D14-B14)/B14,"") | F14: =IFERROR(D14/C14,"") | G14: =IF(A14<>"",IF(SUM(B14:D14)<>0,"是","否"),"是") -> 否
A15: 医药企业利润收入 | B15: 0 | E15: =IFERROR((D15-B15)/B15,"") | F15: =IFERROR(D15/C15,"") | G15: =IF(A15<>"",IF(SUM(B15:D15)<>0,"是","否"),"是") -> 否
A16: 卫生体育福利企业利润收入 | B16: 0 | E16: =IFERROR((D16-B16)/B16,"") | F16: =IFERROR(D16/C16,"") | G16: =IF(A16<>"",IF(SUM(B16:D16)<>0,"是","否"),"是") -> 否
A17: 教育文化广播企业利润收入 | B17: 0 | E17: =IFERROR((D17-B17)/B17,"") | F17: =IFERROR(D17/C17,"") | G17: =IF(A17<>"",IF(SUM(B17:D17)<>0,"是","否"),"是") -> 否
... A21: 其他国有资本经营预算企业利润收入 | B21: 0 | E21: =IFERROR((D21-B21)/B21,"") | F21: =IFERROR(D21/C21,"") | G21: =IF(A21<>"",IF(SUM(B21:D21)<>0,"是","否"),"是") -> 否
A22: 股利、股息收入 | B22: =SUM(B23:B24) -> 5000 | C22: =SUM(C23:C24) -> 2000 | D22: =SUM(D23:D24) -> 3042 | E22: =IFERROR((D22-B22)/B22,"") -> -0.3916 | F22: =IFERROR(D22/C22,"") -> 1.521 | G22: =IF(A22<>"",IF(SUM(B22:D22)<>0,"是","否"),"是") -> 是
A23: 国有控股公司股利、股息收入 | B23: 79 | D23: 99 | E23: =IFERROR((D23-B23)/B23,"") -> 0.25316456 | F23: =IFERROR(D23/C23,"") | G23: =IF(A23<>"",IF(SUM(B23:D23)<>0,"是","否"),"是") -> 是
A24: 国有参股公司股利、股息收入 | B24: 4921 | C24: 2000 | D24: 2943 | E24: =IFERROR((D24-B24)/B24,"") -> -0.40195082 | F24: =IFERROR(D24/C24,"") -> 1.4715 | G24: =IF(A24<>"",IF(SUM(B24:D24)<>0,"是","否"),"是") -> 是
A25: 产权转让收入 | B25: =SUM(B26:B27) -> 0 | C25: =SUM(C26:C27) -> 0 | D25: =SUM(D26:D27) -> 0 | E25: =IFERROR((D25-B25)/B25,"") | F25: =IFERROR(D25/C25,"") | G25: =IF(A25<>"",IF(SUM(B25:D25)<>0,"是","否"),"是") -> 否
A26: 国有股权、股份转让收入 | B26: 0 | E26: =IFERROR((D26-B26)/B26,"") | F26: =IFERROR(D26/C26,"") | G26: =IF(A26<>"",IF(SUM(B26:D26)<>0,"是","否"),"是") -> 否
A27: 国有独资企业产权转让收入 | B27: 0 | E27: =IFERROR((D27-B27)/B27,"") | F27: =IFERROR(D27/C27,"") | G27: =IF(A27<>"",IF(SUM(B27:D27)<>0,"是","否"),"是") -> 否
A28: 清算收入 | B28: =SUM(B29:B29) -> 0 | C28: =SUM(C29:C29) -> 0 | D28: =SUM(D29:D29) -> 0 | E28: =IFERROR((D28-B28)/B28,"") | F28: =IFERROR(D28/C28,"") | G28: =IF(A28<>"",IF(SUM(B28:D28)<>0,"是","否"),"是") -> 否
A29: 国有独资企业清算收入 | B29: 0 | E29: =IFERROR((D29-B29)/B29,"") | F29: =IFERROR(D29/C29,"") | G29: =IF(A29<>"",IF(SUM(B29:D29)<>0,"是","否"),"是") -> 否
A30: 其他国有资本经营预算收入 | B30: 0 | E30: =IFERROR((D30-B30)/B30,"") | F30: =IFERROR(D30/C30,"") | G30: =IF(A30<>"",IF(SUM(B30:D30)<>0,"是","否"),"是") -> 否
A31: 市本级国有资本经营收入 | B31: =SUM(B5,B22,B25,B28,B30) -> 5000 | C31: =SUM(C5,C22,C25,C28,C30) -> 2000 | D31: =SUM(D5,D22,D25,D28,D30) -> 3042 | E31: =IFERROR((D31-B31)/B31,"") -> -0.3916 | F31: =IFERROR(D31/C31,"") -> 1.521 | G31: =IF(A31<>"",IF(SUM(B31:D31)<>0,"是","否"),"是") -> 是
A32: 转移性收入 | B32: 47 | C32: 47 | D32: 47 | E32: =IFERROR((D32-B32)/B32,"") -> 0 | F32: =IFERROR(D32/C32,"") -> 1 | G32: =IF(A32<>"",IF(SUM(B32:D32)<>0,"是","否"),"是") -> 是
A33: 上年结转 | B33: 0 | E33: =IFERROR((D33-B33)/B33,"") | F33: =IFERROR(D33/C33,"") | G33: =IF(A33<>"",IF(SUM(B33:D33)<>0,"是","否"),"是") -> 否
A34: 账务调整收入 | B34: 0 | E34: =IFERROR((D34-B34)/B34,"") | F34: =IFERROR(D34/C34,"") | G34: =IF(A34<>"",IF(SUM(B34:D34)<>0,"是","否"),"是") -> 否
A35: 各项收入合计 | B35: =SUM(B31:B34) -> 5047 | C35: =SUM(C31:C34) -> 2047 | D35: =SUM(D31:D34) -> 3089 | E35: =IFERROR((D35-B35)/B35,"") -> -0.38795324 | F35: =IFERROR(D35/C35,"") -> 1.5090376 | G35: =IF(A35<>"",IF(SUM(B35:D35)<>0,"是","否"),"是") -> 是

Sheet 13
A1: 2025年市本级国有资本经营预算支出执行情况表
A2: 表十三 | F2: 单位：万元
A3: 项 目 | B3: 2024年决算数 | C3: 2025年 | E3: 比较
C4: 预算数 | D4: 执行数 | E4: 比2024年决算数增长% | F4: 完成2025年预算数的% | G4: 打印
A5: 解决历史遗留问题及改革成本支出 | B5: =SUM(B6:B7) -> 829 | C5: =SUM(C6:C7) -> 245 | D5: =SUM(D6:D7) -> 223 | E5: =IFERROR((D5-B5)/B5,"") -> -0.73100121 | F5: =IFERROR(D5/C5,"") -> 0.91020408 | G5: =IF(A5<>"",IF(SUM(B5:D5)<>0,"是","否"),"是") -> 是
A6: "三供一业"移交补助支出 | B6: 0 | E6: =IFERROR((D6-B6)/B6,"") | F6: =IFERROR(D6/C6,"") | G6: =IF(A6<>"",IF(SUM(B6:D6)<>0,"是","否"),"是") -> 否
A7: 其他解决历史遗留问题及改革成本支出 | B7: 829 | C7: 245 | D7: 223 | E7: =IFERROR((D7-B7)/B7,"") -> -0.73100121 | F7: =IFERROR(D7/C7,"") -> 0.91020408 | G7: =IF(A7<>"",IF(SUM(B7:D7)<>0,"是","否"),"是") -> 是
A8: 国有企业资本金注入 | B8: =SUM(B9:B10) -> 405 | C8: =SUM(C9:C10) -> 0 | D8: =SUM(D9:D10) -> 0 | E8: =IFERROR((D8-B8)/B8,"") -> -1 | F8: =IFERROR(D8/C8,"") | G8: =IF(A8<>"",IF(SUM(B8:D8)<>0,"是","否"),"是") -> 是
A9: 国有经济结构调整支出 | B9: 0 | E9: =IFERROR((D9-B9)/B9,"") | F9: =IFERROR(D9/C9,"") | G9: =IF(A9<>"",IF(SUM(B9:D9)<>0,"是","否"),"是") -> 否
A10: 其他国有企业资本金注入 | B10: 405 | E10: =IFERROR((D10-B10)/B10,"") -> -1 | F10: =IFERROR(D10/C10,"") | G10: =IF(A10<>"",IF(SUM(B10:D10)<>0,"是","否"),"是") -> 是
A11: 国有企业政策性补贴 | B11: =B12 -> 0 | C11: =C12 -> 0 | D11: =D12 -> 0 | E11: =IFERROR((D11-B11)/B11,"") | F11: =IFERROR(D11/C11,"") | G11: =IF(A11<>"",IF(SUM(B11:D11)<>0,"是","否"),"是") -> 否
A12: 国有企业政策性补贴（项） | B12: 0 | E12: =IFERROR((D12-B12)/B12,"") | F12: =IFERROR(D12/C12,"") | G12: =IF(A12<>"",IF(SUM(B12:D12)<>0,"是","否"),"是") -> 否
A13: 其他国有资本经营预算支出 | B13: =B14 -> 0 | C13: =C14 -> 167 | D13: =D14 -> 103 | E13: =IFERROR((D13-B13)/B13,"") | F13: =IFERROR(D13/C13,"") -> 0.61676647 | G13: =IF(A13<>"",IF(SUM(B13:D13)<>0,"是","否"),"是") -> 是
A14: 其他国有资本经营预算支出（项） | B14: 0 | C14: 167 | D14: 103 | E14: =IFERROR((D14-B14)/B14,"") | F14: =IFERROR(D14/C14,"") -> 0.61676647 | G14: =IF(A14<>"",IF(SUM(B14:D14)<>0,"是","否"),"是") -> 是
A15: 市本级国有资本经营支出 | B15: =B5+B8+B11+B13 -> 1234 | C15: =C5+C8+C11+C13 -> 412 | D15: =D5+D8+D11+D13 -> 326 | E15: =IFERROR((D15-B15)/B15,"") -> -0.73581848 | F15: =IFERROR(D15/C15,"") -> 0.79126214 | G15: =IF(A15<>"",IF(SUM(B15:D15)<>0,"是","否"),"是") -> 是
A16: 转移性支出 | B16: =SUM(B17:B18) -> 3813 | C16: =SUM(C17:C18) -> 1635 | D16: =SUM(D17:D18) -> 2763 | E16: =IFERROR((D16-B16)/B16,"") -> -0.27537372 | F16: =IFERROR(D16/C16,"") -> 1.6899083 | G16: =IF(A16<>"",IF(SUM(B16:D16)<>0,"是","否"),"是") -> 是
A17: 国有资本经营预算转移支付 | B17: 74 | C17: 74 | D17: 74 | E17: =IFERROR((D17-B17)/B17,"") -> 0 | F17: =IFERROR(D17/C17,"") -> 1 | G17: =IF(A17<>"",IF(SUM(B17:D17)<>0,"是","否"),"是") -> 是
A18: 调出资金 | B18: 3739 | C18: 1561 | D18: 2689 | E18: =IFERROR((D18-B18)/B18,"") -> -0.28082375 | F18: =IFERROR(D18/C18,"") -> 1.7226137 | G18: =IF(A18<>"",IF(SUM(B18:D18)<>0,"是","否"),"是") -> 是
A19: 结转下年 | B19: 0 | E19: =IFERROR((D19-B19)/B19,"") | F19: =IFERROR(D19/C19,"") | G19: =IF(A19<>"",IF(SUM(B19:D19)<>0,"是","否"),"是") -> 否
A20: 各项支出合计 | B20: =B15+B16+B19 -> 5047 | C20: =C15+C16+C19 -> 2047 | D20: =D15+D16+D19 -> 3089 | E20: =IFERROR((D20-B20)/B20,"") -> -0.38795324 | F20: =IFERROR(D20/C20,"") -> 1.5090376 | G20: =IF(A20<>"",IF(SUM(B20:D20)<>0,"是","否"),"是") -> 是

Sheet 14
A1: 2025年丽江市社会保险基金预算收入执行情况表
A2: 表十四 | F2: 单位：万元
A3: 项 目 | B3: 2024年决算数 | C3: 2025年 | E3: 比较
C4: 预算数 | D4: 执行数 | E4: 比2024年决算数增长% | F4: 完成2025年预算数的% | G4: 打印
A5: 一、企业职工基本养老保险基金收入 | B5: 0 | E5: =IFERROR((D5-B5)/B5,"") | F5: =IFERROR(D5/C5,"") | G5: =IF(A5<>"",IF(SUM(B5:D5)<>0,"是","否"),"是") -> 否
A6: 其中：保险费收入 | B6: 0 | E6: =IFERROR((D6-B6)/B6,"") | F6: =IFERROR(D6/C6,"") | G6: =IF(A6<>"",IF(SUM(B6:D6)<>0,"是","否"),"是") -> 否
A7: 利息收入 | B7: 0 | E7: =IFERROR((D7-B7)/B7,"") | F7: =IFERROR(D7/C7,"") | G7: =IF(A7<>"",IF(SUM(B7:D7)<>0,"是","否"),"是") -> 否
A8: 财政补贴收入 | B8: 0 | E8: =IFERROR((D8-B8)/B8,"") | F8: =IFERROR(D8/C8,"") | G8: =IF(A8<>"",IF(SUM(B8:D8)<>0,"是","否"),"是") -> 否
A9: 二、机关事业单位基本养老保险基金收入 | B9: 117263 | C9: 121773 | D9: 122397 | E9: =IFERROR((D9-B9)/B9,"") -> 0.043781926 | F9: =IFERROR(D9/C9,"") -> 1.0051243 | G9: =IF(A9<>"",IF(SUM(B9:D9)<>0,"是","否"),"是") -> 是
A10: 其中：保险费收入 | B10: 100263 | C10: 100073 | D10: 101419 | E10: =IFERROR((D10-B10)/B10,"") -> 0.011529677 | F10: =IFERROR(D10/C10,"") -> 1.0134502 | G10: =IF(A10<>"",IF(SUM(B10:D10)<>0,"是","否"),"是") -> 是
A11: 利息收入 | B11: 1732 | C11: 3514 | D11: 2941 | E11: =IFERROR((D11-B11)/B11,"") -> 0.69803695 | F11: =IFERROR(D11/C11,"") -> 0.83693796 | G11: =IF(A11<>"",IF(SUM(B11:D11)<>0,"是","否"),"是") -> 是
A12: 财政补贴收入 | B12: 13750 | C12: 17007 | D12: 16141 | E12: =IFERROR((D12-B12)/B12,"") -> 0.17389091 | F12: =IFERROR(D12/C12,"") -> 0.94907979 | G12: =IF(A12<>"",IF(SUM(B12:D12)<>0,"是","否"),"是") -> 是
A13: 三、失业保险基金收入 | E13: =IFERROR((D13-B13)/B13,"") | F13: =IFERROR(D13/C13,"") | G13: =IF(A13<>"",IF(SUM(B13:D13)<>0,"是","否"),"是") -> 否
A14: 其中：保险费收入 | B14: 0 | E14: =IFERROR((D14-B14)/B14,"") | F14: =IFERROR(D14/C14,"") | G14: =IF(A14<>"",IF(SUM(B14:D14)<>0,"是","否"),"是") -> 否
A15: 利息收入 | B15: 0 | E15: =IFERROR((D15-B15)/B15,"") | F15: =IFERROR(D15/C15,"") | G15: =IF(A15<>"",IF(SUM(B15:D15)<>0,"是","否"),"是") -> 否
A16: 财政补贴收入 | B16: 0 | E16: =IFERROR((D16-B16)/B16,"") | F16: =IFERROR(D16/C16,"") | G16: =IF(A16<>"",IF(SUM(B16:D16)<>0,"是","否"),"是") -> 否
A17: 四、城镇职工基本医疗保险基金收入 | B17: 96167 | C17: 102281 | D17: 106622 | E17: =IFERROR((D17-B17)/B17,"") -> 0.10871713 | F17: =IFERROR(D17/C17,"") -> 1.0424419 | G17: =IF(A17<>"",IF(SUM(B17:D17)<>0,"是","否"),"是") -> 是
A18: 其中：保险费收入 | B18: 92326 | C18: 95089 | D18: 96947 | E18: =IFERROR((D18-B18)/B18,"") -> 0.050050907 | F18: =IFERROR(D18/C18,"") -> 1.0195396 | G18: =IF(A18<>"",IF(SUM(B18:D18)<>0,"是","否"),"是") -> 是
A19: 利息收入 | B19: 1267 | C19: 6800 | D19: 6634 | E19: =IFERROR((D19-B19)/B19,"") -> 4.2359905 | F19: =IFERROR(D19/C19,"") -> 0.97558824 | G19: =IF(A19<>"",IF(SUM(B19:D19)<>0,"是","否"),"是") -> 是
A20: 财政补贴收入 | B20: 87 | C20: 5 | D20: 23 | E20: =IFERROR((D20-B20)/B20,"") -> -0.73563218 | F20: =IFERROR(D20/C20,"") -> 4.6 | G20: =IF(A20<>"",IF(SUM(B20:D20)<>0,"是","否"),"是") -> 是
A21: 五、工伤保险基金收入 | B21: 0 | E21: =IFERROR((D21-B21)/B21,"") | F21: =IFERROR(D21/C21,"") | G21: =IF(A21<>"",IF(SUM(B21:D21)<>0,"是","否"),"是") -> 否
A22: 其中：保险费收入 | B22: 0 | E22: =IFERROR((D22-B22)/B22,"") | F22: =IFERROR(D22/C22,"") | G22: =IF(A22<>"",IF(SUM(B22:D22)<>0,"是","否"),"是") -> 否
A23: 利息收入 | B23: 0 | E23: =IFERROR((D23-B23)/B23,"") | F23: =IFERROR(D23/C23,"") | G23: =IF(A23<>"",IF(SUM(B23:D23)<>0,"是","否"),"是") -> 否
A24: 财政补贴收入 | B24: 0 | E24: =IFERROR((D24-B24)/B24,"") | F24: =IFERROR(D24/C24,"") | G24: =IF(A24<>"",IF(SUM(B24:D24)<>0,"是","否"),"是") -> 否
A25: 六、城乡居民基本养老保险基金收入 | B25: 55537 | C25: 55554 | D25: 60463 | E25: =IFERROR((D25-B25)/B25,"") -> 0.088697625 | F25: =IFERROR(D25/C25,"") -> 1.0883645 | G25: =IF(A25<>"",IF(SUM(B25:D25)<>0,"是","否"),"是") -> 是
A26: 其中：保险费收入 | B26: 17486 | C26: 15946 | D26: 16885 | E26: =IFERROR((D26-B26)/B26,"") -> -0.034370353 | F26: =IFERROR(D26/C26,"") -> 1.0588862 | G26: =IF(A26<>"",IF(SUM(B26:D26)<>0,"是","否"),"是") -> 是
A27: 利息收入 | B27: 2870 | C27: 1228 | D27: 1458 | E27: =IFERROR((D27-B27)/B27,"") -> -0.49198606 | F27: =IFERROR(D27/C27,"") -> 1.1872964 | G27: =IF(A27<>"",IF(SUM(B27:D27)<>0,"是","否"),"是") -> 是
A28: 财政补贴收入 | B28: 30727 | C28: 35856 | D28: 36669 | E28: =IFERROR((D28-B28)/B28,"") -> 0.19338041 | F28: =IFERROR(D28/C28,"") -> 1.022674 | G28: =IF(A28<>"",IF(SUM(B28:D28)<>0,"是","否"),"是") -> 是
A29: 七、居民基本医疗保险基金收入 | B29: 115545 | C29: 114726 | D29: 114124 | E29: =IFERROR((D29-B29)/B29,"") -> -0.012298239 | F29: =IFERROR(D29/C29,"") -> 0.99475272 | G29: =IF(A29<>"",IF(SUM(B29:D29)<>0,"是","否"),"是") -> 是
A30: 其中：保险费收入 | B30: 40987 | C30: 42541 | D30: 41323 | E30: =IFERROR((D30-B30)/B30,"") -> 0.0081977212 | F30: =IFERROR(D30/C30,"") -> 0.9713688 | G30: =IF(A30<>"",IF(SUM(B30:D30)<>0,"是","否"),"是") -> 是
A31: 利息收入 | B31: 1347 | C31: 704 | D31: 868 | E31: =IFERROR((D31-B31)/B31,"") -> -0.35560505 | F31: =IFERROR(D31/C31,"") -> 1.2329545 | G31: =IF(A31<>"",IF(SUM(B31:D31)<>0,"是","否"),"是") -> 是
A32: 财政补贴收入 | B32: 68418 | C32: 70903 | D32: 70386 | E32: =IFERROR((D32-B32)/B32,"") -> 0.02876436 | F32: =IFERROR(D32/C32,"") -> 0.99270835 | G32: =IF(A32<>"",IF(SUM(B32:D32)<>0,"是","否"),"是") -> 是
A33: 收入小计 | B33: =B5+B9+B13+B17+B21+B25+B29 -> 384512 | C33: =C5+C9+C13+C17+C21+C25+C29 -> 394334 | D33: =D5+D9+D13+D17+D21+D25+D29 -> 403606 | E33: =IFERROR((D33-B33)/B33,"") -> 0.049657748 | F33: =IFERROR(D33/C33,"") -> 1.0235131 | G33: =IF(A33<>"",IF(SUM(B33:D33)<>0,"是","否"),"是") -> 是
A34: 其中：保险费收入 | B34: =B6+B10+B14+B18+B22+B26+B30 -> 251062 | C34: =C6+C10+C14+C18+C22+C26+C30 -> 253649 | D34: =D6+D10+D14+D18+D22+D26+D30 -> 256574 | E34: =IFERROR((D34-B34)/B34,"") -> 0.021954736 | F34: =IFERROR(D34/C34,"") -> 1.0115317 | G34: =IF(A34<>"",IF(SUM(B34:D34)<>0,"是","否"),"是") -> 是
A35: 利息收入 | B35: =B7+B11+B15+B19+B23+B27+B31 -> 7216 | C35: =C7+C11+C15+C19+C23+C27+C31 -> 12246 | D35: =D7+D11+D15+D19+D23+D27+D31 -> 11901 | E35: =IFERROR((D35-B35)/B35,"") -> 0.64925166 | F35: =IFERROR(D35/C35,"") -> 0.97182754 | G35: =IF(A35<>"",IF(SUM(B35:D35)<>0,"是","否"),"是") -> 是
A36: 财政补贴收入 | B36: =B8+B12+B16+B20+B24+B28+B32 -> 112982 | C36: =C8+C12+C16+C20+C24+C28+C32 -> 123771 | D36: =D8+D12+D16+D20+D24+D28+D32 -> 123219 | E36: =IFERROR((D36-B36)/B36,"") -> 0.090607353 | F36: =IFERROR(D36/C36,"") -> 0.99554015 | G36: =IF(A36<>"",IF(SUM(B36:D36)<>0,"是","否"),"是") -> 是
A37: 收入合计 | B37: =B33 -> 384512 | C37: =C33 -> 394334 | D37: =D33 -> 403606 | E37: =IFERROR((D37-B37)/B37,"") -> 0.049657748 | F37: =IFERROR(D37/C37,"") -> 1.0235131 | G37: =IF(A37<>"",IF(SUM(B37:D37)<>0,"是","否"),"是") -> 是

Sheet 15
A1: 2025年丽江市社会保险基金预算支出执行情况表
A2: 表十五 | F2: 单位：万元
A3: 项 目 | B3: 2024年决算数 | C3: 2025年 | E3: 比较
C4: 预算数 | D4: 执行数 | E4: 比2024年决算数增长% | F4: 完成2025年预算数的% | G4: 打印
A5: 一、企业职工基本养老保险基金支出 | E5: =IFERROR((D5-B5)/B5,"") | F5: =IFERROR(D5/C5,"") | G5: =IF(A5<>"",IF(SUM(B5:D5)<>0,"是","否"),"是") -> 否
A6: 其中：待遇支出 | E6: =IFERROR((D6-B6)/B6,"") | F6: =IFERROR(D6/C6,"") | G6: =IF(A6<>"",IF(SUM(B6:D6)<>0,"是","否"),"是") -> 否
A7: 二、机关事业单位基本养老保险基金支出 | B7: 114523 | C7: 123081 | D7: 124617 | E7: =IFERROR((D7-B7)/B7,"") -> 0.0881395 | F7: =IFERROR(D7/C7,"") -> 1.0124796 | G7: =IF(A7<>"",IF(SUM(B7:D7)<>0,"是","否"),"是") -> 是
A8: 其中：待遇支出 | B8: 114361 | C8: 122948 | D8: 124050 | E8: =IFERROR((D8-B8)/B8,"") -> 0.084722939 | F8: =IFERROR(D8/C8,"") -> 1.0089631 | G8: =IF(A8<>"",IF(SUM(B8:D8)<>0,"是","否"),"是") -> 是
A9: 三、失业保险基金支出 | E9: =IFERROR((D9-B9)/B9,"") | F9: =IFERROR(D9/C9,"") | G9: =IF(A9<>"",IF(SUM(B9:D9)<>0,"是","否"),"是") -> 否
A10: 其中：待遇支出 | E10: =IFERROR((D10-B10)/B10,"") | F10: =IFERROR(D10/C10,"") | G10: =IF(A10<>"",IF(SUM(B10:D10)<>0,"是","否"),"是") -> 否
A11: 四、城镇职工基本医疗保险基金支出 | B11: 81351 | C11: 85474 | D11: 79951 | E11: =IFERROR((D11-B11)/B11,"") -> -0.017209377 | F11: =IFERROR(D11/C11,"") -> 0.93538386 | G11: =IF(A11<>"",IF(SUM(B11:D11)<>0,"是","否"),"是") -> 是
A12: 其中：待遇支出 | B12: 79923 | C12: 83935 | D12: 78080 | E12: =IFERROR((D12-B12)/B12,"") -> -0.023059695 | F12: =IFERROR(D12/C12,"") -> 0.93024364 | G12: =IF(A12<>"",IF(SUM(B12:D12)<>0,"是","否"),"是") -> 是
A13: 五、工伤保险基金支出 | E13: =IFERROR((D13-B13)/B13,"") | F13: =IFERROR(D13/C13,"") | G13: =IF(A13<>"",IF(SUM(B13:D13)<>0,"是","否"),"是") -> 否
A14: 其中：待遇支出 | E14: =IFERROR((D14-B14)/B14,"") | F14: =IFERROR(D14/C14,"") | G14: =IF(A14<>"",IF(SUM(B14:D14)<>0,"是","否"),"是") -> 否
A15: 六、城乡居民基本养老保险基金支出 | B15: 35472 | C15: 40976 | D15: 42486 | E15: =IFERROR((D15-B15)/B15,"") -> 0.19773342 | F15: =IFERROR(D15/C15,"") -> 1.0368508 | G15: =IF(A15<>"",IF(SUM(B15:D15)<>0,"是","否"),"是") -> 是
A16: 其中：待遇支出 | B16: 35405 | C16: 40907 | D16: 42398 | E16: =IFERROR((D16-B16)/B16,"") -> 0.19751448 | F16: =IFERROR(D16/C16,"") -> 1.0364485 | G16: =IF(A16<>"",IF(SUM(B16:D16)<>0,"是","否"),"是") -> 是
A17: 七、居民基本医疗保险基金支出 | B17: 104925 | C17: 107211 | D17: 101954 | E17: =IFERROR((D17-B17)/B17,"") -> -0.028315463 | F17: =IFERROR(D17/C17,"") -> 0.95096585 | G17: =IF(A17<>"",IF(SUM(B17:D17)<>0,"是","否"),"是") -> 是
A18: 其中：待遇支出 | B18: 93608 | C18: 95865 | D18: 84341 | E18: =IFERROR((D18-B18)/B18,"") -> -0.098997949 | F18: =IFERROR(D18/C18,"") -> 0.87978929 | G18: =IF(A18<>"",IF(SUM(B18:D18)<>0,"是","否"),"是") -> 是
A19: 支出小计 | B19: =B5+B7+B9+B11+B13+B15+B17 -> 336271 | C19: =C5+C7+C9+C11+C13+C15+C17 -> 356742 | D19: =D5+D7+D9+D11+D13+D15+D17 -> 349008 | E19: =IFERROR((D19-B19)/B19,"") -> 0.037877188 | F19: =IFERROR(D19/C19,"") -> 0.97832047 | G19: =IF(A19<>"",IF(SUM(B19:D19)<>0,"是","否"),"是") -> 是
A20: 其中：社会保险待遇支出 | B20: =B6+B8+B10+B12+B14+B16+B18 -> 323297 | C20: =C6+C8+C10+C12+C14+C16+C18 -> 343655 | D20: =D6+D8+D10+D12+D14+D16+D18 -> 328869 | E20: =IFERROR((D20-B20)/B20,"") -> 0.017234926 | F20: =IFERROR(D20/C20,"") -> 0.95697429 | G20: =IF(A20<>"",IF(SUM(B20:D20)<>0,"是","否"),"是") -> 是
A21: 支出合计 | B21: =B19 -> 336271 | C21: =C19 -> 356742 | D21: =D19 -> 349008 | E21: =IFERROR((D21-B21)/B21,"") -> 0.037877188 | F21: =IFERROR(D21/C21,"") -> 0.97832047 | G21: =IF(A21<>"",IF(SUM(B21:D21)<>0,"是","否"),"是") -> 是

Sheet 16
A1: 2025年丽江市社会保险基金预算结余执行情况表
A2: 表十六 | F2: 单位：万元
A3: 项 目 | B3: 2024年决算数 | C3: 2025年 | E3: 比较
C4: 预算数 | D4: 执行数 | E4: 比2024年决算数增长% | F4: 完成2025年预算数的% | G4: 打印
A5: 一、企业职工基本养老保险基金本年收支结余 | E5: =IFERROR((D5-B5)/B5,"") | F5: =IFERROR(D5/C5,"") | G5: =IF(A5<>"",IF(SUM(B5:D5)<>0,"是","否"),"是") -> 否
A6: 企业职工基本养老保险基金年末滚存结余 | E6: =IFERROR((D6-B6)/B6,"") | F6: =IFERROR(D6/C6,"") | G6: =IF(A6<>"",IF(SUM(B6:D6)<>0,"是","否"),"是") -> 否
A7: 二、机关事业单位基本养老保险基金本年收支结余 | B7: 2740 | C7: -1307 | D7: -2220 | E7: =IFERROR((D7-B7)/B7,"") -> -1.810219 | F7: =IFERROR(D7/C7,"") -> 1.6985463 | G7: =IF(A7<>"",IF(SUM(B7:D7)<>0,"是","否"),"是") -> 是
A8: 机关事业单位基本养老保险基金年末滚存结余 | B8: 122986 | C8: 123479 | D8: 120766 | E8: =IFERROR((D8-B8)/B8,"") -> -0.018050835 | F8: =IFERROR(D8/C8,"") -> 0.97802865 | G8: =IF(A8<>"",IF(SUM(B8:D8)<>0,"是","否"),"是") -> 是
A9: 三、失业保险基金本年收支结余 | E9: =IFERROR((D9-B9)/B9,"") | F9: =IFERROR(D9/C9,"") | G9: =IF(A9<>"",IF(SUM(B9:D9)<>0,"是","否"),"是") -> 否
A10: 失业保险基金年末滚存结余 | E10: =IFERROR((D10-B10)/B10,"") | F10: =IFERROR(D10/C10,"") | G10: =IF(A10<>"",IF(SUM(B10:D10)<>0,"是","否"),"是") -> 否
A11: 四、城镇职工基本医疗保险基金本年收支结余 | B11: 14816 | C11: 16807 | D11: 26671 | E11: =IFERROR((D11-B11)/B11,"") -> 0.80014849 | F11: =IFERROR(D11/C11,"") -> 1.5868983 | G11: =IF(A11<>"",IF(SUM(B11:D11)<>0,"是","否"),"是") -> 是
A12: 城镇职工基本医疗保险基金年末滚存结余 | B12: 257151 | C12: 272658 | D12: 283822 | E12: =IFERROR((D12-B12)/B12,"") -> 0.10371727 | F12: =IFERROR(D12/C12,"") -> 1.0409451 | G12: =IF(A12<>"",IF(SUM(B12:D12)<>0,"是","否"),"是") -> 是
A13: 五、工伤保险基金本年收支结余 | E13: =IFERROR((D13-B13)/B13,"") | F13: =IFERROR(D13/C13,"") | G13: =IF(A13<>"",IF(SUM(B13:D13)<>0,"是","否"),"是") -> 否
A14: 工伤保险基金年末滚存结余 | E14: =IFERROR((D14-B14)/B14,"") | F14: =IFERROR(D14/C14,"") | G14: =IF(A14<>"",IF(SUM(B14:D14)<>0,"是","否"),"是") -> 否
A15: 六、城乡居民基本养老保险基金本年收支结余 | B15: 20065 | C15: 14577 | D15: 17977 | E15: =IFERROR((D15-B15)/B15,"") -> -0.1040618 | F15: =IFERROR(D15/C15,"") -> 1.2332442 | G15: =IF(A15<>"",IF(SUM(B15:D15)<>0,"是","否"),"是") -> 是
A16: 城乡居民基本养老保险基金年末滚存结余 | B16: 176747 | C16: 188423 | D16: 194724 | E16: =IFERROR((D16-B16)/B16,"") -> 0.10171035 | F16: =IFERROR(D16/C16,"") -> 1.0334407 | G16: =IF(A16<>"",IF(SUM(B16:D16)<>0,"是","否"),"是") -> 是
A17: 七、居民基本医疗保险基金本年收支结余 | B17: 10621 | C17: 7515 | D17: 12170 | E17: =IFERROR((D17-B17)/B17,"") -> 0.14584314 | F17: =IFERROR(D17/C17,"") -> 1.6194278 | G17: =IF(A17<>"",IF(SUM(B17:D17)<>0,"是","否"),"是") -> 是
A18: 居民基本医疗保险基金年末滚存结余 | B18: 91406 | C18: 93027 | D18: 103576 | E18: =IFERROR((D18-B18)/B18,"") -> 0.13314224 | F18: =IFERROR(D18/C18,"") -> 1.1133972 | G18: =IF(A18<>"",IF(SUM(B18:D18)<>0,"是","否"),"是") -> 是
A19: 本年收支结余 | B19: =B5+B7+B9+B11+B13+B15+B17 -> 48242 | C19: =C5+C7+C9+C11+C13+C15+C17 -> 37592 | D19: =D5+D7+D9+D11+D13+D15+D17 -> 54598 | E19: =IFERROR((D19-B19)/B19,"") -> 0.13175241 | F19: =IFERROR(D19/C19,"") -> 1.4523835 | G19: =IF(A19<>"",IF(SUM(B19:D19)<>0,"是","否"),"是") -> 是
A20: 年末滚存结余 | B20: =B6+B8+B10+B12+B14+B16+B18 -> 648290 | C20: =C6+C8+C10+C12+C14+C16+C18 -> 677587 | D20: =D6+D8+D10+D12+D14+D16+D18 -> 702888 | E20: =IFERROR((D20-B20)/B20,"") -> 0.084218482 | F20: =IFERROR(D20/C20,"") -> 1.0373399 | G20: =IF(A20<>"",IF(SUM(B20:D20)<>0,"是","否"),"是") -> 是

Sheet 17
A1: 2025年市本级社会保险基金预算收入执行情况表
A2: 表十七 | G2: 单位：万元
A3: 项 目 | B3: 2024年决算数 | C3: 2025年 | F3: 比较
C4: 预算数 | D4: 调整预算数 | E4: 执行数 | F4: 比2024年决算数增长% | G4: 完成2025年预算数的% | H4: 打印
A5: 一、企业职工基本养老保险基金收入 | F5: =IFERROR((E5-B5)/B5,"") | G5: =IFERROR(E5/C5,"") | H5: =IF(A5<>"",IF(SUM(B5:E5)<>0,"是","否"),"是") -> 否
A6: 其中：保险费收入 | F6: =IFERROR((E6-B6)/B6,"") | G6: =IFERROR(E6/C6,"") | H6: =IF(A6<>"",IF(SUM(B6:E6)<>0,"是","否"),"是") -> 否
A7: 利息收入 | F7: =IFERROR((E7-B7)/B7,"") | G7: =IFERROR(E7/C7,"") | H7: =IF(A7<>"",IF(SUM(B7:E7)<>0,"是","否"),"是") -> 否
A8: 财政补贴收入 | F8: =IFERROR((E8-B8)/B8,"") | G8: =IFERROR(E8/C8,"") | H8: =IF(A8<>"",IF(SUM(B8:E8)<>0,"是","否"),"是") -> 否
A9: 二、机关事业单位基本养老保险基金收入 | B9: 20828 | C9: 21223 | D9: 21223 | E9: 21523 | F9: =IFERROR((E9-B9)/B9,"") -> 0.033368542 | G9: =IFERROR(E9/C9,"") -> 1.0141356 | H9: =IF(A9<>"",IF(SUM(B9:E9)<>0,"是","否"),"是") -> 是
A10: 其中：保险费收入 | B10: 18166 | C10: 17987 | D10: 17987 | E10: 17910 | F10: =IFERROR((E10-B10)/B10,"") -> -0.01409226 | G10: =IFERROR(E10/C10,"") -> 0.99571913 | H10: =IF(A10<>"",IF(SUM(B10:E10)<>0,"是","否"),"是") -> 是
A11: 利息收入 | B11: 381 | C11: 1225 | D11: 1225 | E11: 1261 | F11: =IFERROR((E11-B11)/B11,"") -> 2.3097113 | G11: =IFERROR(E11/C11,"") -> 1.0293878 | H11: =IF(A11<>"",IF(SUM(B11:E11)<>0,"是","否"),"是") -> 是
A12: 财政补贴收入 | B12: 1875 | C12: 1685 | D12: 1685 | E12: 1801 | F12: =IFERROR((E12-B12)/B12,"") -> -0.039466667 | G12: =IFERROR(E12/C12,"") -> 1.0688427 | H12: =IF(A12<>"",IF(SUM(B12:E12)<>0,"是","否"),"是") -> 是
A13: 三、失业保险基金收入 | D13: 0 | F13: =IFERROR((E13-B13)/B13,"") | G13: =IFERROR(E13/C13,"") | H13: =IF(A13<>"",IF(SUM(B13:E13)<>0,"是","否"),"是") -> 否
A14: 其中：保险费收入 | D14: 0 | F14: =IFERROR((E14-B14)/B14,"") | G14: =IFERROR(E14/C14,"") | H14: =IF(A14<>"",IF(SUM(B14:E14)<>0,"是","否"),"是") -> 否
A15: 利息收入 | D15: 0 | F15: =IFERROR((E15-B15)/B15,"") | G15: =IFERROR(E15/C15,"") | H15: =IF(A15<>"",IF(SUM(B15:E15)<>0,"是","否"),"是") -> 否
A16: 财政补贴收入 | D16: 0 | F16: =IFERROR((E16-B16)/B16,"") | G16: =IFERROR(E16/C16,"") | H16: =IF(A16<>"",IF(SUM(B16:E16)<>0,"是","否"),"是") -> 否
A17: 四、城镇职工基本医疗保险基金收入 | B17: 96167 | C17: 102281 | D17: 102281 | E17: 106622 | F17: =IFERROR((E17-B17)/B17,"") -> 0.10871713 | G17: =IFERROR(E17/C17,"") -> 1.0424419 | H17: =IF(A17<>"",IF(SUM(B17:E17)<>0,"是","否"),"是") -> 是
A18: 其中：保险费收入 | B18: 92326 | C18: 95089 | D18: 95089 | E18: 96947 | F18: =IFERROR((E18-B18)/B18,"") -> 0.050050907 | G18: =IFERROR(E18/C18,"") -> 1.0195396 | H18: =IF(A18<>"",IF(SUM(B18:E18)<>0,"是","否"),"是") -> 是
A19: 利息收入 | B19: 1267 | C19: 6800 | D19: 6800 | E19: 6634 | F19: =IFERROR((E19-B19)/B19,"") -> 4.2359905 | G19: =IFERROR(E19/C19,"") -> 0.97558824 | H19: =IF(A19<>"",IF(SUM(B19:E19)<>0,"是","否"),"是") -> 是
A20: 财政补贴收入 | B20: 87 | C20: 5 | D20: 5 | E20: 23 | F20: =IFERROR((E20-B20)/B20,"") -> -0.73563218 | G20: =IFERROR(E20/C20,"") -> 4.6 | H20: =IF(A20<>"",IF(SUM(B20:E20)<>0,"是","否"),"是") -> 是
A21: 五、工伤保险基金收入 | D21: 0 | F21: =IFERROR((E21-B21)/B21,"") | G21: =IFERROR(E21/C21,"") | H21: =IF(A21<>"",IF(SUM(B21:E21)<>0,"是","否"),"是") -> 否
A22: 其中：保险费收入 | D22: 0 | F22: =IFERROR((E22-B22)/B22,"") | G22: =IFERROR(E22/C22,"") | H22: =IF(A22<>"",IF(SUM(B22:E22)<>0,"是","否"),"是") -> 否
A23: 利息收入 | D23: 0 | F23: =IFERROR((E23-B23)/B23,"") | G23: =IFERROR(E23/C23,"") | H23: =IF(A23<>"",IF(SUM(B23:E23)<>0,"是","否"),"是") -> 否
A24: 财政补贴收入 | D24: 0 | F24: =IFERROR((E24-B24)/B24,"") | G24: =IFERROR(E24/C24,"") | H24: =IF(A24<>"",IF(SUM(B24:E24)<>0,"是","否"),"是") -> 否
A25: 六、城乡居民基本养老保险基金收入 | B25: 55537 | C25: 55554 | D25: 56989 | E25: 60463 | F25: =IFERROR((E25-B25)/B25,"") -> 0.088697625 | G25: =IFERROR(E25/C25,"") -> 1.0883645 | H25: =IF(A25<>"",IF(SUM(B25:E25)<>0,"是","否"),"是") -> 是
A26: 其中：保险费收入 | B26: 17486 | C26: 15946 | D26: 14370 | E26: 16885 | F26: =IFERROR((E26-B26)/B26,"") -> -0.034370353 | G26: =IFERROR(E26/C26,"") -> 1.0588862 | H26: =IF(A26<>"",IF(SUM(B26:E26)<>0,"是","否"),"是") -> 是
A27: 利息收入 | B27: 2870 | C27: 1228 | D27: 1527 | E27: 1458 | F27: =IFERROR((E27-B27)/B27,"") -> -0.49198606 | G27: =IFERROR(E27/C27,"") -> 1.1872964 | H27: =IF(A27<>"",IF(SUM(B27:E27)<>0,"是","否"),"是") -> 是
A28: 财政补贴收入 | B28: 30727 | C28: 35856 | D28: 38549 | E28: 36669 | F28: =IFERROR((E28-B28)/B28,"") -> 0.19338041 | G28: =IFERROR(E28/C28,"") -> 1.022674 | H28: =IF(A28<>"",IF(SUM(B28:E28)<>0,"是","否"),"是") -> 是
A29: 七、居民基本医疗保险基金收入 | B29: 115545 | C29: 114726 | D29: 114726 | E29: 114124 | F29: =IFERROR((E29-B29)/B29,"") -> -0.012298239 | G29: =IFERROR(E29/C29,"") -> 0.99475272 | H29: =IF(A29<>"",IF(SUM(B29:E29)<>0,"是","否"),"是") -> 是
A30: 其中：保险费收入 | B30: 40987 | C30: 42541 | D30: 42541 | E30: 41323 | F30: =IFERROR((E30-B30)/B30,"") -> 0.0081977212 | G30: =IFERROR(E30/C30,"") -> 0.9713688 | H30: =IF(A30<>"",IF(SUM(B30:E30)<>0,"是","否"),"是") -> 是
A31: 利息收入 | B31: 1347 | C31: 704 | D31: 704 | E31: 868 | F31: =IFERROR((E31-B31)/B31,"") -> -0.35560505 | G31: =IFERROR(E31/C31,"") -> 1.2329545 | H31: =IF(A31<>"",IF(SUM(B31:E31)<>0,"是","否"),"是") -> 是
A32: 财政补贴收入 | B32: 68418 | C32: 70903 | D32: 70903 | E32: 70386 | F32: =IFERROR((E32-B32)/B32,"") -> 0.02876436 | G32: =IFERROR(E32/C32,"") -> 0.99270835 | H32: =IF(A32<>"",IF(SUM(B32:E32)<>0,"是","否"),"是") -> 是
